Workbook
Name Selected_Standard_Definitions: '2. Dimension Definition'!$4:$4
Name Additional_Custom_Dimensions: '2. Dimension Definition'!$51:$51

Sheet 0. Instructions
B1: Instructions
B2: How to use this template
B5: # | C5: Instruction
B6: 1 | C6: Navigate to the Task Type & Dimension Selection tab
B7: 2 | C7: In the Task Type & Dimension Selection tab, select all of the Task Types (e.g., SFT, RLHF, Rubrics) that are contained in your project as well as the Verticals associated (Languages, Experts, Code). The Standard Dimensions and Sub-Dimensions corresponding to those Task Types (e.g., Prompt - Feasibility) will populate automatically. Note: en_US or "Generalists" tasks are included in the Languages selection
B8: 3 | C8: For each Standard Dimension+Sub-Dimension in the Task Type & Dimension Selection tab, use the corresponding checkbox to indicate whether it is applicable to your project Note: Do not edit the "Late Addition" column unless you have already proceeded to step Tab:3 and made edits. Checking this column for late additions is vital to ensure your revisions on tab 3 do not become misaligned
B9: 4 | C9: Navigate to the Dimension Definition tab. The Selected Standard Dimensions section (row 4) is automatically populated with all of the Standard Dimension & Sub-Dimensions that you marked as applicable in the previous step, along with each Standard definitions of 1, 3. and 5 quality. Please add any error categories that you would like used as [Error Category] within any new dimensions you add
B10: 5 | C10: For each Standard Dimension & Sub-Dimension in the Dimension Definition tab, you have the opportunity to request a revision to the 1, 3, and/or 5 quality definitions.
B11: 6 | C11: Navigate within the Dimension Definition tab to the Additional Custom Dimensions section. Here you have the opportunity to add custom dimensions that are unique to your project / not already captuired in the standard dimensions.
B12: 7 | C12: Message [QC member TBD] to signal that you've finished completing the template
B13: 8 | C13: If QC or MLDG has feedback for the standards return to the 2.Dimension Definition tab to update the revised language to match shared understanding
B14: 9 | C14: In the PT & QC Sample Audit Alignment tab, complete at least five sample audits using the Output Rubric
B15: 10 | C15: Got a minute? Share your thoughts in our New Spec Process Survey and help us improve!
B18: # | C18: Additional Links & Videos
B19: 1 | C19: Spec Doc Template
B20: 2 | C20: Project Team How To - First 2 minutes are general basics - Next 6 minutes are walkthrough with example project
B21: 3 | C21: QC <> MLDG How To

Sheet 1. Task Type & Dimension Select
B1: Task Type & Dimension Selection
B2: Project Team Input
B4: Vertical | C4: Languages, Code | H4: =IFERROR(__xludf.DUMMYFUNCTION("unique(filter('A. Standard Dimensions & Rating'!B2:B1003,'A. Standard Dimensions & Rating'!B2:B1003<>""All""))"),"Agents") -> Agents | I4: =IFERROR(__xludf.DUMMYFUNCTION("unique(filter('A. Standard Dimensions & Rating'!A2:A1003,'A. Standard Dimensions & Rating'!A2:A1003<>""All""))"),"Code") -> Code
H5: =IFERROR(__xludf.DUMMYFUNCTION("""COMPUTED_VALUE"""),"Audio") -> Audio | I5: =IFERROR(__xludf.DUMMYFUNCTION("""COMPUTED_VALUE"""),"Experts") -> Experts
B6: Task Type(s) | C6: SFT | H6: =IFERROR(__xludf.DUMMYFUNCTION("""COMPUTED_VALUE"""),"Data_Science") -> Data_Science | I6: =IFERROR(__xludf.DUMMYFUNCTION("""COMPUTED_VALUE"""),"Languages") -> Languages
F7: Only select one | H7: =IFERROR(__xludf.DUMMYFUNCTION("""COMPUTED_VALUE"""),"MM_Image") -> MM_Image
B8: Task Type | C8: Dimension | D8: Sub-Dimension | E8: "5 out of 5" Definition | F8: Applicable? | G8: Late Addition? | H8: =IFERROR(__xludf.DUMMYFUNCTION("""COMPUTED_VALUE"""),"RLHF/Evals") -> RLHF/Evals
B9: =IFERROR(__xludf.DUMMYFUNCTION("iferror(FILTER( { 'A. Standard Dimensions & Rating'!B2:D1003, 'A. Standard Dimensions & Rating'!G2:G1003 }, ( ('A. Standard Dimensions & Rating'!A2:A1003=""All"") + ISNUMBER(MATCH('A. Standard Dimensions & Rating'!A2:A1003, IF(C4<>"""", SPLIT(C4, "", ""),"&" {""""}), 0)) ) * ( ('A. Standard Dimensions & Rating'!B2:B1003=""All"") + ISNUMBER(MATCH('A. Standard Dimensions & Rating'!B2:B1003, IF(C6<>"""", SPLIT(C6, "", ""), {""""}), 0)) ) ), """")"),"All") -> All | C9: =IFERROR(__xludf.DUMMYFUNCTION("""COMPUTED_VALUE"""),"Prompt") -> Prompt | D9: =IFERROR(__xludf.DUMMYFUNCTION("""COMPUTED_VALUE"""),"Unique Ground Truth") -> Unique Ground Truth | E9: =IFERROR(__xludf.DUMMYFUNCTION("""COMPUTED_VALUE"""),"- The prompt has a unique ground truth answer. All the experts on the subject would come to the same conclusion") -> - The prompt has a unique ground truth answer. All the experts on the subject would come to the same conclusion | F9: TRUE | G9: FALSE | H9: =IFERROR(__xludf.DUMMYFUNCTION("""COMPUTED_VALUE"""),"Rubrics") -> Rubrics
B10: =IFERROR(__xludf.DUMMYFUNCTION("""COMPUTED_VALUE"""),"All") -> All | C10: =IFERROR(__xludf.DUMMYFUNCTION("""COMPUTED_VALUE"""),"Prompt") -> Prompt | D10: =IFERROR(__xludf.DUMMYFUNCTION("""COMPUTED_VALUE"""),"Timelessness") -> Timelessness | E10: =IFERROR(__xludf.DUMMYFUNCTION("""COMPUTED_VALUE"""),"- The answer to the prompt is not time dependent") -> - The answer to the prompt is not time dependent | F10: FALSE | G10: FALSE | H10: =IFERROR(__xludf.DUMMYFUNCTION("""COMPUTED_VALUE"""),"SFT") -> SFT
B11: =IFERROR(__xludf.DUMMYFUNCTION("""COMPUTED_VALUE"""),"All") -> All | C11: =IFERROR(__xludf.DUMMYFUNCTION("""COMPUTED_VALUE"""),"Prompt") -> Prompt | D11: =IFERROR(__xludf.DUMMYFUNCTION("""COMPUTED_VALUE"""),"Prompt Clarity and Specificity / Unique Ground Truth") -> Prompt Clarity and Specificity / Unique Ground Truth | E11: =IFERROR(__xludf.DUMMYFUNCTION("""COMPUTED_VALUE"""),"- The prompt has a unique ground truth answer. Any variances in the GTFA are still equivalent (e.g., π vs. 3.14, IUPAC name vs. common name). All the experts on the subject would come to the same conclusion") -> - The prompt has a unique ground truth answer. Any variances in the GTFA are still equivalent (e.g., π vs. 3.14, IUPAC name vs. common name). All the experts on the subject would come to the same conclusion | F11: FALSE | G11: FALSE | H11: =IFERROR(__xludf.DUMMYFUNCTION("""COMPUTED_VALUE"""),"Tool_Use") -> Tool_Use
B12: =IFERROR(__xludf.DUMMYFUNCTION("""COMPUTED_VALUE"""),"All") -> All | C12: =IFERROR(__xludf.DUMMYFUNCTION("""COMPUTED_VALUE"""),"Prompt") -> Prompt | D12: =IFERROR(__xludf.DUMMYFUNCTION("""COMPUTED_VALUE"""),"Domain Relevance") -> Domain Relevance | E12: =IFERROR(__xludf.DUMMYFUNCTION("""COMPUTED_VALUE"""),"- The Prompt(s) are clearly related to the assigned domain.") -> - The Prompt(s) are clearly related to the assigned domain. | F12: FALSE | G12: FALSE | H12: =IFERROR(__xludf.DUMMYFUNCTION("""COMPUTED_VALUE"""),"Translation") -> Translation
B13: =IFERROR(__xludf.DUMMYFUNCTION("""COMPUTED_VALUE"""),"All") -> All | C13: =IFERROR(__xludf.DUMMYFUNCTION("""COMPUTED_VALUE"""),"Prompt") -> Prompt | D13: =IFERROR(__xludf.DUMMYFUNCTION("""COMPUTED_VALUE"""),"Category Relevance") -> Category Relevance | E13: =IFERROR(__xludf.DUMMYFUNCTION("""COMPUTED_VALUE"""),"- The Prompt clearly fits the assigned category and showcases subject expertise") -> - The Prompt clearly fits the assigned category and showcases subject expertise | F13: FALSE | G13: FALSE | H13: =IFERROR(__xludf.DUMMYFUNCTION("""COMPUTED_VALUE"""),"UI") -> UI
B14: =IFERROR(__xludf.DUMMYFUNCTION("""COMPUTED_VALUE"""),"All") -> All | C14: =IFERROR(__xludf.DUMMYFUNCTION("""COMPUTED_VALUE"""),"Prompt") -> Prompt | D14: =IFERROR(__xludf.DUMMYFUNCTION("""COMPUTED_VALUE"""),"Reasoning Requirement") -> Reasoning Requirement | E14: =IFERROR(__xludf.DUMMYFUNCTION("""COMPUTED_VALUE"""),"- The prompt requires reasoning in-line with the assigned domain/expertise level, beyond jsut simple recall") -> - The prompt requires reasoning in-line with the assigned domain/expertise level, beyond jsut simple recall | F14: FALSE | G14: FALSE
B15: =IFERROR(__xludf.DUMMYFUNCTION("""COMPUTED_VALUE"""),"All") -> All | C15: =IFERROR(__xludf.DUMMYFUNCTION("""COMPUTED_VALUE"""),"Prompt") -> Prompt | D15: =IFERROR(__xludf.DUMMYFUNCTION("""COMPUTED_VALUE"""),"Difficulty") -> Difficulty | E15: =IFERROR(__xludf.DUMMYFUNCTION("""COMPUTED_VALUE"""),"- The prompt perfectly matches the assigned difficulty level") -> - The prompt perfectly matches the assigned difficulty level | F15: FALSE | G15: FALSE
B16: =IFERROR(__xludf.DUMMYFUNCTION("""COMPUTED_VALUE"""),"All") -> All | C16: =IFERROR(__xludf.DUMMYFUNCTION("""COMPUTED_VALUE"""),"Prompt") -> Prompt | D16: =IFERROR(__xludf.DUMMYFUNCTION("""COMPUTED_VALUE"""),"Constraints") -> Constraints | E16: =IFERROR(__xludf.DUMMYFUNCTION("""COMPUTED_VALUE"""),"- Any constraints feel natural and are what a real user asking this question to a chatbot would want ") -> - Any constraints feel natural and are what a real user asking this question to a chatbot would want | F16: FALSE | G16: FALSE
B17: =IFERROR(__xludf.DUMMYFUNCTION("""COMPUTED_VALUE"""),"All") -> All | C17: =IFERROR(__xludf.DUMMYFUNCTION("""COMPUTED_VALUE"""),"Prompt") -> Prompt | D17: =IFERROR(__xludf.DUMMYFUNCTION("""COMPUTED_VALUE"""),"Prompt Validity") -> Prompt Validity | E17: =IFERROR(__xludf.DUMMYFUNCTION("""COMPUTED_VALUE"""),"- The task is marked correctly as invalid or valid.") -> - The task is marked correctly as invalid or valid. | F17: FALSE | G17: FALSE
B18: =IFERROR(__xludf.DUMMYFUNCTION("""COMPUTED_VALUE"""),"All") -> All | C18: =IFERROR(__xludf.DUMMYFUNCTION("""COMPUTED_VALUE"""),"All CB Generated Content") -> All CB Generated Content | D18: =IFERROR(__xludf.DUMMYFUNCTION("""COMPUTED_VALUE"""),"Unlisted Minor Errors") -> Unlisted Minor Errors | E18: =IFERROR(__xludf.DUMMYFUNCTION("""COMPUTED_VALUE"""),"- There are no unlisted errors that you feel degrade the quality of the task") -> - There are no unlisted errors that you feel degrade the quality of the task | F18: FALSE | G18: FALSE
B19: =IFERROR(__xludf.DUMMYFUNCTION("""COMPUTED_VALUE"""),"All") -> All | C19: =IFERROR(__xludf.DUMMYFUNCTION("""COMPUTED_VALUE"""),"All CB Generated Content") -> All CB Generated Content | D19: =IFERROR(__xludf.DUMMYFUNCTION("""COMPUTED_VALUE"""),"Un-auditable") -> Un-auditable | F19: FALSE | G19: FALSE
B20: =IFERROR(__xludf.DUMMYFUNCTION("""COMPUTED_VALUE"""),"SFT") -> SFT | C20: =IFERROR(__xludf.DUMMYFUNCTION("""COMPUTED_VALUE"""),"Prompt") -> Prompt | D20: =IFERROR(__xludf.DUMMYFUNCTION("""COMPUTED_VALUE"""),"Prompt Clarity and Specificity") -> Prompt Clarity and Specificity | E20: =IFERROR(__xludf.DUMMYFUNCTION("""COMPUTED_VALUE"""),"- There is little to no room for misinterpretation of the specific request - Prompt has a specific request that doesn't require more than one minor assumption to answer it") -> - There is little to no room for misinterpretation of the specific request - Prompt has a specific request that doesn't require more than one minor assumption to answer it | F20: TRUE | G20: FALSE
B21: =IFERROR(__xludf.DUMMYFUNCTION("""COMPUTED_VALUE"""),"SFT") -> SFT | C21: =IFERROR(__xludf.DUMMYFUNCTION("""COMPUTED_VALUE"""),"Prompt") -> Prompt | D21: =IFERROR(__xludf.DUMMYFUNCTION("""COMPUTED_VALUE"""),"Feasibility") -> Feasibility | E21: =IFERROR(__xludf.DUMMYFUNCTION("""COMPUTED_VALUE"""),"- The prompt is completely actionable by an LLM or chatbot - The prompt contains no conflicting instructions/statements ") -> - The prompt is completely actionable by an LLM or chatbot - The prompt contains no conflicting instructions/statements | F21: FALSE | G21: FALSE
B22: =IFERROR(__xludf.DUMMYFUNCTION("""COMPUTED_VALUE"""),"SFT") -> SFT | C22: =IFERROR(__xludf.DUMMYFUNCTION("""COMPUTED_VALUE"""),"Prompt") -> Prompt | D22: =IFERROR(__xludf.DUMMYFUNCTION("""COMPUTED_VALUE"""),"Multiturn: Conversational Flow") -> Multiturn: Conversational Flow | E22: =IFERROR(__xludf.DUMMYFUNCTION("""COMPUTED_VALUE"""),"- All follow-up prompts are grounded in the conversation and do not digress the conversation from the first turn of the prompt") -> - All follow-up prompts are grounded in the conversation and do not digress the conversation from the first turn of the prompt | F22: FALSE | G22: FALSE
B23: =IFERROR(__xludf.DUMMYFUNCTION("""COMPUTED_VALUE"""),"SFT") -> SFT | C23: =IFERROR(__xludf.DUMMYFUNCTION("""COMPUTED_VALUE"""),"Prompt") -> Prompt | D23: =IFERROR(__xludf.DUMMYFUNCTION("""COMPUTED_VALUE"""),"Prompt Category") -> Prompt Category | E23: =IFERROR(__xludf.DUMMYFUNCTION("""COMPUTED_VALUE"""),"- The prompt content matches the category selected") -> - The prompt content matches the category selected | F23: FALSE | G23: FALSE
B24: =IFERROR(__xludf.DUMMYFUNCTION("""COMPUTED_VALUE"""),"SFT") -> SFT | C24: =IFERROR(__xludf.DUMMYFUNCTION("""COMPUTED_VALUE"""),"Prompt") -> Prompt | D24: =IFERROR(__xludf.DUMMYFUNCTION("""COMPUTED_VALUE"""),"Contrived / Unnatural Prompts") -> Contrived / Unnatural Prompts | E24: =IFERROR(__xludf.DUMMYFUNCTION("""COMPUTED_VALUE"""),"- The prompt is neither contrived or unnatural") -> - The prompt is neither contrived or unnatural | F24: TRUE | G24: FALSE
B25: =IFERROR(__xludf.DUMMYFUNCTION("""COMPUTED_VALUE"""),"SFT") -> SFT | C25: =IFERROR(__xludf.DUMMYFUNCTION("""COMPUTED_VALUE"""),"Prompt") -> Prompt | D25: =IFERROR(__xludf.DUMMYFUNCTION("""COMPUTED_VALUE"""),"Prompt Ratability") -> Prompt Ratability | E25: =IFERROR(__xludf.DUMMYFUNCTION("""COMPUTED_VALUE"""),"- Prompt is correctly marked as rateable or ratable") -> - Prompt is correctly marked as rateable or ratable | F25: FALSE | G25: FALSE
B26: =IFERROR(__xludf.DUMMYFUNCTION("""COMPUTED_VALUE"""),"SFT") -> SFT | C26: =IFERROR(__xludf.DUMMYFUNCTION("""COMPUTED_VALUE"""),"Prompt") -> Prompt | D26: =IFERROR(__xludf.DUMMYFUNCTION("""COMPUTED_VALUE"""),"Prompt Localization") -> Prompt Localization | E26: =IFERROR(__xludf.DUMMYFUNCTION("""COMPUTED_VALUE"""),"- The prompt is appropriate given its intended locale") -> - The prompt is appropriate given its intended locale | F26: FALSE | G26: FALSE
B27: =IFERROR(__xludf.DUMMYFUNCTION("""COMPUTED_VALUE"""),"SFT") -> SFT | C27: =IFERROR(__xludf.DUMMYFUNCTION("""COMPUTED_VALUE"""),"Prompt") -> Prompt | D27: =IFERROR(__xludf.DUMMYFUNCTION("""COMPUTED_VALUE"""),"Code coherence with request") -> Code coherence with request | E27: =IFERROR(__xludf.DUMMYFUNCTION("""COMPUTED_VALUE"""),"- The code in the prompt is completely coherent with the request - The code in the prompt completely aligns with how it's described in the prompt's text") -> - The code in the prompt is completely coherent with the request - The code in the prompt completely aligns with how it's described in the prompt's text | F27: FALSE | G27: FALSE
B28: =IFERROR(__xludf.DUMMYFUNCTION("""COMPUTED_VALUE"""),"SFT") -> SFT | C28: =IFERROR(__xludf.DUMMYFUNCTION("""COMPUTED_VALUE"""),"Prompt") -> Prompt | D28: =IFERROR(__xludf.DUMMYFUNCTION("""COMPUTED_VALUE"""),"Prompt Coding Language") -> Prompt Coding Language | E28: =IFERROR(__xludf.DUMMYFUNCTION("""COMPUTED_VALUE"""),"- Prompts adhere to the specified coding language or allowed coding languages within the project.") -> - Prompts adhere to the specified coding language or allowed coding languages within the project. | F28: FALSE | G28: FALSE
B29: =IFERROR(__xludf.DUMMYFUNCTION("""COMPUTED_VALUE"""),"SFT") -> SFT | C29: =IFERROR(__xludf.DUMMYFUNCTION("""COMPUTED_VALUE"""),"Prompt") -> Prompt | D29: =IFERROR(__xludf.DUMMYFUNCTION("""COMPUTED_VALUE"""),"Truthfulness") -> Truthfulness | E29: =IFERROR(__xludf.DUMMYFUNCTION("""COMPUTED_VALUE"""),"- The prompt has no factual errors - The prompt has no misleading statements") -> - The prompt has no factual errors - The prompt has no misleading statements | F29: TRUE | G29: FALSE
B30: =IFERROR(__xludf.DUMMYFUNCTION("""COMPUTED_VALUE"""),"SFT") -> SFT | C30: =IFERROR(__xludf.DUMMYFUNCTION("""COMPUTED_VALUE"""),"Prompt") -> Prompt | D30: =IFERROR(__xludf.DUMMYFUNCTION("""COMPUTED_VALUE"""),"LaTeX Formatting") -> LaTeX Formatting | E30: =IFERROR(__xludf.DUMMYFUNCTION("""COMPUTED_VALUE"""),"- The prompt uses correct LaTeX formatting where required") -> - The prompt uses correct LaTeX formatting where required | F30: FALSE | G30: FALSE
B31: =IFERROR(__xludf.DUMMYFUNCTION("""COMPUTED_VALUE"""),"SFT") -> SFT | C31: =IFERROR(__xludf.DUMMYFUNCTION("""COMPUTED_VALUE"""),"Response") -> Response | D31: =IFERROR(__xludf.DUMMYFUNCTION("""COMPUTED_VALUE"""),"Accuracy") -> Accuracy | E31: =IFERROR(__xludf.DUMMYFUNCTION("""COMPUTED_VALUE"""),"- The response has no factual errors - The response has no misleading statements") -> - The response has no factual errors - The response has no misleading statements | F31: FALSE | G31: FALSE
B32: =IFERROR(__xludf.DUMMYFUNCTION("""COMPUTED_VALUE"""),"SFT") -> SFT | C32: =IFERROR(__xludf.DUMMYFUNCTION("""COMPUTED_VALUE"""),"Response") -> Response | D32: =IFERROR(__xludf.DUMMYFUNCTION("""COMPUTED_VALUE"""),"Instruction Following / Response Fulfillment") -> Instruction Following / Response Fulfillment | E32: =IFERROR(__xludf.DUMMYFUNCTION("""COMPUTED_VALUE"""),"- All explicit instructions are clearly followed - The response fully answers the question ") -> - All explicit instructions are clearly followed - The response fully answers the question | F32: FALSE | G32: FALSE
B33: =IFERROR(__xludf.DUMMYFUNCTION("""COMPUTED_VALUE"""),"SFT") -> SFT | C33: =IFERROR(__xludf.DUMMYFUNCTION("""COMPUTED_VALUE"""),"Response") -> Response | D33: =IFERROR(__xludf.DUMMYFUNCTION("""COMPUTED_VALUE"""),"Comparison to Original Model Response") -> Comparison to Original Model Response | E33: =IFERROR(__xludf.DUMMYFUNCTION("""COMPUTED_VALUE"""),"- The updated response would clearly perform better overall across quality dimensions") -> - The updated response would clearly perform better overall across quality dimensions | F33: FALSE | G33: FALSE
B34: =IFERROR(__xludf.DUMMYFUNCTION("""COMPUTED_VALUE"""),"SFT") -> SFT | C34: =IFERROR(__xludf.DUMMYFUNCTION("""COMPUTED_VALUE"""),"Response") -> Response | D34: =IFERROR(__xludf.DUMMYFUNCTION("""COMPUTED_VALUE"""),"Compilation") -> Compilation | E34: =IFERROR(__xludf.DUMMYFUNCTION("""COMPUTED_VALUE"""),"- Code runs perfectly without any errors or warnings") -> - Code runs perfectly without any errors or warnings | F34: FALSE | G34: FALSE
B35: =IFERROR(__xludf.DUMMYFUNCTION("""COMPUTED_VALUE"""),"SFT") -> SFT | C35: =IFERROR(__xludf.DUMMYFUNCTION("""COMPUTED_VALUE"""),"Response") -> Response | D35: =IFERROR(__xludf.DUMMYFUNCTION("""COMPUTED_VALUE"""),"Execution Output") -> Execution Output | E35: =IFERROR(__xludf.DUMMYFUNCTION("""COMPUTED_VALUE"""),"- Output perfectly aligns with the requirements of the prompt, including edge cases") -> - Output perfectly aligns with the requirements of the prompt, including edge cases | F35: FALSE | G35: FALSE
B36: =IFERROR(__xludf.DUMMYFUNCTION("""COMPUTED_VALUE"""),"SFT") -> SFT | C36: =IFERROR(__xludf.DUMMYFUNCTION("""COMPUTED_VALUE"""),"Response") -> Response | D36: =IFERROR(__xludf.DUMMYFUNCTION("""COMPUTED_VALUE"""),"Performance") -> Performance | E36: =IFERROR(__xludf.DUMMYFUNCTION("""COMPUTED_VALUE"""),"- The code implementation is well-optimized, utilizing efficient algorithms and data structures wherever possible") -> - The code implementation is well-optimized, utilizing efficient algorithms and data structures wherever possible | F36: FALSE | G36: FALSE
B37: =IFERROR(__xludf.DUMMYFUNCTION("""COMPUTED_VALUE"""),"SFT") -> SFT | C37: =IFERROR(__xludf.DUMMYFUNCTION("""COMPUTED_VALUE"""),"Response") -> Response | D37: =IFERROR(__xludf.DUMMYFUNCTION("""COMPUTED_VALUE"""),"Readability") -> Readability | E37: =IFERROR(__xludf.DUMMYFUNCTION("""COMPUTED_VALUE"""),"- The code is well organized and uses consistent formatting, making it highly readable - Variable/class/method names are meaningfully chosen and are reflective of their purpose") -> - The code is well organized and uses consistent formatting, making it highly readable - Variable/class/method names are meaningfully chosen and are reflective of their purpose | F37: FALSE | G37: FALSE
B38: =IFERROR(__xludf.DUMMYFUNCTION("""COMPUTED_VALUE"""),"SFT") -> SFT | C38: =IFERROR(__xludf.DUMMYFUNCTION("""COMPUTED_VALUE"""),"Response") -> Response | D38: =IFERROR(__xludf.DUMMYFUNCTION("""COMPUTED_VALUE"""),"Code Documentation") -> Code Documentation | E38: =IFERROR(__xludf.DUMMYFUNCTION("""COMPUTED_VALUE"""),"- All code is well documented and includes detailed comments (Documentation constitutes both code comments and docstrings)") -> - All code is well documented and includes detailed comments (Documentation constitutes both code comments and docstrings) | F38: FALSE | G38: FALSE
B39: =IFERROR(__xludf.DUMMYFUNCTION("""COMPUTED_VALUE"""),"SFT") -> SFT | C39: =IFERROR(__xludf.DUMMYFUNCTION("""COMPUTED_VALUE"""),"Response") -> Response | D39: =IFERROR(__xludf.DUMMYFUNCTION("""COMPUTED_VALUE"""),"Code Design") -> Code Design | E39: =IFERROR(__xludf.DUMMYFUNCTION("""COMPUTED_VALUE"""),"- Code implementation follows most of the design principles, making the code easy to maintain and extend down the line (Code design constitutes good programming practices such as modularity, separation of concerns, abstraction, etc)") -> - Code implementation follows most of the design principles, making the code easy to maintain and extend down the line (Code design constitutes good programming practices such as modularity, separation of concerns, abstraction, etc) | F39: FALSE | G39: FALSE
B40: =IFERROR(__xludf.DUMMYFUNCTION("""COMPUTED_VALUE"""),"SFT") -> SFT | C40: =IFERROR(__xludf.DUMMYFUNCTION("""COMPUTED_VALUE"""),"Response") -> Response | D40: =IFERROR(__xludf.DUMMYFUNCTION("""COMPUTED_VALUE"""),"Code Safety/Security") -> Code Safety/Security | E40: =IFERROR(__xludf.DUMMYFUNCTION("""COMPUTED_VALUE"""),"- The code implementation has no security or safety issues") -> - The code implementation has no security or safety issues | F40: FALSE | G40: FALSE
B41: =IFERROR(__xludf.DUMMYFUNCTION("""COMPUTED_VALUE"""),"SFT") -> SFT | C41: =IFERROR(__xludf.DUMMYFUNCTION("""COMPUTED_VALUE"""),"Response") -> Response | D41: =IFERROR(__xludf.DUMMYFUNCTION("""COMPUTED_VALUE"""),"Rewrite Requirements") -> Rewrite Requirements | E41: =IFERROR(__xludf.DUMMYFUNCTION("""COMPUTED_VALUE"""),"Re-write results in a perfect response that fulfills the objectives of the prompt and has perfect code compilation and correct output. - The re-written response should fully achieve the most recent prompt. - The re-written response should address any sec"&"ondary objectives implied by the prompt. - The re-written response should correct all errors (major or minor) - The re-written response should be coherent and logically connected to the prior conversation. - The re-written response should fulfill all the "&"dimensions for ""No Issues"" in the rating rubrics. (for rubrics problems) - The re-written response should follow the formatting specifications. - The code of the re-written response should contain enough comments. (when applicable) - The code of the re-"&"written response MUST run properly and be optimal and efficient. (when applicable)") -> Re-write results in a perfect response that fulfills the objectives of the prompt and has perfect code compilation and correct output. - The re-written response should fully achieve the most recent prompt. - The re-written response should address any secondary objectives implied by the prompt. - The re-written response should correct all errors (major or minor) - The re-written response should be coherent and logically connected to the prior conversation. - The re-written response should fulfill all the dimensions for "No Issues" in the rating rubrics. (for rubrics problems) - The re-written response should follow the formatting specifications. - The code of the re-written response should contain enough comments. (when applicable) - The code of the re-written response MUST run properly and be optimal and efficient. (when applicable) | F41: FALSE | G41: FALSE
B42: =IFERROR(__xludf.DUMMYFUNCTION("""COMPUTED_VALUE"""),"SFT") -> SFT | C42: =IFERROR(__xludf.DUMMYFUNCTION("""COMPUTED_VALUE"""),"Response") -> Response | D42: =IFERROR(__xludf.DUMMYFUNCTION("""COMPUTED_VALUE"""),"LaTeX Satisfaction") -> LaTeX Satisfaction | E42: =IFERROR(__xludf.DUMMYFUNCTION("""COMPUTED_VALUE"""),"- The response contains no LaTeX errors") -> - The response contains no LaTeX errors | F42: FALSE | G42: FALSE
B43: =IFERROR(__xludf.DUMMYFUNCTION("""COMPUTED_VALUE"""),"SFT") -> SFT | C43: =IFERROR(__xludf.DUMMYFUNCTION("""COMPUTED_VALUE"""),"All CB Generated Content") -> All CB Generated Content | D43: =IFERROR(__xludf.DUMMYFUNCTION("""COMPUTED_VALUE"""),"Native Fluency") -> Native Fluency | E43: =IFERROR(__xludf.DUMMYFUNCTION("""COMPUTED_VALUE"""),"- Native-level writing for specified language and locale.") -> - Native-level writing for specified language and locale. | F43: FALSE | G43: FALSE
B44: =IFERROR(__xludf.DUMMYFUNCTION("""COMPUTED_VALUE"""),"SFT") -> SFT | C44: =IFERROR(__xludf.DUMMYFUNCTION("""COMPUTED_VALUE"""),"All CB Generated Content") -> All CB Generated Content | D44: =IFERROR(__xludf.DUMMYFUNCTION("""COMPUTED_VALUE"""),"Spelling / Grammar / Formatting") -> Spelling / Grammar / Formatting | E44: =IFERROR(__xludf.DUMMYFUNCTION("""COMPUTED_VALUE"""),"- (5) There are no easily discernible errors") -> - (5) There are no easily discernible errors | F44: FALSE | G44: FALSE
B45: =IFERROR(__xludf.DUMMYFUNCTION("""COMPUTED_VALUE"""),"SFT") -> SFT | C45: =IFERROR(__xludf.DUMMYFUNCTION("""COMPUTED_VALUE"""),"All CB Generated Content") -> All CB Generated Content | D45: =IFERROR(__xludf.DUMMYFUNCTION("""COMPUTED_VALUE"""),"Repetitiveness / Relevance") -> Repetitiveness / Relevance | E45: =IFERROR(__xludf.DUMMYFUNCTION("""COMPUTED_VALUE"""),"- The content does not contain unnecessary repetition, having 2 or fewer sentences that express the same idea - The content contains 2 or fewer irrelevant sentences ") -> - The content does not contain unnecessary repetition, having 2 or fewer sentences that express the same idea - The content contains 2 or fewer irrelevant sentences | F45: FALSE | G45: FALSE
B46: =IFERROR(__xludf.DUMMYFUNCTION("""COMPUTED_VALUE"""),"SFT") -> SFT | C46: =IFERROR(__xludf.DUMMYFUNCTION("""COMPUTED_VALUE"""),"All CB Generated Content") -> All CB Generated Content | D46: =IFERROR(__xludf.DUMMYFUNCTION("""COMPUTED_VALUE"""),"Original Work") -> Original Work | E46: =IFERROR(__xludf.DUMMYFUNCTION("""COMPUTED_VALUE"""),"-[Non-Fail - Suspected LLM Cheating] - The content shows evidence of unsanctioned LLM usage or otherwise appears unnatural, but it is not obvious that an LLM was used to generate their work - The content does not contain clear or obvious evidence of LLM"&" usage - The content does not contain direct plagiarism without citation") -> -[Non-Fail - Suspected LLM Cheating] - The content shows evidence of unsanctioned LLM usage or otherwise appears unnatural, but it is not obvious that an LLM was used to generate their work - The content does not contain clear or obvious evidence of LLM usage - The content does not contain direct plagiarism without citation | F46: FALSE | G46: FALSE
B47: =IFERROR(__xludf.DUMMYFUNCTION("""COMPUTED_VALUE"""),"SFT") -> SFT | C47: =IFERROR(__xludf.DUMMYFUNCTION("""COMPUTED_VALUE"""),"All CB Generated Content") -> All CB Generated Content | D47: =IFERROR(__xludf.DUMMYFUNCTION("""COMPUTED_VALUE"""),"Harmful Content") -> Harmful Content | E47: =IFERROR(__xludf.DUMMYFUNCTION("""COMPUTED_VALUE"""),"- Content does not contain or ask about harmful content") -> - Content does not contain or ask about harmful content | F47: FALSE | G47: FALSE
B48: =IFERROR(__xludf.DUMMYFUNCTION("""COMPUTED_VALUE"""),"SFT") -> SFT | C48: =IFERROR(__xludf.DUMMYFUNCTION("""COMPUTED_VALUE"""),"Response") -> Response | D48: =IFERROR(__xludf.DUMMYFUNCTION("""COMPUTED_VALUE"""),"Missing Detail") -> Missing Detail | E48: =IFERROR(__xludf.DUMMYFUNCTION("""COMPUTED_VALUE"""),"- The response is clear, focused, and demonstrates a solid understanding of the topic, providing sufficient detail and nuance without overwhelming or distracting from the key points. ") -> - The response is clear, focused, and demonstrates a solid understanding of the topic, providing sufficient detail and nuance without overwhelming or distracting from the key points. | F48: FALSE | G48: FALSE
B49: =IFERROR(__xludf.DUMMYFUNCTION("""COMPUTED_VALUE"""),"SFT") -> SFT | C49: =IFERROR(__xludf.DUMMYFUNCTION("""COMPUTED_VALUE"""),"Core Dimensions") -> Core Dimensions | D49: =IFERROR(__xludf.DUMMYFUNCTION("""COMPUTED_VALUE"""),"Clarity Issues") -> Clarity Issues | E49: =IFERROR(__xludf.DUMMYFUNCTION("""COMPUTED_VALUE"""),"- The response is clear and easy to follow, with well-structured ideas and language that effectively communicates the intended message. ") -> - The response is clear and easy to follow, with well-structured ideas and language that effectively communicates the intended message. | F49: FALSE | G49: FALSE
B50: =IFERROR(__xludf.DUMMYFUNCTION("""COMPUTED_VALUE"""),"SFT") -> SFT | C50: =IFERROR(__xludf.DUMMYFUNCTION("""COMPUTED_VALUE"""),"Response") -> Response | D50: =IFERROR(__xludf.DUMMYFUNCTION("""COMPUTED_VALUE"""),"(Rewrite/SxS) Clearly Worse Than Model Response") -> (Rewrite/SxS) Clearly Worse Than Model Response | E50: =IFERROR(__xludf.DUMMYFUNCTION("""COMPUTED_VALUE"""),"- The updated response matches or exceeds the original model’s quality across all rubric dimensions, demonstrating clear improvement or consistency in relevance, clarity, and completeness. ") -> - The updated response matches or exceeds the original model’s quality across all rubric dimensions, demonstrating clear improvement or consistency in relevance, clarity, and completeness. | F50: FALSE | G50: FALSE
F51: TRUE | G51: FALSE
F52: TRUE | G52: FALSE
F53: TRUE | G53: FALSE
F54: TRUE | G54: FALSE
F55: TRUE | G55: FALSE
F56: TRUE | G56: FALSE
F57: TRUE | G57: FALSE
F58: TRUE | G58: FALSE
F59: TRUE | G59: FALSE
F60: TRUE | G60: FALSE
F61: TRUE | G61: FALSE
F62: TRUE | G62: FALSE
... F235: TRUE | G235: FALSE
F236: TRUE
F237: TRUE
F238: TRUE
F239: TRUE
F240: TRUE
F241: TRUE
F242: TRUE
F243: TRUE
F244: TRUE
F245: TRUE
F246: TRUE
F247: TRUE
... F1003: TRUE

Sheet 2. Dimension Definition
A1: Dimension Definition | E1: Link to Net New-- Custom Dimensions | F1: Something looking wrong? Link to Debugging / Common Errors
A2: Project Team Input
A4: Selected Standard Dimensions | D4: #'s | E4: input any needed context | F4: Expand to revise >> | G4: Please write as a standard to grade to, not as a note of applicability | H4: Expand to revise >> | J4: Expand to revise >>
A5: Task Type | B5: Dimension | C5: Sub-Dimension | D5: Order of Appearance in Rubric | E5: Additional Notes for Auditors | F5: 1- 2 (Standard) | G5: 1 - 2 (Revision) | H5: 3 - 4 (Standard) | I5: 3 - 4 (Revision) | J5: 5 (Standard) | K5: 5 (Revision) | L5: Revised & Needs Review
A6: =IFERROR(__xludf.DUMMYFUNCTION("IFERROR(QUERY('1. Task Type & Dimension Select'!B9:G1032, ""SELECT Col1, Col2, Col3 WHERE (Col5 = TRUE OR Col6 = TRUE) AND Col1 IS NOT NULL ORDER BY Col5 DESC, Col6 DESC"", 0), ""(no task type and/or dimensions selected in the previous step)"") "),"All") -> All | B6: =IFERROR(__xludf.DUMMYFUNCTION("""COMPUTED_VALUE"""),"Prompt") -> Prompt | C6: =IFERROR(__xludf.DUMMYFUNCTION("""COMPUTED_VALUE"""),"Unique Ground Truth") -> Unique Ground Truth | D6: 1 | F6: {=iferror(index('A. Standard Dimensions & Rating'!E:E,match(1,('A. Standard Dimensions & Rating'!$B:$B=$A6)*('A. Standard Dimensions & Rating'!$C:$C=$B6)*('A. Standard Dimensions & Rating'!$D:$D=$C6),0)),"")} -> Fail - Multiple Valid Answers] - The prompt can reasonably produce two or more different correct answers, and the prompt does not clearly indicate which answer is intended. | H6: [Non-Fail - Multiple Valid Answers] The prompt is ambiguous, but there is either: a leading interpretation that the majority of people would pick if polled, or there are two different valid interpretations where making a small, logically defensible assumption would clarify which was intended by the user. | J6: {=iferror(index('A. Standard Dimensions & Rating'!G:G,match(1,('A. Standard Dimensions & Rating'!$B:$B=$A6)*('A. Standard Dimensions & Rating'!$C:$C=$B6)*('A. Standard Dimensions & Rating'!$D:$D=$C6),0)),"")} -> - The prompt has a unique ground truth answer. All the experts on the subject would come to the same conclusion | L6: =if(len(A6)>0,if(len(CONCATENATE(G6,I6,K6))>0,true,false),"") -> FALSE
A7: =IFERROR(__xludf.DUMMYFUNCTION("""COMPUTED_VALUE"""),"SFT") -> SFT | B7: =IFERROR(__xludf.DUMMYFUNCTION("""COMPUTED_VALUE"""),"Prompt") -> Prompt | C7: =IFERROR(__xludf.DUMMYFUNCTION("""COMPUTED_VALUE"""),"Prompt Clarity and Specificity") -> Prompt Clarity and Specificity | D7: 1 | F7: {=iferror(index('A. Standard Dimensions & Rating'!E:E,match(1,('A. Standard Dimensions & Rating'!$B:$B=$A7)*('A. Standard Dimensions & Rating'!$C:$C=$B7)*('A. Standard Dimensions & Rating'!$D:$D=$C7),0)),"")} -> [Fail - Major Clarity / Specificity Issues] - It's not clear what is being asked, the prompt is extremely difficult to follow, or is overly vague; the user intent cannot be reasonably understood from the prompt. - Major details are missing that are needed to answer the prompt and cannot be reasonably assumed | H7: {=iferror(index('A. Standard Dimensions & Rating'!F:F,match(1,('A. Standard Dimensions & Rating'!$B:$B=$A7)*('A. Standard Dimensions & Rating'!$C:$C=$B7)*('A. Standard Dimensions & Rating'!$D:$D=$C7),0)),"")} -> [Non-Fail Minor Clarity / Specificity Issues] - It's mostly clear what is being asked but the request could reasonably be interpreted multiple ways | J7: {=iferror(index('A. Standard Dimensions & Rating'!G:G,match(1,('A. Standard Dimensions & Rating'!$B:$B=$A7)*('A. Standard Dimensions & Rating'!$C:$C=$B7)*('A. Standard Dimensions & Rating'!$D:$D=$C7),0)),"")} -> - There is little to no room for misinterpretation of the specific request - Prompt has a specific request that doesn't require more than one minor assumption to answer it | L7: =if(len(A7)>0,if(len(CONCATENATE(G7,I7,K7))>0,true,false),"") -> FALSE
A8: =IFERROR(__xludf.DUMMYFUNCTION("""COMPUTED_VALUE"""),"SFT") -> SFT | B8: =IFERROR(__xludf.DUMMYFUNCTION("""COMPUTED_VALUE"""),"Prompt") -> Prompt | C8: =IFERROR(__xludf.DUMMYFUNCTION("""COMPUTED_VALUE"""),"Contrived / Unnatural Prompts") -> Contrived / Unnatural Prompts | D8: 1 | E8: This should check for artificial difficulty vs. natural complexity. Contrived examples include: demanding exact timestamps ("Find the email from January 15th at 3:47 PM"), requiring arbitrary format constraints ("Respond in exactly 3 sentences using passive voice"), or asking the agent to do something no real employee would do ("Intentionally send an incorrect email to test error handling"). Natural difficulty comes from entity confusion, scattered information, conflicting data across services, and hidden root causes. Prompts written as step-by-step command lists ("First search emails, then check CRM…") should also be considered contrived. | F8: {=iferror(index('A. Standard Dimensions & Rating'!E:E,match(1,('A. Standard Dimensions & Rating'!$B:$B=$A8)*('A. Standard Dimensions & Rating'!$C:$C=$B8)*('A. Standard Dimensions & Rating'!$D:$D=$C8),0)),"")} -> [Fail - Contrived / Unnatural Prompt] - Prompt is contrived or otherwise unnatural note: prompts such as riddles that are intentionally constraints/details laden should not be considered contrived. | H8: {=iferror(index('A. Standard Dimensions & Rating'!F:F,match(1,('A. Standard Dimensions & Rating'!$B:$B=$A8)*('A. Standard Dimensions & Rating'!$C:$C=$B8)*('A. Standard Dimensions & Rating'!$D:$D=$C8),0)),"")} -> [Non-Fail - Somewhat Contrived / Unnatural Prompt] - Prompt is somewhat contrived or is somewhat unnatural note: prompts such as riddles that are intentionally constraints/details laden should not be considered contrived. | J8: {=iferror(index('A. Standard Dimensions & Rating'!G:G,match(1,('A. Standard Dimensions & Rating'!$B:$B=$A8)*('A. Standard Dimensions & Rating'!$C:$C=$B8)*('A. Standard Dimensions & Rating'!$D:$D=$C8),0)),"")} -> - The prompt is neither contrived or unnatural | L8: =if(len(A8)>0,if(len(CONCATENATE(G8,I8,K8))>0,true,false),"") -> FALSE
A9: =IFERROR(__xludf.DUMMYFUNCTION("""COMPUTED_VALUE"""),"SFT") -> SFT | B9: =IFERROR(__xludf.DUMMYFUNCTION("""COMPUTED_VALUE"""),"Prompt") -> Prompt | C9: =IFERROR(__xludf.DUMMYFUNCTION("""COMPUTED_VALUE"""),"Truthfulness") -> Truthfulness | D9: 1 | F9: {=iferror(index('A. Standard Dimensions & Rating'!E:E,match(1,('A. Standard Dimensions & Rating'!$B:$B=$A9)*('A. Standard Dimensions & Rating'!$C:$C=$B9)*('A. Standard Dimensions & Rating'!$D:$D=$C9),0)),"")} -> [Fail - Major Factual Errors] - The prompt contains 1 or more major factual errors [Fail - Minor Factual Errors] - The prompt contains 2 or more minor factual errors (e.g., statements irrelevant to the fulfillment of the prompt's request) | H9: {=iferror(index('A. Standard Dimensions & Rating'!F:F,match(1,('A. Standard Dimensions & Rating'!$B:$B=$A9)*('A. Standard Dimensions & Rating'!$C:$C=$B9)*('A. Standard Dimensions & Rating'!$D:$D=$C9),0)),"")} -> [Non-Fail - Minor Factual Errors] - The prompt contains 1 minor factual errors. | J9: {=iferror(index('A. Standard Dimensions & Rating'!G:G,match(1,('A. Standard Dimensions & Rating'!$B:$B=$A9)*('A. Standard Dimensions & Rating'!$C:$C=$B9)*('A. Standard Dimensions & Rating'!$D:$D=$C9),0)),"")} -> - The prompt has no factual errors - The prompt has no misleading statements | L9: =if(len(A9)>0,if(len(CONCATENATE(G9,I9,K9))>0,true,false),"") -> FALSE
D10: 1 | F10: {=iferror(index('A. Standard Dimensions & Rating'!E:E,match(1,('A. Standard Dimensions & Rating'!$B:$B=$A10)*('A. Standard Dimensions & Rating'!$C:$C=$B10)*('A. Standard Dimensions & Rating'!$D:$D=$C10),0)),"")} | H10: {=iferror(index('A. Standard Dimensions & Rating'!F:F,match(1,('A. Standard Dimensions & Rating'!$B:$B=$A10)*('A. Standard Dimensions & Rating'!$C:$C=$B10)*('A. Standard Dimensions & Rating'!$D:$D=$C10),0)),"")} | J10: {=iferror(index('A. Standard Dimensions & Rating'!G:G,match(1,('A. Standard Dimensions & Rating'!$B:$B=$A10)*('A. Standard Dimensions & Rating'!$C:$C=$B10)*('A. Standard Dimensions & Rating'!$D:$D=$C10),0)),"")} | L10: =if(len(A10)>0,if(len(CONCATENATE(G10,I10,K10))>0,true,false),"")
D11: 1 | F11: {=iferror(index('A. Standard Dimensions & Rating'!E:E,match(1,('A. Standard Dimensions & Rating'!$B:$B=$A11)*('A. Standard Dimensions & Rating'!$C:$C=$B11)*('A. Standard Dimensions & Rating'!$D:$D=$C11),0)),"")} | H11: {=iferror(index('A. Standard Dimensions & Rating'!F:F,match(1,('A. Standard Dimensions & Rating'!$B:$B=$A11)*('A. Standard Dimensions & Rating'!$C:$C=$B11)*('A. Standard Dimensions & Rating'!$D:$D=$C11),0)),"")} | J11: {=iferror(index('A. Standard Dimensions & Rating'!G:G,match(1,('A. Standard Dimensions & Rating'!$B:$B=$A11)*('A. Standard Dimensions & Rating'!$C:$C=$B11)*('A. Standard Dimensions & Rating'!$D:$D=$C11),0)),"")} | L11: =if(len(A11)>0,if(len(CONCATENATE(G11,I11,K11))>0,true,false),"")
D12: 2 | F12: {=iferror(index('A. Standard Dimensions & Rating'!E:E,match(1,('A. Standard Dimensions & Rating'!$B:$B=$A12)*('A. Standard Dimensions & Rating'!$C:$C=$B12)*('A. Standard Dimensions & Rating'!$D:$D=$C12),0)),"")} | H12: {=iferror(index('A. Standard Dimensions & Rating'!F:F,match(1,('A. Standard Dimensions & Rating'!$B:$B=$A12)*('A. Standard Dimensions & Rating'!$C:$C=$B12)*('A. Standard Dimensions & Rating'!$D:$D=$C12),0)),"")} | J12: {=iferror(index('A. Standard Dimensions & Rating'!G:G,match(1,('A. Standard Dimensions & Rating'!$B:$B=$A12)*('A. Standard Dimensions & Rating'!$C:$C=$B12)*('A. Standard Dimensions & Rating'!$D:$D=$C12),0)),"")} | L12: =if(len(A12)>0,if(len(CONCATENATE(G12,I12,K12))>0,true,false),"")
D13: 2 | F13: {=iferror(index('A. Standard Dimensions & Rating'!E:E,match(1,('A. Standard Dimensions & Rating'!$B:$B=$A13)*('A. Standard Dimensions & Rating'!$C:$C=$B13)*('A. Standard Dimensions & Rating'!$D:$D=$C13),0)),"")} | H13: {=iferror(index('A. Standard Dimensions & Rating'!F:F,match(1,('A. Standard Dimensions & Rating'!$B:$B=$A13)*('A. Standard Dimensions & Rating'!$C:$C=$B13)*('A. Standard Dimensions & Rating'!$D:$D=$C13),0)),"")} | J13: {=iferror(index('A. Standard Dimensions & Rating'!G:G,match(1,('A. Standard Dimensions & Rating'!$B:$B=$A13)*('A. Standard Dimensions & Rating'!$C:$C=$B13)*('A. Standard Dimensions & Rating'!$D:$D=$C13),0)),"")} | L13: =if(len(A13)>0,if(len(CONCATENATE(G13,I13,K13))>0,true,false),"")
D14: 2 | F14: {=iferror(index('A. Standard Dimensions & Rating'!E:E,match(1,('A. Standard Dimensions & Rating'!$B:$B=$A14)*('A. Standard Dimensions & Rating'!$C:$C=$B14)*('A. Standard Dimensions & Rating'!$D:$D=$C14),0)),"")} | H14: {=iferror(index('A. Standard Dimensions & Rating'!F:F,match(1,('A. Standard Dimensions & Rating'!$B:$B=$A14)*('A. Standard Dimensions & Rating'!$C:$C=$B14)*('A. Standard Dimensions & Rating'!$D:$D=$C14),0)),"")} | J14: {=iferror(index('A. Standard Dimensions & Rating'!G:G,match(1,('A. Standard Dimensions & Rating'!$B:$B=$A14)*('A. Standard Dimensions & Rating'!$C:$C=$B14)*('A. Standard Dimensions & Rating'!$D:$D=$C14),0)),"")} | L14: =if(len(A14)>0,if(len(CONCATENATE(G14,I14,K14))>0,true,false),"")
D15: 3 | F15: {=iferror(index('A. Standard Dimensions & Rating'!E:E,match(1,('A. Standard Dimensions & Rating'!$B:$B=$A15)*('A. Standard Dimensions & Rating'!$C:$C=$B15)*('A. Standard Dimensions & Rating'!$D:$D=$C15),0)),"")} | H15: {=iferror(index('A. Standard Dimensions & Rating'!F:F,match(1,('A. Standard Dimensions & Rating'!$B:$B=$A15)*('A. Standard Dimensions & Rating'!$C:$C=$B15)*('A. Standard Dimensions & Rating'!$D:$D=$C15),0)),"")} | J15: {=iferror(index('A. Standard Dimensions & Rating'!G:G,match(1,('A. Standard Dimensions & Rating'!$B:$B=$A15)*('A. Standard Dimensions & Rating'!$C:$C=$B15)*('A. Standard Dimensions & Rating'!$D:$D=$C15),0)),"")} | L15: =if(len(A15)>0,if(len(CONCATENATE(G15,I15,K15))>0,true,false),"")
D16: 3 | F16: {=iferror(index('A. Standard Dimensions & Rating'!E:E,match(1,('A. Standard Dimensions & Rating'!$B:$B=$A16)*('A. Standard Dimensions & Rating'!$C:$C=$B16)*('A. Standard Dimensions & Rating'!$D:$D=$C16),0)),"")} | H16: {=iferror(index('A. Standard Dimensions & Rating'!F:F,match(1,('A. Standard Dimensions & Rating'!$B:$B=$A16)*('A. Standard Dimensions & Rating'!$C:$C=$B16)*('A. Standard Dimensions & Rating'!$D:$D=$C16),0)),"")} | J16: {=iferror(index('A. Standard Dimensions & Rating'!G:G,match(1,('A. Standard Dimensions & Rating'!$B:$B=$A16)*('A. Standard Dimensions & Rating'!$C:$C=$B16)*('A. Standard Dimensions & Rating'!$D:$D=$C16),0)),"")} | L16: =if(len(A16)>0,if(len(CONCATENATE(G16,I16,K16))>0,true,false),"")
D17: 3 | F17: {=iferror(index('A. Standard Dimensions & Rating'!E:E,match(1,('A. Standard Dimensions & Rating'!$B:$B=$A17)*('A. Standard Dimensions & Rating'!$C:$C=$B17)*('A. Standard Dimensions & Rating'!$D:$D=$C17),0)),"")} | H17: {=iferror(index('A. Standard Dimensions & Rating'!F:F,match(1,('A. Standard Dimensions & Rating'!$B:$B=$A17)*('A. Standard Dimensions & Rating'!$C:$C=$B17)*('A. Standard Dimensions & Rating'!$D:$D=$C17),0)),"")} | J17: {=iferror(index('A. Standard Dimensions & Rating'!G:G,match(1,('A. Standard Dimensions & Rating'!$B:$B=$A17)*('A. Standard Dimensions & Rating'!$C:$C=$B17)*('A. Standard Dimensions & Rating'!$D:$D=$C17),0)),"")} | L17: =if(len(A17)>0,if(len(CONCATENATE(G17,I17,K17))>0,true,false),"")
F18: {=iferror(index('A. Standard Dimensions & Rating'!E:E,match(1,('A. Standard Dimensions & Rating'!$B:$B=$A18)*('A. Standard Dimensions & Rating'!$C:$C=$B18)*('A. Standard Dimensions & Rating'!$D:$D=$C18),0)),"")} | H18: {=iferror(index('A. Standard Dimensions & Rating'!F:F,match(1,('A. Standard Dimensions & Rating'!$B:$B=$A18)*('A. Standard Dimensions & Rating'!$C:$C=$B18)*('A. Standard Dimensions & Rating'!$D:$D=$C18),0)),"")} | J18: {=iferror(index('A. Standard Dimensions & Rating'!G:G,match(1,('A. Standard Dimensions & Rating'!$B:$B=$A18)*('A. Standard Dimensions & Rating'!$C:$C=$B18)*('A. Standard Dimensions & Rating'!$D:$D=$C18),0)),"")} | L18: =if(len(A18)>0,if(len(CONCATENATE(G18,I18,K18))>0,true,false),"")
F19: {=iferror(index('A. Standard Dimensions & Rating'!E:E,match(1,('A. Standard Dimensions & Rating'!$B:$B=$A19)*('A. Standard Dimensions & Rating'!$C:$C=$B19)*('A. Standard Dimensions & Rating'!$D:$D=$C19),0)),"")} | H19: {=iferror(index('A. Standard Dimensions & Rating'!F:F,match(1,('A. Standard Dimensions & Rating'!$B:$B=$A19)*('A. Standard Dimensions & Rating'!$C:$C=$B19)*('A. Standard Dimensions & Rating'!$D:$D=$C19),0)),"")} | J19: {=iferror(index('A. Standard Dimensions & Rating'!G:G,match(1,('A. Standard Dimensions & Rating'!$B:$B=$A19)*('A. Standard Dimensions & Rating'!$C:$C=$B19)*('A. Standard Dimensions & Rating'!$D:$D=$C19),0)),"")} | L19: =if(len(A19)>0,if(len(CONCATENATE(G19,I19,K19))>0,true,false),"")
F20: {=iferror(index('A. Standard Dimensions & Rating'!E:E,match(1,('A. Standard Dimensions & Rating'!$B:$B=$A20)*('A. Standard Dimensions & Rating'!$C:$C=$B20)*('A. Standard Dimensions & Rating'!$D:$D=$C20),0)),"")} | H20: {=iferror(index('A. Standard Dimensions & Rating'!F:F,match(1,('A. Standard Dimensions & Rating'!$B:$B=$A20)*('A. Standard Dimensions & Rating'!$C:$C=$B20)*('A. Standard Dimensions & Rating'!$D:$D=$C20),0)),"")} | J20: {=iferror(index('A. Standard Dimensions & Rating'!G:G,match(1,('A. Standard Dimensions & Rating'!$B:$B=$A20)*('A. Standard Dimensions & Rating'!$C:$C=$B20)*('A. Standard Dimensions & Rating'!$D:$D=$C20),0)),"")} | L20: =if(len(A20)>0,if(len(CONCATENATE(G20,I20,K20))>0,true,false),"")
F21: {=iferror(index('A. Standard Dimensions & Rating'!E:E,match(1,('A. Standard Dimensions & Rating'!$B:$B=$A21)*('A. Standard Dimensions & Rating'!$C:$C=$B21)*('A. Standard Dimensions & Rating'!$D:$D=$C21),0)),"")} | H21: {=iferror(index('A. Standard Dimensions & Rating'!F:F,match(1,('A. Standard Dimensions & Rating'!$B:$B=$A21)*('A. Standard Dimensions & Rating'!$C:$C=$B21)*('A. Standard Dimensions & Rating'!$D:$D=$C21),0)),"")} | J21: {=iferror(index('A. Standard Dimensions & Rating'!G:G,match(1,('A. Standard Dimensions & Rating'!$B:$B=$A21)*('A. Standard Dimensions & Rating'!$C:$C=$B21)*('A. Standard Dimensions & Rating'!$D:$D=$C21),0)),"")} | L21: =if(len(A21)>0,if(len(CONCATENATE(G21,I21,K21))>0,true,false),"")
F22: {=iferror(index('A. Standard Dimensions & Rating'!E:E,match(1,('A. Standard Dimensions & Rating'!$B:$B=$A22)*('A. Standard Dimensions & Rating'!$C:$C=$B22)*('A. Standard Dimensions & Rating'!$D:$D=$C22),0)),"")} | H22: {=iferror(index('A. Standard Dimensions & Rating'!F:F,match(1,('A. Standard Dimensions & Rating'!$B:$B=$A22)*('A. Standard Dimensions & Rating'!$C:$C=$B22)*('A. Standard Dimensions & Rating'!$D:$D=$C22),0)),"")} | J22: {=iferror(index('A. Standard Dimensions & Rating'!G:G,match(1,('A. Standard Dimensions & Rating'!$B:$B=$A22)*('A. Standard Dimensions & Rating'!$C:$C=$B22)*('A. Standard Dimensions & Rating'!$D:$D=$C22),0)),"")} | L22: =if(len(A22)>0,if(len(CONCATENATE(G22,I22,K22))>0,true,false),"")
F23: {=iferror(index('A. Standard Dimensions & Rating'!E:E,match(1,('A. Standard Dimensions & Rating'!$B:$B=$A23)*('A. Standard Dimensions & Rating'!$C:$C=$B23)*('A. Standard Dimensions & Rating'!$D:$D=$C23),0)),"")} | H23: {=iferror(index('A. Standard Dimensions & Rating'!F:F,match(1,('A. Standard Dimensions & Rating'!$B:$B=$A23)*('A. Standard Dimensions & Rating'!$C:$C=$B23)*('A. Standard Dimensions & Rating'!$D:$D=$C23),0)),"")} | J23: {=iferror(index('A. Standard Dimensions & Rating'!G:G,match(1,('A. Standard Dimensions & Rating'!$B:$B=$A23)*('A. Standard Dimensions & Rating'!$C:$C=$B23)*('A. Standard Dimensions & Rating'!$D:$D=$C23),0)),"")} | L23: =if(len(A23)>0,if(len(CONCATENATE(G23,I23,K23))>0,true,false),"")
F24: {=iferror(index('A. Standard Dimensions & Rating'!E:E,match(1,('A. Standard Dimensions & Rating'!$B:$B=$A24)*('A. Standard Dimensions & Rating'!$C:$C=$B24)*('A. Standard Dimensions & Rating'!$D:$D=$C24),0)),"")} | H24: {=iferror(index('A. Standard Dimensions & Rating'!F:F,match(1,('A. Standard Dimensions & Rating'!$B:$B=$A24)*('A. Standard Dimensions & Rating'!$C:$C=$B24)*('A. Standard Dimensions & Rating'!$D:$D=$C24),0)),"")} | J24: {=iferror(index('A. Standard Dimensions & Rating'!G:G,match(1,('A. Standard Dimensions & Rating'!$B:$B=$A24)*('A. Standard Dimensions & Rating'!$C:$C=$B24)*('A. Standard Dimensions & Rating'!$D:$D=$C24),0)),"")} | L24: =if(len(A24)>0,if(len(CONCATENATE(G24,I24,K24))>0,true,false),"")
F25: {=iferror(index('A. Standard Dimensions & Rating'!E:E,match(1,('A. Standard Dimensions & Rating'!$B:$B=$A25)*('A. Standard Dimensions & Rating'!$C:$C=$B25)*('A. Standard Dimensions & Rating'!$D:$D=$C25),0)),"")} | H25: {=iferror(index('A. Standard Dimensions & Rating'!F:F,match(1,('A. Standard Dimensions & Rating'!$B:$B=$A25)*('A. Standard Dimensions & Rating'!$C:$C=$B25)*('A. Standard Dimensions & Rating'!$D:$D=$C25),0)),"")} | J25: {=iferror(index('A. Standard Dimensions & Rating'!G:G,match(1,('A. Standard Dimensions & Rating'!$B:$B=$A25)*('A. Standard Dimensions & Rating'!$C:$C=$B25)*('A. Standard Dimensions & Rating'!$D:$D=$C25),0)),"")} | L25: =if(len(A25)>0,if(len(CONCATENATE(G25,I25,K25))>0,true,false),"")
F26: {=iferror(index('A. Standard Dimensions & Rating'!E:E,match(1,('A. Standard Dimensions & Rating'!$B:$B=$A26)*('A. Standard Dimensions & Rating'!$C:$C=$B26)*('A. Standard Dimensions & Rating'!$D:$D=$C26),0)),"")} | H26: {=iferror(index('A. Standard Dimensions & Rating'!F:F,match(1,('A. Standard Dimensions & Rating'!$B:$B=$A26)*('A. Standard Dimensions & Rating'!$C:$C=$B26)*('A. Standard Dimensions & Rating'!$D:$D=$C26),0)),"")} | J26: {=iferror(index('A. Standard Dimensions & Rating'!G:G,match(1,('A. Standard Dimensions & Rating'!$B:$B=$A26)*('A. Standard Dimensions & Rating'!$C:$C=$B26)*('A. Standard Dimensions & Rating'!$D:$D=$C26),0)),"")} | L26: =if(len(A26)>0,if(len(CONCATENATE(G26,I26,K26))>0,true,false),"")
F27: {=iferror(index('A. Standard Dimensions & Rating'!E:E,match(1,('A. Standard Dimensions & Rating'!$B:$B=$A27)*('A. Standard Dimensions & Rating'!$C:$C=$B27)*('A. Standard Dimensions & Rating'!$D:$D=$C27),0)),"")} | H27: {=iferror(index('A. Standard Dimensions & Rating'!F:F,match(1,('A. Standard Dimensions & Rating'!$B:$B=$A27)*('A. Standard Dimensions & Rating'!$C:$C=$B27)*('A. Standard Dimensions & Rating'!$D:$D=$C27),0)),"")} | J27: {=iferror(index('A. Standard Dimensions & Rating'!G:G,match(1,('A. Standard Dimensions & Rating'!$B:$B=$A27)*('A. Standard Dimensions & Rating'!$C:$C=$B27)*('A. Standard Dimensions & Rating'!$D:$D=$C27),0)),"")} | L27: =if(len(A27)>0,if(len(CONCATENATE(G27,I27,K27))>0,true,false),"")
F28: {=iferror(index('A. Standard Dimensions & Rating'!E:E,match(1,('A. Standard Dimensions & Rating'!$B:$B=$A28)*('A. Standard Dimensions & Rating'!$C:$C=$B28)*('A. Standard Dimensions & Rating'!$D:$D=$C28),0)),"")} | H28: {=iferror(index('A. Standard Dimensions & Rating'!F:F,match(1,('A. Standard Dimensions & Rating'!$B:$B=$A28)*('A. Standard Dimensions & Rating'!$C:$C=$B28)*('A. Standard Dimensions & Rating'!$D:$D=$C28),0)),"")} | J28: {=iferror(index('A. Standard Dimensions & Rating'!G:G,match(1,('A. Standard Dimensions & Rating'!$B:$B=$A28)*('A. Standard Dimensions & Rating'!$C:$C=$B28)*('A. Standard Dimensions & Rating'!$D:$D=$C28),0)),"")} | L28: =if(len(A28)>0,if(len(CONCATENATE(G28,I28,K28))>0,true,false),"")
F29: {=iferror(index('A. Standard Dimensions & Rating'!E:E,match(1,('A. Standard Dimensions & Rating'!$B:$B=$A29)*('A. Standard Dimensions & Rating'!$C:$C=$B29)*('A. Standard Dimensions & Rating'!$D:$D=$C29),0)),"")} | H29: {=iferror(index('A. Standard Dimensions & Rating'!F:F,match(1,('A. Standard Dimensions & Rating'!$B:$B=$A29)*('A. Standard Dimensions & Rating'!$C:$C=$B29)*('A. Standard Dimensions & Rating'!$D:$D=$C29),0)),"")} | J29: {=iferror(index('A. Standard Dimensions & Rating'!G:G,match(1,('A. Standard Dimensions & Rating'!$B:$B=$A29)*('A. Standard Dimensions & Rating'!$C:$C=$B29)*('A. Standard Dimensions & Rating'!$D:$D=$C29),0)),"")} | L29: =if(len(A29)>0,if(len(CONCATENATE(G29,I29,K29))>0,true,false),"")
... F49: {=iferror(index('A. Standard Dimensions & Rating'!E:E,match(1,('A. Standard Dimensions & Rating'!$B:$B=$A49)*('A. Standard Dimensions & Rating'!$C:$C=$B49)*('A. Standard Dimensions & Rating'!$D:$D=$C49),0)),"")} | H49: {=iferror(index('A. Standard Dimensions & Rating'!F:F,match(1,('A. Standard Dimensions & Rating'!$B:$B=$A49)*('A. Standard Dimensions & Rating'!$C:$C=$B49)*('A. Standard Dimensions & Rating'!$D:$D=$C49),0)),"")} | J49: {=iferror(index('A. Standard Dimensions & Rating'!G:G,match(1,('A. Standard Dimensions & Rating'!$B:$B=$A49)*('A. Standard Dimensions & Rating'!$C:$C=$B49)*('A. Standard Dimensions & Rating'!$D:$D=$C49),0)),"")} | L49: =if(len(A49)>0,if(len(CONCATENATE(G49,I49,K49))>0,true,false),"")
F50: {=iferror(index('Original Copy of Standard Dimen'!E:E,match(1,('Original Copy of Standard Dimen'!$A:$A=$A50)*('Original Copy of Standard Dimen'!$B:$B=$B50)*('Original Copy of Standard Dimen'!$C:$C=$C50),0)),"")} | H50: {=iferror(index('Original Copy of Standard Dimen'!F:F,match(1,('Original Copy of Standard Dimen'!$A:$A=$A50)*('Original Copy of Standard Dimen'!$B:$B=$B50)*('Original Copy of Standard Dimen'!$C:$C=$C50),0)),"")} | J50: {=iferror(index('Original Copy of Standard Dimen'!G:G,match(1,('Original Copy of Standard Dimen'!$A:$A=$A50)*('Original Copy of Standard Dimen'!$B:$B=$B50)*('Original Copy of Standard Dimen'!$C:$C=$C50),0)),"")} | L50: =if(len(A50)>0,if(len(CONCATENATE(G50,I50,K50))>0,true,false),"")
A51: Additional Custom Dimensions
A52: Task Type | B52: Dimension | C52: Sub-Dimension | E52: Additional Notes for Auditors | F52: 1 (Custom) | H52: 3 (Custom) | J52: 5 (Custom) | L52: Complete
A53: RL | B53: Prompt | C53: Feasibility | D53: 1 | F53: [Fail - Prompt Impractical Request] - Prompt contains an impractical request that can't be answered by an LLM in a single response [Fail - Prompt Impossible Request] - Prompt has at least one request that can't be fulfilled at all [Fail - Prompt Conflicting Instructions] - Prompt gives instructions that conflict/contradict with itself that can't be fulfilled simultaneously [Fail - Prompt Feasibility with Tools] - Prompt contains an impractical or impossible request that can't be answered by the tools available or enabled for the task | H53: Non-Fail - Prompt Impractical Secondary Request] - There are multiple requests in the prompt and it's verging on being impractical for a model to answer it in a single response, but the core request of the prompt can be fulfilled with minor concessions on the secondary requests | J53: - The prompt is completely actionable by an LLM agent. - The prompt contains no conflicting instructions/statements | L53: =if(and(len(A53)>0,len(B53)>0,len(C53)>0,len(F53)>0),true,) -> TRUE
A54: RL | B54: Prompt | C54: Tool use and Cross-service requirement | D54: 2 | F54: [Fail - Tool Dependence] - The prompt can be answered without having to make any tool calls (either through basic reasoning or general knowledge) [Fail - Cross-service Requirement] - Prompt can be fully resolved within a single service (e.g., just email or just CRM), or only trivially touches a second service. | H54: N/A | J54: - Prompt requires investigation across 2+ services to answer correctly (e.g., facts needed are scattered and must be reconciled). | L54: =if(and(len(A54)>0,len(B54)>0,len(C54)>0,len(F54)>0),true,) -> TRUE
A55: RL | B55: Prompt | C55: Explicit Tool Mention | D55: 1 | F55: [Fail - Explicit Tool Mention] The prompt explicitly mentions a specific tool name The prompt unnaturally refers to an MCP server in an inorganic, technical manner “Use the Airbnb tool to…” (technical, unnatural) “I want to use Airbnb to find…” (general, natural) | H55: N/A | J55: - The prompt does not explicitly state the use of tools | L55: =if(and(len(A55)>0,len(B55)>0,len(C55)>0,len(F55)>0),true,) -> TRUE
A56: RL | B56: Prompt | C56: Investigation + Action | D56: 2 | F56: [Fail - Action Missing] - Prompt only asks for a summary/report/research with no required action. [Fail - Pre-solved] - Prompt tells agent the root cause and no investigation is needed. | H56: N/A | J56: Prompt clearly requires investigtion and at least one concrete action (email, ticket creation/update, booking, calendar scheduling, CRM update, etc.), and it logically follows from investigation. | L56: =if(and(len(A56)>0,len(B56)>0,len(C56)>0,len(F56)>0),true,) -> TRUE
A57: RL | B57: Prompt | C57: Coherence | D57: 2 | E57: An example of failing bolt-on requests: "Check weather in Miami, update my calendar for next week, email Marcus about Q3, and look up Seattle flights." Why it fails: Four unrelated requests stapled together. Each sub-request should causally flow from the same situation. How to tell if your prompt is "bolted": Remove any one sentence. If the rest still makes perfect sense without it, that sentence is a bolt-on | F57: [Fail - Bolt-on requests] - Contains unrelated bolt-on requests; removing a sentence doesn’t change the rest. | H57: N/A | J57: One cohesive situation; stacked asks all tie back to the same purpose. | L57: =if(and(len(A57)>0,len(B57)>0,len(C57)>0,len(F57)>0),true,) -> TRUE
A58: RL | B58: Universe | C58: Universe Feasibility (Data Exists) | D58: 3 | E58: Auditors should check the Universe Explorer or Sandbox to verify that key data needed for the prompt exists. | F58: [Fail - Missing Universe Data] - Task depends on key facts/entities/events that do not exist in the universe (or cannot be retrieved with available tools), making the task unsolvable. | H58: N/A | J58: All core facts required to solve the task exist in the universe and are retrievable via tools. | L58: =if(and(len(A58)>0,len(B58)>0,len(C58)>0,len(F58)>0),true,) -> TRUE
A59: RL | B59: Universe | C59: Cross-service Coherence | D59: 3 | E59: Auditors should refer to the changelog table in the sandbox to check changes that were made to the universe (if edits were made). | F59: [Fail - Incoherent Universe Changes] - Universe edits create contradictions that break solvability or realism (e.g., mismatched names across email vs CRM, impossible dates, entities referenced in one service but not elsewhere when required). Note: When evaluating a contradiction, if there is sufficient supporting evidence to support one piece of information against a contradicting low-supported piece of information, do not count that as a contradiction. | J59: Universe edits (if any) are internally consistent and coherent across services, including dates, names, and storyline continuity. | L59: =if(and(len(A59)>0,len(B59)>0,len(C59)>0,len(F59)>0),true,) -> TRUE
A60: RL | B60: Oracle Events (OEs) | C60: OE Accuracy | D60: 4 | E60: Auditors should verify OEs against the universe data using the Explorer or Sandbox. Each OE should reference the correct tool, correct service, correct parameters, and correct expected data. An OE that describes "look up Fatimah's relocations in Linear" when relocation records are actually in the CRM is inaccurate — the data exists but the OE points to the wrong place. OE Accuracy is distinct from OE Completeness: completeness checks whether steps are missing; accuracy checks whether the steps that exist are correct. | F60: N/A | H60: [Non-Fail - Minor OE Inaccuracies] OEs are substantively correct but contain minor imprecisions (e.g., slightly wrong parameter name that doesn't change the outcome, approximate rather than exact expected values for freetext fields). [Non-Fail - Inaccurate Oracle Events] One or more OEs reference the wrong tool, wrong service, wrong parameters, or wrong expected data. The described steps would not produce the correct results if followed literally (e.g., searching the wrong service for data that lives elsewhere, expecting data that doesn't match the universe, specifying incorrect entity names or identifiers). | J60: All OEs are factually accurate. Tools, services, parameters, and expected data match the universe. Following the OEs literally would produce a correct trajectory. | L60: =if(and(len(A60)>0,len(B60)>0,len(C60)>0,len(F60)>0),true,) -> TRUE
A61: RL | B61: Oracle Events (OEs) | C61: OE Completeness | D61: 4 | E61: Additional Notes: OEs are the key steps a correct agent would take. They serve two purposes: (1) prove solvability, and (2) generate TS and QC rubrics. Each OE should note: what action happens, what info is discovered, what tool is used, and what parameters matter. OEs describe tool-use steps — not what the final response should say. | F61: N/A | H61: [Non-Fail - Incomplete Oracle Events] - OEs are missing critical steps needed to solve the task (e.g., no step describing how key info is retrieved, or how required action is executed). | J61: OEs describe the full critical path: key discovery steps + dependency chain(s) + required write action(s). | L61: =if(and(len(A61)>0,len(B61)>0,len(C61)>0,len(F61)>0),true,) -> TRUE
A62: RL | B62: Rubrics | C62: Overall Rubric Quality | D62: 5 | F62: Use the number of criteria that the CB wrote as the denominator while calculating % values. See the additional notes section for the numerator. Do NOT double count criteria while tallying even if it has multiple issues. [Fail - 10%+ Major Rubric Errors] More than 10% (>10%) of the criteria contain major issues [Fail - 15%+ Moderate Rubric Errors] More than 15% (>15%) of the criteria contain moderate or major issues [Fail - 20%+ Minor Rubric Errors] More than 20% (>20%) of the criteria contain minor or moderate or major issues | H62: [Non-Fail - Up to 10% Major Errors] Up to 10% (<=10%) of the criteria contain major issues [Non-Fail - Up to 15% Moderate Errors] Up to 15% (<=15%) of criteria contain moderate or major issues (with major issues contributing lower than 5%) [Non-Fail - 5-20% Minor Errors] Between 5 and 20% (>=5% and <=20%) of criteria contain minor or moderate or major issues (with major issues contributing lower than 5% and moderate issues contributing lower than 15%) | J62: - Less than 5% (<5%) of the rubrics have minor issues - No major or moderate issues | L62: =if(and(len(A62)>0,len(B62)>0,len(C62)>0,len(F62)>0),true,) -> TRUE
A63: RL | B63: Rubrics | C63: Rubric Category Balance | D63: 5 | E63: Outcome rubrics check final correctness (was the result right?). Process rubrics = Tool Selection + Query Construction (did the agent use the right tools with the right parameters?). Target ratio is approximately 80% Outcome, 20% Process. | F63: [Fail - No Outcome Rubrics] - The rubric set contains zero Outcome rubrics. [Fail - Process-Heavy] - More than 50% of rubrics are Process (Tool Selection + Query Construction), with Outcome rubrics underrepresented. [Fail - Missing Grounding Check] Investigation-heavy task has no grounding-check rubric verifying the agent retrieved data before reporting it. | J63: Approximately 80% or more of rubrics are Outcome. Process rubrics (TS + QC) are present but limited to critical oracle-event steps. | L63: =if(and(len(A63)>0,len(B63)>0,len(C63)>0,len(F63)>0),true,) -> TRUE
A64: RL | B64: Trajectory | C64: Tool Call Count | D64: 6 | E64: Important note for auditors: During the QH audits, this criterion should not be evaluated. | F64: [Fail - Insufficient Tool Calls] - All trajectories contains fewer than 30 tool calls | H64: [Non-Fail - Below Target Tool Calls] - At least one trajectory contains 30–39 tool calls. The task elicits broad exploration but falls slightly short of the 40-call complexity target. | J64: At least one trajectory contains 40+ tool calls, reflecting genuine cross-service investigation and action complexity. | L64: =if(and(len(A64)>0,len(B64)>0,len(C64)>0,len(F64)>0),true,) -> TRUE
A65: RL | B65: Trajectory | C65: Agent Failure Rate | D65: 6 | E65: At least 4 of the agent runs need to fail the prompt. A failure is defined as the model failing at least one valid outcome rubric. Process rubric failures are not model failures. | F65: [Fail - Too Easy] - More than 2 of 6 runs pass all valid outcome rubrics (i.e., pass@1 > 40%) | J65: 0–2 of 6 runs pass all outcome rubrics (pass@1 ≤ 40%), proving the task is sufficiently difficult | L65: =if(and(len(A65)>0,len(B65)>0,len(C65)>0,len(F65)>0),true,) -> TRUE
A66: RL | B66: Prompt | C66: Persona | D66: 2 | E66: See the list of personas in the instructions doc or in the summary doc | F66: [Fail - Persona Mismatch] The prompt written by the CB does not read like it could have been written by the persona selected. Note: Do not flag if you think the prompt suits a different persona, but rather only fail the task if the prompt cannot plausibly be written by the persona selected. | H66: [Non-Fail - Persona Mismatch] The prompt written by the CB is plausible for the persona selected, but fits a different persona better | J66: The prompt written by the CB aligns with the persona selected | L66: =if(and(len(A66)>0,len(B66)>0,len(C66)>0,len(F66)>0),true,) -> TRUE
A67: =if(len(CONCATENATE(B67:J67))>0,A45,"") | L67: =if(and(len(A67)>0,len(B67)>0,len(C67)>0,len(F67)>0),true,)
A68: =if(len(CONCATENATE(B68:J68))>0,A46,"") | L68: =if(and(len(A68)>0,len(B68)>0,len(C68)>0,len(F68)>0),true,)
A69: =if(len(CONCATENATE(B69:J69))>0,A47,"") | L69: =if(and(len(A69)>0,len(B69)>0,len(C69)>0,len(F69)>0),true,)
A70: =if(len(CONCATENATE(B70:J70))>0,A48,"") | L70: =if(and(len(A70)>0,len(B70)>0,len(C70)>0,len(F70)>0),true,)
A71: =if(len(CONCATENATE(B71:J71))>0,A49,"") | L71: =if(and(len(A71)>0,len(B71)>0,len(C71)>0,len(F71)>0),true,)
A72: =if(len(CONCATENATE(B72:J72))>0,A50,"") | L72: =if(and(len(A72)>0,len(B72)>0,len(C72)>0,len(F72)>0),true,)
A73: =if(len(CONCATENATE(B73:J73))>0,A51,"") | L73: =if(and(len(A73)>0,len(B73)>0,len(C73)>0,len(F73)>0),true,)
A74: =if(len(CONCATENATE(B74:J74))>0,A52,"") | L74: =if(and(len(A74)>0,len(B74)>0,len(C74)>0,len(F74)>0),true,)
A75: =if(len(CONCATENATE(B75:J75))>0,A53,"") | L75: =if(and(len(A75)>0,len(B75)>0,len(C75)>0,len(F75)>0),true,)
A76: =if(len(CONCATENATE(B76:J76))>0,A54,"") | L76: =if(and(len(A76)>0,len(B76)>0,len(C76)>0,len(F76)>0),true,)
A77: =if(len(CONCATENATE(B77:J77))>0,A55,"") | L77: =if(and(len(A77)>0,len(B77)>0,len(C77)>0,len(F77)>0),true,)
A78: =if(len(CONCATENATE(B78:J78))>0,#REF!,"") | L78: =if(and(len(A78)>0,len(B78)>0,len(C78)>0,len(F78)>0),true,)
A79: =if(len(CONCATENATE(B79:J79))>0,A56,"")
A80: =if(len(CONCATENATE(B80:J80))>0,A57,"")
A81: =if(len(CONCATENATE(B81:J81))>0,A58,"")
A82: =if(len(CONCATENATE(B82:J82))>0,A59,"")
A83: =if(len(CONCATENATE(B83:J83))>0,A61,"")
A84: =if(len(CONCATENATE(B84:J84))>0,A62,"")
A85: =if(len(CONCATENATE(B85:J85))>0,A64,"")
A86: =if(len(CONCATENATE(B86:J86))>0,A65,"")
A87: =if(len(CONCATENATE(B87:J87))>0,A66,"")
A88: =if(len(CONCATENATE(B88:J88))>0,A67,"")
A89: =if(len(CONCATENATE(B89:J89))>0,A68,"")
A90: =if(len(CONCATENATE(B90:J90))>0,A69,"")
A91: =if(len(CONCATENATE(B91:J91))>0,A70,"")
A92: =if(len(CONCATENATE(B92:J92))>0,A71,"")
A93: =if(len(CONCATENATE(B93:J93))>0,A72,"")
A94: =if(len(CONCATENATE(B94:J94))>0,A73,"")
A95: =if(len(CONCATENATE(B95:J95))>0,A74,"")
A96: =if(len(CONCATENATE(B96:J96))>0,A75,"")
... A1032: =if(len(CONCATENATE(B1032:J1032))>0,A1011,"")

Sheet 3. ML & QC Review
A1: ML & QC Review | C1: Status: | D1: ` | E1: Please perform any agreed edits at this stage on Tab 2 | G1: Please perform any agreed edits at this stage on Tab 2 | I1: Please perform any agreed edits at this stage on Tab 2 | K1: Please perform any agreed edits at this stage on Tab 2
A2: ML & QC Input Only | C2: =if(countifs(A6:A33,"<>",K6:K33,"<>Approved")+countifs(A6:A33,"<>",O6:O33,"<>Approved")+countifs(A36:A1013,"<>",K36:K1013,"<>Approved")+countifs(A36:A1013,"<>",O36:O1013,"<>Approved")>0,"Pending Approval","Approved") -> Approved
A4: Revised Dimensions | K4: See Full Rubric Preview | O4: See Full Rubric Preview
A5: Task Type | B5: Dimension | C5: Sub-Dimension | D5: Notes | E5: 1 - 2 (Standard) | F5: 1 - 2 (Revision) | G5: 3 - 4 (Standard) | H5: 3 - 4 (Revision) | I5: 5 (Standard) | J5: 5 (Revision) | K5: QC Approval | L5: QC AM/ Auditor Lead Designee | M5: QC Approval Date/Time | N5: QC Suggestion | O5: ML Approval | P5: ML Approver | Q5: ML Approval Date/Time | R5: ML Suggestion
A6: =IFERROR(__xludf.DUMMYFUNCTION("iferror(filter('2. Dimension Definition'!A6:C50,'2. Dimension Definition'!L6:L50=true))"),"") | D6: =IFERROR(__xludf.DUMMYFUNCTION("iferror(filter('2. Dimension Definition'!E6:K50,'2. Dimension Definition'!L6:L50=true),""(no revised dimensions)"")"),"(no revised dimensions)") -> (no revised dimensions) | K6: Pending Review / Edits | O6: Pending Review / Edits
A34: Additional Custom Dimensions | E34: Note: If an error appears in D36 please delete the contents of E36 -- J36 and down, this will allow range to be expanded. Ignore edit warnings
A35: Task Type | B35: Dimension | C35: Sub-Dimension | D35: Notes | E35: 1 (Custom) | G35: 3 (Custom) | I35: 5 (Custom) | K35: QC Approval | L35: Approval Date/Time | N35: QC Suggestion | O35: ML Approval | P35: ML Approver | Q35: ML Approval Date/Time | R35: ML Suggestion
A36: =IFERROR(__xludf.DUMMYFUNCTION("iferror(filter('2. Dimension Definition'!A53:C1013,'2. Dimension Definition'!L53:L1013=true),""(no custom dimensions)"")"),"RL") -> RL | B36: =IFERROR(__xludf.DUMMYFUNCTION("""COMPUTED_VALUE"""),"Prompt") -> Prompt | C36: =IFERROR(__xludf.DUMMYFUNCTION("""COMPUTED_VALUE"""),"Feasibility") -> Feasibility | D36: =IFERROR(__xludf.DUMMYFUNCTION("iferror(filter('2. Dimension Definition'!E53:J1013,'2. Dimension Definition'!L53:L1013=true),""(no custom dimensions)"")"),"") | E36: =IFERROR(__xludf.DUMMYFUNCTION("""COMPUTED_VALUE"""),"[Fail - Prompt Impractical Request] - Prompt contains an impractical request that can't be answered by an LLM in a single response [Fail - Prompt Impossible Request] - Prompt has at least one request that can't be fulfilled at all [Fail - Prompt Conflic"&"ting Instructions] - Prompt gives instructions that conflict/contradict with itself that can't be fulfilled simultaneously [Fail - Prompt Feasibility with Tools] - Prompt contains an impractical or impossible request that can't be answered by the tools a"&"vailable or enabled for the task") -> [Fail - Prompt Impractical Request] - Prompt contains an impractical request that can't be answered by an LLM in a single response [Fail - Prompt Impossible Request] - Prompt has at least one request that can't be fulfilled at all [Fail - Prompt Conflicting Instructions] - Prompt gives instructions that conflict/contradict with itself that can't be fulfilled simultaneously [Fail - Prompt Feasibility with Tools] - Prompt contains an impractical or impossible request that can't be answered by the tools available or enabled for the task | G36: =IFERROR(__xludf.DUMMYFUNCTION("""COMPUTED_VALUE"""),"Non-Fail - Prompt Impractical Secondary Request] - There are multiple requests in the prompt and it's verging on being impractical for a model to answer it in a single response, but the core request of the prompt can be fulfilled with minor concessions on"&" the secondary requests") -> Non-Fail - Prompt Impractical Secondary Request] - There are multiple requests in the prompt and it's verging on being impractical for a model to answer it in a single response, but the core request of the prompt can be fulfilled with minor concessions on the secondary requests | I36: =IFERROR(__xludf.DUMMYFUNCTION("""COMPUTED_VALUE"""),"- The prompt is completely actionable by an LLM agent. - The prompt contains no conflicting instructions/statements") -> - The prompt is completely actionable by an LLM agent. - The prompt contains no conflicting instructions/statements | K36: Approved | L36: Varun Kumar Velidandi | M36: 3 PM PST, Mar 5 2026 | O36: Approved | R36: Reviewed by ML in alignment call
A37: =IFERROR(__xludf.DUMMYFUNCTION("""COMPUTED_VALUE"""),"RL") -> RL | B37: =IFERROR(__xludf.DUMMYFUNCTION("""COMPUTED_VALUE"""),"Prompt") -> Prompt | C37: =IFERROR(__xludf.DUMMYFUNCTION("""COMPUTED_VALUE"""),"Tool use and Cross-service requirement") -> Tool use and Cross-service requirement | E37: =IFERROR(__xludf.DUMMYFUNCTION("""COMPUTED_VALUE"""),"[Fail - Tool Dependence] - The prompt can be answered without having to make any tool calls (either through basic reasoning or general knowledge) [Fail - Cross-service Requirement] - Prompt can be fully resolved within a single service (e.g., just email "&"or just CRM), or only trivially touches a second service.") -> [Fail - Tool Dependence] - The prompt can be answered without having to make any tool calls (either through basic reasoning or general knowledge) [Fail - Cross-service Requirement] - Prompt can be fully resolved within a single service (e.g., just email or just CRM), or only trivially touches a second service. | G37: =IFERROR(__xludf.DUMMYFUNCTION("""COMPUTED_VALUE"""),"N/A") -> N/A | I37: =IFERROR(__xludf.DUMMYFUNCTION("""COMPUTED_VALUE"""),"- Prompt requires investigation across 2+ services to answer correctly (e.g., facts needed are scattered and must be reconciled).") -> - Prompt requires investigation across 2+ services to answer correctly (e.g., facts needed are scattered and must be reconciled). | K37: Approved | L37: Varun Kumar Velidandi | M37: 3 PM PST, Mar 5 2026 | O37: Approved | R37: Reviewed by ML in alignment call
A38: =IFERROR(__xludf.DUMMYFUNCTION("""COMPUTED_VALUE"""),"RL") -> RL | B38: =IFERROR(__xludf.DUMMYFUNCTION("""COMPUTED_VALUE"""),"Prompt") -> Prompt | C38: =IFERROR(__xludf.DUMMYFUNCTION("""COMPUTED_VALUE"""),"Explicit Tool Mention") -> Explicit Tool Mention | E38: =IFERROR(__xludf.DUMMYFUNCTION("""COMPUTED_VALUE"""),"[Fail - Explicit Tool Mention] The prompt explicitly mentions a specific tool name The prompt unnaturally refers to an MCP server in an inorganic, technical manner “Use the Airbnb tool to…” (technical, unnatural) “I want to use Airbnb to find…” (general, "&"natural)") -> [Fail - Explicit Tool Mention] The prompt explicitly mentions a specific tool name The prompt unnaturally refers to an MCP server in an inorganic, technical manner “Use the Airbnb tool to…” (technical, unnatural) “I want to use Airbnb to find…” (general, natural) | G38: =IFERROR(__xludf.DUMMYFUNCTION("""COMPUTED_VALUE"""),"N/A") -> N/A | I38: =IFERROR(__xludf.DUMMYFUNCTION("""COMPUTED_VALUE"""),"- The prompt does not explicitly state the use of tools ") -> - The prompt does not explicitly state the use of tools | K38: Approved | L38: Varun Kumar Velidandi | M38: 3 PM PST, Mar 5 2026 | O38: Approved | R38: Reviewed by ML in alignment call
A39: =IFERROR(__xludf.DUMMYFUNCTION("""COMPUTED_VALUE"""),"RL") -> RL | B39: =IFERROR(__xludf.DUMMYFUNCTION("""COMPUTED_VALUE"""),"Prompt") -> Prompt | C39: =IFERROR(__xludf.DUMMYFUNCTION("""COMPUTED_VALUE"""),"Investigation + Action") -> Investigation + Action | E39: =IFERROR(__xludf.DUMMYFUNCTION("""COMPUTED_VALUE"""),"[Fail - Action Missing] - Prompt only asks for a summary/report/research with no required action. [Fail - Pre-solved] - Prompt tells agent the root cause and no investigation is needed.") -> [Fail - Action Missing] - Prompt only asks for a summary/report/research with no required action. [Fail - Pre-solved] - Prompt tells agent the root cause and no investigation is needed. | G39: =IFERROR(__xludf.DUMMYFUNCTION("""COMPUTED_VALUE"""),"N/A") -> N/A | I39: =IFERROR(__xludf.DUMMYFUNCTION("""COMPUTED_VALUE"""),"Prompt clearly requires investigtion and at least one concrete action (email, ticket creation/update, booking, calendar scheduling, CRM update, etc.), and it logically follows from investigation.") -> Prompt clearly requires investigtion and at least one concrete action (email, ticket creation/update, booking, calendar scheduling, CRM update, etc.), and it logically follows from investigation. | K39: Approved | L39: Varun Kumar Velidandi | M39: 3 PM PST, Mar 5 2026 | O39: Approved | R39: Reviewed by ML in alignment call
A40: =IFERROR(__xludf.DUMMYFUNCTION("""COMPUTED_VALUE"""),"RL") -> RL | B40: =IFERROR(__xludf.DUMMYFUNCTION("""COMPUTED_VALUE"""),"Prompt") -> Prompt | C40: =IFERROR(__xludf.DUMMYFUNCTION("""COMPUTED_VALUE"""),"Coherence") -> Coherence | D40: =IFERROR(__xludf.DUMMYFUNCTION("""COMPUTED_VALUE"""),"An example of failing bolt-on requests: ""Check weather in Miami, update my calendar for next week, email Marcus about Q3, and look up Seattle flights."" Why it fails: Four unrelated requests stapled together. Each sub-request should causally flow from "&"the same situation. How to tell if your prompt is ""bolted"": Remove any one sentence. If the rest still makes perfect sense without it, that sentence is a bolt-on") -> An example of failing bolt-on requests: "Check weather in Miami, update my calendar for next week, email Marcus about Q3, and look up Seattle flights." Why it fails: Four unrelated requests stapled together. Each sub-request should causally flow from the same situation. How to tell if your prompt is "bolted": Remove any one sentence. If the rest still makes perfect sense without it, that sentence is a bolt-on | E40: =IFERROR(__xludf.DUMMYFUNCTION("""COMPUTED_VALUE"""),"[Fail - Bolt-on requests] - Contains unrelated bolt-on requests; removing a sentence doesn’t change the rest.") -> [Fail - Bolt-on requests] - Contains unrelated bolt-on requests; removing a sentence doesn’t change the rest. | G40: =IFERROR(__xludf.DUMMYFUNCTION("""COMPUTED_VALUE"""),"N/A") -> N/A | I40: =IFERROR(__xludf.DUMMYFUNCTION("""COMPUTED_VALUE"""),"One cohesive situation; stacked asks all tie back to the same purpose.") -> One cohesive situation; stacked asks all tie back to the same purpose. | K40: Approved | L40: Varun Kumar Velidandi | M40: 3 PM PST, Mar 5 2026 | O40: Approved | R40: Reviewed by ML in alignment call
A41: =IFERROR(__xludf.DUMMYFUNCTION("""COMPUTED_VALUE"""),"RL") -> RL | B41: =IFERROR(__xludf.DUMMYFUNCTION("""COMPUTED_VALUE"""),"Universe") -> Universe | C41: =IFERROR(__xludf.DUMMYFUNCTION("""COMPUTED_VALUE"""),"Universe Feasibility (Data Exists)") -> Universe Feasibility (Data Exists) | D41: =IFERROR(__xludf.DUMMYFUNCTION("""COMPUTED_VALUE"""),"Auditors should check the Universe Explorer or Sandbox to verify that key data needed for the prompt exists. ") -> Auditors should check the Universe Explorer or Sandbox to verify that key data needed for the prompt exists. | E41: =IFERROR(__xludf.DUMMYFUNCTION("""COMPUTED_VALUE"""),"[Fail - Missing Universe Data] - Task depends on key facts/entities/events that do not exist in the universe (or cannot be retrieved with available tools), making the task unsolvable.") -> [Fail - Missing Universe Data] - Task depends on key facts/entities/events that do not exist in the universe (or cannot be retrieved with available tools), making the task unsolvable. | G41: =IFERROR(__xludf.DUMMYFUNCTION("""COMPUTED_VALUE"""),"N/A") -> N/A | I41: =IFERROR(__xludf.DUMMYFUNCTION("""COMPUTED_VALUE"""),"All core facts required to solve the task exist in the universe and are retrievable via tools.") -> All core facts required to solve the task exist in the universe and are retrievable via tools. | K41: Approved | L41: Varun Kumar Velidandi | M41: 3 PM PST, Mar 5 2026 | O41: Approved | R41: Reviewed by ML in alignment call
A42: =IFERROR(__xludf.DUMMYFUNCTION("""COMPUTED_VALUE"""),"RL") -> RL | B42: =IFERROR(__xludf.DUMMYFUNCTION("""COMPUTED_VALUE"""),"Universe") -> Universe | C42: =IFERROR(__xludf.DUMMYFUNCTION("""COMPUTED_VALUE"""),"Cross-service Coherence") -> Cross-service Coherence | D42: =IFERROR(__xludf.DUMMYFUNCTION("""COMPUTED_VALUE"""),"Auditors should refer to the changelog table in the sandbox to check changes that were made to the universe (if edits were made).") -> Auditors should refer to the changelog table in the sandbox to check changes that were made to the universe (if edits were made). | E42: =IFERROR(__xludf.DUMMYFUNCTION("""COMPUTED_VALUE"""),"[Fail - Incoherent Universe Changes] - Universe edits create contradictions that break solvability or realism (e.g., mismatched names across email vs CRM, impossible dates, entities referenced in one service but not elsewhere when required). Note: When e"&"valuating a contradiction, if there is sufficient supporting evidence to support one piece of information against a contradicting low-supported piece of information, do not count that as a contradiction.") -> [Fail - Incoherent Universe Changes] - Universe edits create contradictions that break solvability or realism (e.g., mismatched names across email vs CRM, impossible dates, entities referenced in one service but not elsewhere when required). Note: When evaluating a contradiction, if there is sufficient supporting evidence to support one piece of information against a contradicting low-supported piece of information, do not count that as a contradiction. | I42: =IFERROR(__xludf.DUMMYFUNCTION("""COMPUTED_VALUE"""),"Universe edits (if any) are internally consistent and coherent across services, including dates, names, and storyline continuity.") -> Universe edits (if any) are internally consistent and coherent across services, including dates, names, and storyline continuity. | K42: Approved | L42: Varun Kumar Velidandi | M42: 3 PM PST, Mar 5 2026 | O42: Approved | R42: Reviewed by ML in alignment call
A43: =IFERROR(__xludf.DUMMYFUNCTION("""COMPUTED_VALUE"""),"RL") -> RL | B43: =IFERROR(__xludf.DUMMYFUNCTION("""COMPUTED_VALUE"""),"Oracle Events (OEs)") -> Oracle Events (OEs) | C43: =IFERROR(__xludf.DUMMYFUNCTION("""COMPUTED_VALUE"""),"OE Accuracy") -> OE Accuracy | D43: =IFERROR(__xludf.DUMMYFUNCTION("""COMPUTED_VALUE"""),"Auditors should verify OEs against the universe data using the Explorer or Sandbox. Each OE should reference the correct tool, correct service, correct parameters, and correct expected data. An OE that describes ""look up Fatimah's relocations in Linear"""&" when relocation records are actually in the CRM is inaccurate — the data exists but the OE points to the wrong place. OE Accuracy is distinct from OE Completeness: completeness checks whether steps are missing; accuracy checks whether the steps that exis"&"t are correct.") -> Auditors should verify OEs against the universe data using the Explorer or Sandbox. Each OE should reference the correct tool, correct service, correct parameters, and correct expected data. An OE that describes "look up Fatimah's relocations in Linear" when relocation records are actually in the CRM is inaccurate — the data exists but the OE points to the wrong place. OE Accuracy is distinct from OE Completeness: completeness checks whether steps are missing; accuracy checks whether the steps that exist are correct. | E43: =IFERROR(__xludf.DUMMYFUNCTION("""COMPUTED_VALUE"""),"N/A") -> N/A | G43: =IFERROR(__xludf.DUMMYFUNCTION("""COMPUTED_VALUE"""),"[Non-Fail - Minor OE Inaccuracies] OEs are substantively correct but contain minor imprecisions (e.g., slightly wrong parameter name that doesn't change the outcome, approximate rather than exact expected values for freetext fields). [Non-Fail - Inaccura"&"te Oracle Events] One or more OEs reference the wrong tool, wrong service, wrong parameters, or wrong expected data. The described steps would not produce the correct results if followed literally (e.g., searching the wrong service for data that lives els"&"ewhere, expecting data that doesn't match the universe, specifying incorrect entity names or identifiers).") -> [Non-Fail - Minor OE Inaccuracies] OEs are substantively correct but contain minor imprecisions (e.g., slightly wrong parameter name that doesn't change the outcome, approximate rather than exact expected values for freetext fields). [Non-Fail - Inaccurate Oracle Events] One or more OEs reference the wrong tool, wrong service, wrong parameters, or wrong expected data. The described steps would not produce the correct results if followed literally (e.g., searching the wrong service for data that lives elsewhere, expecting data that doesn't match the universe, specifying incorrect entity names or identifiers). | I43: =IFERROR(__xludf.DUMMYFUNCTION("""COMPUTED_VALUE"""),"All OEs are factually accurate. Tools, services, parameters, and expected data match the universe. Following the OEs literally would produce a correct trajectory.") -> All OEs are factually accurate. Tools, services, parameters, and expected data match the universe. Following the OEs literally would produce a correct trajectory. | K43: Approved | L43: Varun Kumar Velidandi | M43: 3 PM PST, Mar 5 2026 | O43: Approved | R43: Reviewed by ML in alignment call
A44: =IFERROR(__xludf.DUMMYFUNCTION("""COMPUTED_VALUE"""),"RL") -> RL | B44: =IFERROR(__xludf.DUMMYFUNCTION("""COMPUTED_VALUE"""),"Oracle Events (OEs)") -> Oracle Events (OEs) | C44: =IFERROR(__xludf.DUMMYFUNCTION("""COMPUTED_VALUE"""),"OE Completeness") -> OE Completeness | D44: =IFERROR(__xludf.DUMMYFUNCTION("""COMPUTED_VALUE"""),"Additional Notes: OEs are the key steps a correct agent would take. They serve two purposes: (1) prove solvability, and (2) generate TS and QC rubrics. Each OE should note: what action happens, what info is discovered, what tool is used, and what param"&"eters matter. OEs describe tool-use steps — not what the final response should say.") -> Additional Notes: OEs are the key steps a correct agent would take. They serve two purposes: (1) prove solvability, and (2) generate TS and QC rubrics. Each OE should note: what action happens, what info is discovered, what tool is used, and what parameters matter. OEs describe tool-use steps — not what the final response should say. | E44: =IFERROR(__xludf.DUMMYFUNCTION("""COMPUTED_VALUE"""),"N/A") -> N/A | G44: =IFERROR(__xludf.DUMMYFUNCTION("""COMPUTED_VALUE"""),"[Non-Fail - Incomplete Oracle Events] - OEs are missing critical steps needed to solve the task (e.g., no step describing how key info is retrieved, or how required action is executed).") -> [Non-Fail - Incomplete Oracle Events] - OEs are missing critical steps needed to solve the task (e.g., no step describing how key info is retrieved, or how required action is executed). | I44: =IFERROR(__xludf.DUMMYFUNCTION("""COMPUTED_VALUE"""),"OEs describe the full critical path: key discovery steps + dependency chain(s) + required write action(s).") -> OEs describe the full critical path: key discovery steps + dependency chain(s) + required write action(s). | K44: Approved | L44: Varun Kumar Velidandi | M44: 3 PM PST, Mar 5 2026 | O44: Approved | R44: Reviewed by ML in alignment call
A45: =IFERROR(__xludf.DUMMYFUNCTION("""COMPUTED_VALUE"""),"RL") -> RL | B45: =IFERROR(__xludf.DUMMYFUNCTION("""COMPUTED_VALUE"""),"Rubrics") -> Rubrics | C45: =IFERROR(__xludf.DUMMYFUNCTION("""COMPUTED_VALUE"""),"Overall Rubric Quality") -> Overall Rubric Quality | E45: =IFERROR(__xludf.DUMMYFUNCTION("""COMPUTED_VALUE"""),"Use the number of criteria that the CB wrote as the denominator while calculating % values. See the additional notes section for the numerator. Do NOT double count criteria while tallying even if it has multiple issues. [Fail - 10%+ Major Rubric Errors] "&"More than 10% (>10%) of the criteria contain major issues [Fail - 15%+ Moderate Rubric Errors] More than 15% (>15%) of the criteria contain moderate or major issues [Fail - 20%+ Minor Rubric Errors] More than 20% (>20%) of the criteria contain minor or "&"moderate or major issues") -> Use the number of criteria that the CB wrote as the denominator while calculating % values. See the additional notes section for the numerator. Do NOT double count criteria while tallying even if it has multiple issues. [Fail - 10%+ Major Rubric Errors] More than 10% (>10%) of the criteria contain major issues [Fail - 15%+ Moderate Rubric Errors] More than 15% (>15%) of the criteria contain moderate or major issues [Fail - 20%+ Minor Rubric Errors] More than 20% (>20%) of the criteria contain minor or moderate or major issues | G45: =IFERROR(__xludf.DUMMYFUNCTION("""COMPUTED_VALUE"""),"[Non-Fail - Up to 10% Major Errors] Up to 10% (<=10%) of the criteria contain major issues [Non-Fail - Up to 15% Moderate Errors] Up to 15% (<=15%) of criteria contain moderate or major issues (with major issues contributing lower than 5%) [Non-Fail - 5"&"-20% Minor Errors] Between 5 and 20% (>=5% and <=20%) of criteria contain minor or moderate or major issues (with major issues contributing lower than 5% and moderate issues contributing lower than 15%) ") -> [Non-Fail - Up to 10% Major Errors] Up to 10% (<=10%) of the criteria contain major issues [Non-Fail - Up to 15% Moderate Errors] Up to 15% (<=15%) of criteria contain moderate or major issues (with major issues contributing lower than 5%) [Non-Fail - 5-20% Minor Errors] Between 5 and 20% (>=5% and <=20%) of criteria contain minor or moderate or major issues (with major issues contributing lower than 5% and moderate issues contributing lower than 15%) | I45: =IFERROR(__xludf.DUMMYFUNCTION("""COMPUTED_VALUE"""),"- Less than 5% (<5%) of the rubrics have minor issues - No major or moderate issues ") -> - Less than 5% (<5%) of the rubrics have minor issues - No major or moderate issues | K45: Approved | L45: Varun Kumar Velidandi | M45: 3 PM PST, Mar 5 2026 | O45: Approved | R45: Reviewed by ML in alignment call
A46: =IFERROR(__xludf.DUMMYFUNCTION("""COMPUTED_VALUE"""),"RL") -> RL | B46: =IFERROR(__xludf.DUMMYFUNCTION("""COMPUTED_VALUE"""),"Rubrics") -> Rubrics | C46: =IFERROR(__xludf.DUMMYFUNCTION("""COMPUTED_VALUE"""),"Rubric Category Balance") -> Rubric Category Balance | D46: =IFERROR(__xludf.DUMMYFUNCTION("""COMPUTED_VALUE"""),"Outcome rubrics check final correctness (was the result right?). Process rubrics = Tool Selection + Query Construction (did the agent use the right tools with the right parameters?). Target ratio is approximately 80% Outcome, 20% Process. ") -> Outcome rubrics check final correctness (was the result right?). Process rubrics = Tool Selection + Query Construction (did the agent use the right tools with the right parameters?). Target ratio is approximately 80% Outcome, 20% Process. | E46: =IFERROR(__xludf.DUMMYFUNCTION("""COMPUTED_VALUE"""),"[Fail - No Outcome Rubrics] - The rubric set contains zero Outcome rubrics. [Fail - Process-Heavy] - More than 50% of rubrics are Process (Tool Selection + Query Construction), with Outcome rubrics underrepresented. [Fail - Missing Grounding Check] Inves"&"tigation-heavy task has no grounding-check rubric verifying the agent retrieved data before reporting it.") -> [Fail - No Outcome Rubrics] - The rubric set contains zero Outcome rubrics. [Fail - Process-Heavy] - More than 50% of rubrics are Process (Tool Selection + Query Construction), with Outcome rubrics underrepresented. [Fail - Missing Grounding Check] Investigation-heavy task has no grounding-check rubric verifying the agent retrieved data before reporting it. | I46: =IFERROR(__xludf.DUMMYFUNCTION("""COMPUTED_VALUE"""),"Approximately 80% or more of rubrics are Outcome. Process rubrics (TS + QC) are present but limited to critical oracle-event steps.") -> Approximately 80% or more of rubrics are Outcome. Process rubrics (TS + QC) are present but limited to critical oracle-event steps. | K46: Approved | L46: Varun Kumar Velidandi | M46: 3 PM PST, Mar 5 2026 | O46: Approved | R46: Reviewed by ML in alignment call
A47: =IFERROR(__xludf.DUMMYFUNCTION("""COMPUTED_VALUE"""),"RL") -> RL | B47: =IFERROR(__xludf.DUMMYFUNCTION("""COMPUTED_VALUE"""),"Trajectory") -> Trajectory | C47: =IFERROR(__xludf.DUMMYFUNCTION("""COMPUTED_VALUE"""),"Tool Call Count") -> Tool Call Count | D47: =IFERROR(__xludf.DUMMYFUNCTION("""COMPUTED_VALUE""")," Important note for auditors: During the QH audits, this criterion should not be evaluated.") -> Important note for auditors: During the QH audits, this criterion should not be evaluated. | E47: =IFERROR(__xludf.DUMMYFUNCTION("""COMPUTED_VALUE"""),"[Fail - Insufficient Tool Calls] - All trajectories contains fewer than 30 tool calls") -> [Fail - Insufficient Tool Calls] - All trajectories contains fewer than 30 tool calls | G47: =IFERROR(__xludf.DUMMYFUNCTION("""COMPUTED_VALUE"""),"[Non-Fail - Below Target Tool Calls] - At least one trajectory contains 30–39 tool calls. The task elicits broad exploration but falls slightly short of the 40-call complexity target.") -> [Non-Fail - Below Target Tool Calls] - At least one trajectory contains 30–39 tool calls. The task elicits broad exploration but falls slightly short of the 40-call complexity target. | I47: =IFERROR(__xludf.DUMMYFUNCTION("""COMPUTED_VALUE"""),"At least one trajectory contains 40+ tool calls, reflecting genuine cross-service investigation and action complexity.") -> At least one trajectory contains 40+ tool calls, reflecting genuine cross-service investigation and action complexity. | K47: Approved | L47: Varun Kumar Velidandi | M47: 3 PM PST, Mar 5 2026 | O47: Approved | R47: Reviewed by ML in alignment call
A48: =IFERROR(__xludf.DUMMYFUNCTION("""COMPUTED_VALUE"""),"RL") -> RL | B48: =IFERROR(__xludf.DUMMYFUNCTION("""COMPUTED_VALUE"""),"Trajectory") -> Trajectory | C48: =IFERROR(__xludf.DUMMYFUNCTION("""COMPUTED_VALUE"""),"Agent Failure Rate") -> Agent Failure Rate | D48: =IFERROR(__xludf.DUMMYFUNCTION("""COMPUTED_VALUE"""),"At least 4 of the agent runs need to fail the prompt. A failure is defined as the model failing at least one valid outcome rubric. Process rubric failures are not model failures.") -> At least 4 of the agent runs need to fail the prompt. A failure is defined as the model failing at least one valid outcome rubric. Process rubric failures are not model failures. | E48: =IFERROR(__xludf.DUMMYFUNCTION("""COMPUTED_VALUE"""),"[Fail - Too Easy] - More than 2 of 6 runs pass all valid outcome rubrics (i.e., pass@1 > 40%) ") -> [Fail - Too Easy] - More than 2 of 6 runs pass all valid outcome rubrics (i.e., pass@1 > 40%) | I48: =IFERROR(__xludf.DUMMYFUNCTION("""COMPUTED_VALUE"""),"0–2 of 6 runs pass all outcome rubrics (pass@1 ≤ 40%), proving the task is sufficiently difficult") -> 0–2 of 6 runs pass all outcome rubrics (pass@1 ≤ 40%), proving the task is sufficiently difficult | K48: Approved | L48: Varun Kumar Velidandi | M48: 3 PM PST, Mar 5 2026 | O48: Approved | R48: Reviewed by ML in alignment call
A49: =IFERROR(__xludf.DUMMYFUNCTION("""COMPUTED_VALUE"""),"RL") -> RL | B49: =IFERROR(__xludf.DUMMYFUNCTION("""COMPUTED_VALUE"""),"Prompt") -> Prompt | C49: =IFERROR(__xludf.DUMMYFUNCTION("""COMPUTED_VALUE"""),"Persona") -> Persona | D49: =IFERROR(__xludf.DUMMYFUNCTION("""COMPUTED_VALUE"""),"See the list of personas in the instructions doc or in the summary doc") -> See the list of personas in the instructions doc or in the summary doc | E49: =IFERROR(__xludf.DUMMYFUNCTION("""COMPUTED_VALUE"""),"[Fail - Persona Mismatch] The prompt written by the CB does not read like it could have been written by the persona selected. Note: Do not flag if you think the prompt suits a different persona, but rather only fail the task if the prompt cannot plausibly"&" be written by the persona selected.") -> [Fail - Persona Mismatch] The prompt written by the CB does not read like it could have been written by the persona selected. Note: Do not flag if you think the prompt suits a different persona, but rather only fail the task if the prompt cannot plausibly be written by the persona selected. | G49: =IFERROR(__xludf.DUMMYFUNCTION("""COMPUTED_VALUE"""),"[Non-Fail - Persona Mismatch] The prompt written by the CB is plausible for the persona selected, but fits a different persona better") -> [Non-Fail - Persona Mismatch] The prompt written by the CB is plausible for the persona selected, but fits a different persona better | I49: =IFERROR(__xludf.DUMMYFUNCTION("""COMPUTED_VALUE"""),"The prompt written by the CB aligns with the persona selected") -> The prompt written by the CB aligns with the persona selected | K49: Approved | L49: Varun Kumar Velidandi | M49: 3 PM PST, Mar 5 2026 | O49: Approved | R49: Reviewed by ML in alignment call
I79: ='2. Dimension Definition'!J97
I80: ='2. Dimension Definition'!J98
I81: ='2. Dimension Definition'!J99
I82: ='2. Dimension Definition'!J100
I83: ='2. Dimension Definition'!J101
I84: ='2. Dimension Definition'!J102
E85: ='2. Dimension Definition'!F103 | I85: ='2. Dimension Definition'!J103
E86: ='2. Dimension Definition'!F104 | I86: ='2. Dimension Definition'!J104
E87: ='2. Dimension Definition'!F105 | I87: ='2. Dimension Definition'!J105
E88: ='2. Dimension Definition'!F106 | I88: ='2. Dimension Definition'!J106
E89: ='2. Dimension Definition'!F107 | I89: ='2. Dimension Definition'!J107
E90: ='2. Dimension Definition'!F108 | I90: ='2. Dimension Definition'!J108
E91: ='2. Dimension Definition'!F109 | G91: ='2. Dimension Definition'!H109 | I91: ='2. Dimension Definition'!J109
E92: ='2. Dimension Definition'!F110 | G92: ='2. Dimension Definition'!H110 | I92: ='2. Dimension Definition'!J110
E93: ='2. Dimension Definition'!F111 | G93: ='2. Dimension Definition'!H111 | I93: ='2. Dimension Definition'!J111
E94: ='2. Dimension Definition'!F112 | G94: ='2. Dimension Definition'!H112 | I94: ='2. Dimension Definition'!J112
E95: ='2. Dimension Definition'!F113 | G95: ='2. Dimension Definition'!H113 | I95: ='2. Dimension Definition'!J113
E96: ='2. Dimension Definition'!F114 | G96: ='2. Dimension Definition'!H114 | I96: ='2. Dimension Definition'!J114
E97: ='2. Dimension Definition'!F115 | G97: ='2. Dimension Definition'!H115 | I97: ='2. Dimension Definition'!J115
E98: ='2. Dimension Definition'!F116 | G98: ='2. Dimension Definition'!H116 | I98: ='2. Dimension Definition'!J116
E99: ='2. Dimension Definition'!F117 | G99: ='2. Dimension Definition'!H117 | I99: ='2. Dimension Definition'!J117
E100: ='2. Dimension Definition'!F118 | G100: ='2. Dimension Definition'!H118 | I100: ='2. Dimension Definition'!J118
E101: ='2. Dimension Definition'!F119 | G101: ='2. Dimension Definition'!H119 | I101: ='2. Dimension Definition'!J119
E102: ='2. Dimension Definition'!F120 | G102: ='2. Dimension Definition'!H120 | I102: ='2. Dimension Definition'!J120
... E1013: ='2. Dimension Definition'!F1031 | G1013: ='2. Dimension Definition'!H1031 | I1013: ='2. Dimension Definition'!J1031

Sheet 4. FINAL QC Output Rubric
A1: Dimension | B1: Sub- Dimension | C1: Notes for Auditors | D1: 1 - 2 | E1: 3 - 4 | F1: 5 | G1: Nonstandard Dimension
A2: {=if('3. ML & QC Review'!C2="Approved",sort(Transform!M2:S1000,Transform!K2:K1000,1,Transform!L2:L1000,1),"Pending Approval")} -> Prompt | B2: Unique Ground Truth | D2: Fail - Multiple Valid Answers] - The prompt can reasonably produce two or more different correct answers, and the prompt does not clearly indicate which answer is intended. | E2: [Non-Fail - Multiple Valid Answers] The prompt is ambiguous, but there is either: a leading interpretation that the majority of people would pick if polled, or there are two different valid interpretations where making a small, logically defensible assumption would clarify which was intended by the user. | F2: - The prompt has a unique ground truth answer. All the experts on the subject would come to the same conclusion | G2: FALSE
A3: Prompt | B3: Feasibility | D3: [Fail - Prompt Impractical Request] - Prompt contains an impractical request that can't be answered by an LLM in a single response [Fail - Prompt Impossible Request] - Prompt has at least one request that can't be fulfilled at all [Fail - Prompt Conflicting Instructions] - Prompt gives instructions that conflict/contradict with itself that can't be fulfilled simultaneously [Fail - Prompt Feasibility with Tools] - Prompt contains an impractical or impossible request that can't be answered by the tools available or enabled for the task | E3: Non-Fail - Prompt Impractical Secondary Request] - There are multiple requests in the prompt and it's verging on being impractical for a model to answer it in a single response, but the core request of the prompt can be fulfilled with minor concessions on the secondary requests | F3: - The prompt is completely actionable by an LLM agent. - The prompt contains no conflicting instructions/statements | G3: TRUE
A4: Prompt | B4: Explicit Tool Mention | D4: [Fail - Explicit Tool Mention] The prompt explicitly mentions a specific tool name The prompt unnaturally refers to an MCP server in an inorganic, technical manner “Use the Airbnb tool to…” (technical, unnatural) “I want to use Airbnb to find…” (general, natural) | E4: N/A | F4: - The prompt does not explicitly state the use of tools | G4: TRUE
A5: Prompt | B5: Prompt Clarity and Specificity | D5: [Fail - Major Clarity / Specificity Issues] - It's not clear what is being asked, the prompt is extremely difficult to follow, or is overly vague; the user intent cannot be reasonably understood from the prompt. - Major details are missing that are needed to answer the prompt and cannot be reasonably assumed | E5: [Non-Fail Minor Clarity / Specificity Issues] - It's mostly clear what is being asked but the request could reasonably be interpreted multiple ways | F5: - There is little to no room for misinterpretation of the specific request - Prompt has a specific request that doesn't require more than one minor assumption to answer it | G5: FALSE
A6: Prompt | B6: Contrived / Unnatural Prompts | C6: This should check for artificial difficulty vs. natural complexity. Contrived examples include: demanding exact timestamps ("Find the email from January 15th at 3:47 PM"), requiring arbitrary format constraints ("Respond in exactly 3 sentences using passive voice"), or asking the agent to do something no real employee would do ("Intentionally send an incorrect email to test error handling"). Natural difficulty comes from entity confusion, scattered information, conflicting data across services, and hidden root causes. Prompts written as step-by-step command lists ("First search emails, then check CRM…") should also be considered contrived. | D6: [Fail - Contrived / Unnatural Prompt] - Prompt is contrived or otherwise unnatural note: prompts such as riddles that are intentionally constraints/details laden should not be considered contrived. | E6: [Non-Fail - Somewhat Contrived / Unnatural Prompt] - Prompt is somewhat contrived or is somewhat unnatural note: prompts such as riddles that are intentionally constraints/details laden should not be considered contrived. | F6: - The prompt is neither contrived or unnatural | G6: FALSE
A7: Prompt | B7: Truthfulness | D7: [Fail - Major Factual Errors] - The prompt contains 1 or more major factual errors [Fail - Minor Factual Errors] - The prompt contains 2 or more minor factual errors (e.g., statements irrelevant to the fulfillment of the prompt's request) | E7: [Non-Fail - Minor Factual Errors] - The prompt contains 1 minor factual errors. | F7: - The prompt has no factual errors - The prompt has no misleading statements | G7: FALSE
A8: Prompt | B8: Tool use and Cross-service requirement | D8: [Fail - Tool Dependence] - The prompt can be answered without having to make any tool calls (either through basic reasoning or general knowledge) [Fail - Cross-service Requirement] - Prompt can be fully resolved within a single service (e.g., just email or just CRM), or only trivially touches a second service. | E8: N/A | F8: - Prompt requires investigation across 2+ services to answer correctly (e.g., facts needed are scattered and must be reconciled). | G8: TRUE
A9: Prompt | B9: Investigation + Action | D9: [Fail - Action Missing] - Prompt only asks for a summary/report/research with no required action. [Fail - Pre-solved] - Prompt tells agent the root cause and no investigation is needed. | E9: N/A | F9: Prompt clearly requires investigtion and at least one concrete action (email, ticket creation/update, booking, calendar scheduling, CRM update, etc.), and it logically follows from investigation. | G9: TRUE
A10: Prompt | B10: Coherence | C10: An example of failing bolt-on requests: "Check weather in Miami, update my calendar for next week, email Marcus about Q3, and look up Seattle flights." Why it fails: Four unrelated requests stapled together. Each sub-request should causally flow from the same situation. How to tell if your prompt is "bolted": Remove any one sentence. If the rest still makes perfect sense without it, that sentence is a bolt-on | D10: [Fail - Bolt-on requests] - Contains unrelated bolt-on requests; removing a sentence doesn’t change the rest. | E10: N/A | F10: One cohesive situation; stacked asks all tie back to the same purpose. | G10: TRUE
A11: Prompt | B11: Persona | C11: See the list of personas in the instructions doc or in the summary doc | D11: [Fail - Persona Mismatch] The prompt written by the CB does not read like it could have been written by the persona selected. Note: Do not flag if you think the prompt suits a different persona, but rather only fail the task if the prompt cannot plausibly be written by the persona selected. | E11: [Non-Fail - Persona Mismatch] The prompt written by the CB is plausible for the persona selected, but fits a different persona better | F11: The prompt written by the CB aligns with the persona selected | G11: TRUE
A12: Universe | B12: Universe Feasibility (Data Exists) | C12: Auditors should check the Universe Explorer or Sandbox to verify that key data needed for the prompt exists. | D12: [Fail - Missing Universe Data] - Task depends on key facts/entities/events that do not exist in the universe (or cannot be retrieved with available tools), making the task unsolvable. | E12: N/A | F12: All core facts required to solve the task exist in the universe and are retrievable via tools. | G12: TRUE
A13: Universe | B13: Cross-service Coherence | C13: Auditors should refer to the changelog table in the sandbox to check changes that were made to the universe (if edits were made). | D13: [Fail - Incoherent Universe Changes] - Universe edits create contradictions that break solvability or realism (e.g., mismatched names across email vs CRM, impossible dates, entities referenced in one service but not elsewhere when required). Note: When evaluating a contradiction, if there is sufficient supporting evidence to support one piece of information against a contradicting low-supported piece of information, do not count that as a contradiction. | F13: Universe edits (if any) are internally consistent and coherent across services, including dates, names, and storyline continuity. | G13: TRUE
A14: Oracle Events (OEs) | B14: OE Accuracy | C14: Auditors should verify OEs against the universe data using the Explorer or Sandbox. Each OE should reference the correct tool, correct service, correct parameters, and correct expected data. An OE that describes "look up Fatimah's relocations in Linear" when relocation records are actually in the CRM is inaccurate — the data exists but the OE points to the wrong place. OE Accuracy is distinct from OE Completeness: completeness checks whether steps are missing; accuracy checks whether the steps that exist are correct. | D14: N/A | E14: [Non-Fail - Minor OE Inaccuracies] OEs are substantively correct but contain minor imprecisions (e.g., slightly wrong parameter name that doesn't change the outcome, approximate rather than exact expected values for freetext fields). [Non-Fail - Inaccurate Oracle Events] One or more OEs reference the wrong tool, wrong service, wrong parameters, or wrong expected data. The described steps would not produce the correct results if followed literally (e.g., searching the wrong service for data that lives elsewhere, expecting data that doesn't match the universe, specifying incorrect entity names or identifiers). | F14: All OEs are factually accurate. Tools, services, parameters, and expected data match the universe. Following the OEs literally would produce a correct trajectory. | G14: TRUE
A15: Oracle Events (OEs) | B15: OE Completeness | C15: Additional Notes: OEs are the key steps a correct agent would take. They serve two purposes: (1) prove solvability, and (2) generate TS and QC rubrics. Each OE should note: what action happens, what info is discovered, what tool is used, and what parameters matter. OEs describe tool-use steps — not what the final response should say. | D15: N/A | E15: [Non-Fail - Incomplete Oracle Events] - OEs are missing critical steps needed to solve the task (e.g., no step describing how key info is retrieved, or how required action is executed). | F15: OEs describe the full critical path: key discovery steps + dependency chain(s) + required write action(s). | G15: TRUE
A16: Rubrics | B16: Overall Rubric Quality | D16: Use the number of criteria that the CB wrote as the denominator while calculating % values. See the additional notes section for the numerator. Do NOT double count criteria while tallying even if it has multiple issues. [Fail - 10%+ Major Rubric Errors] More than 10% (>10%) of the criteria contain major issues [Fail - 15%+ Moderate Rubric Errors] More than 15% (>15%) of the criteria contain moderate or major issues [Fail - 20%+ Minor Rubric Errors] More than 20% (>20%) of the criteria contain minor or moderate or major issues | E16: [Non-Fail - Up to 10% Major Errors] Up to 10% (<=10%) of the criteria contain major issues [Non-Fail - Up to 15% Moderate Errors] Up to 15% (<=15%) of criteria contain moderate or major issues (with major issues contributing lower than 5%) [Non-Fail - 5-20% Minor Errors] Between 5 and 20% (>=5% and <=20%) of criteria contain minor or moderate or major issues (with major issues contributing lower than 5% and moderate issues contributing lower than 15%) | F16: - Less than 5% (<5%) of the rubrics have minor issues - No major or moderate issues | G16: TRUE
A17: Rubrics | B17: Rubric Category Balance | C17: Outcome rubrics check final correctness (was the result right?). Process rubrics = Tool Selection + Query Construction (did the agent use the right tools with the right parameters?). Target ratio is approximately 80% Outcome, 20% Process. | D17: [Fail - No Outcome Rubrics] - The rubric set contains zero Outcome rubrics. [Fail - Process-Heavy] - More than 50% of rubrics are Process (Tool Selection + Query Construction), with Outcome rubrics underrepresented. [Fail - Missing Grounding Check] Investigation-heavy task has no grounding-check rubric verifying the agent retrieved data before reporting it. | F17: Approximately 80% or more of rubrics are Outcome. Process rubrics (TS + QC) are present but limited to critical oracle-event steps. | G17: TRUE
A18: Trajectory | B18: Tool Call Count | C18: Important note for auditors: During the QH audits, this criterion should not be evaluated. | D18: [Fail - Insufficient Tool Calls] - All trajectories contains fewer than 30 tool calls | E18: [Non-Fail - Below Target Tool Calls] - At least one trajectory contains 30–39 tool calls. The task elicits broad exploration but falls slightly short of the 40-call complexity target. | F18: At least one trajectory contains 40+ tool calls, reflecting genuine cross-service investigation and action complexity. | G18: TRUE
A19: Trajectory | B19: Agent Failure Rate | C19: At least 4 of the agent runs need to fail the prompt. A failure is defined as the model failing at least one valid outcome rubric. Process rubric failures are not model failures. | D19: [Fail - Too Easy] - More than 2 of 6 runs pass all valid outcome rubrics (i.e., pass@1 > 40%) | F19: 0–2 of 6 runs pass all outcome rubrics (pass@1 ≤ 40%), proving the task is sufficiently difficult | G19: TRUE

Sheet TBC Change Log

Sheet Transform
A1: Order | B1: Task Type | C1: Dimension | D1: Sub-Dimension | E1: Additional Notes for Auditors | F1: 1 | G1: 3 | H1: 5 | I1: revision/addition | K1: Order | L1: Task Type | M1: Dimension | N1: Sub-Dimension | O1: Additional Notes for Auditors | P1: 1 | Q1: 3 | R1: 5 | S1: revision/addition | U1: Task Type | V1: Dimension | W1: Sub-Dimension | X1: 1 | Y1: 3 | Z1: 5
A2: ='2. Dimension Definition'!D6 -> 1 | B2: ='2. Dimension Definition'!A6 -> All | C2: ='2. Dimension Definition'!B6 -> Prompt | D2: ='2. Dimension Definition'!C6 -> Unique Ground Truth | E2: =if(len('2. Dimension Definition'!E6)>0,'2. Dimension Definition'!E6,'2. Dimension Definition'!E6) | F2: =if(len('2. Dimension Definition'!G6)>0,'2. Dimension Definition'!G6,'2. Dimension Definition'!F6) -> Fail - Multiple Valid Answers] - The prompt can reasonably produce two or more different correct answers, and the prompt does not clearly indicate which answer is intended. | G2: =if(len('2. Dimension Definition'!I6)>0,'2. Dimension Definition'!I6,'2. Dimension Definition'!H6) -> [Non-Fail - Multiple Valid Answers] The prompt is ambiguous, but there is either: a leading interpretation that the majority of people would pick if polled, or there are two different valid interpretations where making a small, logically defensible assumption would clarify which was intended by the user. | H2: =if(len('2. Dimension Definition'!K6)>0,'2. Dimension Definition'!K6,'2. Dimension Definition'!J6) -> - The prompt has a unique ground truth answer. All the experts on the subject would come to the same conclusion | I2: ='2. Dimension Definition'!L6 -> FALSE | K2: =IFERROR(__xludf.DUMMYFUNCTION("unique(filter(A2:I1002,B2:B1002<>""""))"),1.0) -> 1 | L2: =IFERROR(__xludf.DUMMYFUNCTION("""COMPUTED_VALUE"""),"All") -> All | M2: =IFERROR(__xludf.DUMMYFUNCTION("""COMPUTED_VALUE"""),"Prompt") -> Prompt | N2: =IFERROR(__xludf.DUMMYFUNCTION("""COMPUTED_VALUE"""),"Unique Ground Truth") -> Unique Ground Truth | P2: =IFERROR(__xludf.DUMMYFUNCTION("""COMPUTED_VALUE"""),"Fail - Multiple Valid Answers] - The prompt can reasonably produce two or more different correct answers, and the prompt does not clearly indicate which answer is intended.") -> Fail - Multiple Valid Answers] - The prompt can reasonably produce two or more different correct answers, and the prompt does not clearly indicate which answer is intended. | Q2: =IFERROR(__xludf.DUMMYFUNCTION("""COMPUTED_VALUE"""),"[Non-Fail - Multiple Valid Answers] The prompt is ambiguous, but there is either: a leading interpretation that the majority of people would pick if polled, or there are two different valid interpretations where making a small, logically defensible assump"&"tion would clarify which was intended by the user.") -> [Non-Fail - Multiple Valid Answers] The prompt is ambiguous, but there is either: a leading interpretation that the majority of people would pick if polled, or there are two different valid interpretations where making a small, logically defensible assumption would clarify which was intended by the user. | R2: =IFERROR(__xludf.DUMMYFUNCTION("""COMPUTED_VALUE"""),"- The prompt has a unique ground truth answer. All the experts on the subject would come to the same conclusion") -> - The prompt has a unique ground truth answer. All the experts on the subject would come to the same conclusion | S2: =IFERROR(__xludf.DUMMYFUNCTION("""COMPUTED_VALUE"""),FALSE) -> FALSE
A3: ='2. Dimension Definition'!D7 -> 1 | B3: ='2. Dimension Definition'!A7 -> SFT | C3: ='2. Dimension Definition'!B7 -> Prompt | D3: ='2. Dimension Definition'!C7 -> Prompt Clarity and Specificity | E3: =if(len('2. Dimension Definition'!E7)>0,'2. Dimension Definition'!E7,'2. Dimension Definition'!E7) | F3: =if(len('2. Dimension Definition'!G7)>0,'2. Dimension Definition'!G7,'2. Dimension Definition'!F7) -> [Fail - Major Clarity / Specificity Issues] - It's not clear what is being asked, the prompt is extremely difficult to follow, or is overly vague; the user intent cannot be reasonably understood from the prompt. - Major details are missing that are needed to answer the prompt and cannot be reasonably assumed | G3: =if(len('2. Dimension Definition'!I7)>0,'2. Dimension Definition'!I7,'2. Dimension Definition'!H7) -> [Non-Fail Minor Clarity / Specificity Issues] - It's mostly clear what is being asked but the request could reasonably be interpreted multiple ways | H3: =if(len('2. Dimension Definition'!K7)>0,'2. Dimension Definition'!K7,'2. Dimension Definition'!J7) -> - There is little to no room for misinterpretation of the specific request - Prompt has a specific request that doesn't require more than one minor assumption to answer it | I3: ='2. Dimension Definition'!L7 -> FALSE | K3: =IFERROR(__xludf.DUMMYFUNCTION("""COMPUTED_VALUE"""),1.0) -> 1 | L3: =IFERROR(__xludf.DUMMYFUNCTION("""COMPUTED_VALUE"""),"SFT") -> SFT | M3: =IFERROR(__xludf.DUMMYFUNCTION("""COMPUTED_VALUE"""),"Prompt") -> Prompt | N3: =IFERROR(__xludf.DUMMYFUNCTION("""COMPUTED_VALUE"""),"Prompt Clarity and Specificity") -> Prompt Clarity and Specificity | P3: =IFERROR(__xludf.DUMMYFUNCTION("""COMPUTED_VALUE"""),"[Fail - Major Clarity / Specificity Issues] - It's not clear what is being asked, the prompt is extremely difficult to follow, or is overly vague; the user intent cannot be reasonably understood from the prompt. - Major details are missing that are neede"&"d to answer the prompt and cannot be reasonably assumed") -> [Fail - Major Clarity / Specificity Issues] - It's not clear what is being asked, the prompt is extremely difficult to follow, or is overly vague; the user intent cannot be reasonably understood from the prompt. - Major details are missing that are needed to answer the prompt and cannot be reasonably assumed | Q3: =IFERROR(__xludf.DUMMYFUNCTION("""COMPUTED_VALUE"""),"[Non-Fail Minor Clarity / Specificity Issues] - It's mostly clear what is being asked but the request could reasonably be interpreted multiple ways ") -> [Non-Fail Minor Clarity / Specificity Issues] - It's mostly clear what is being asked but the request could reasonably be interpreted multiple ways | R3: =IFERROR(__xludf.DUMMYFUNCTION("""COMPUTED_VALUE"""),"- There is little to no room for misinterpretation of the specific request - Prompt has a specific request that doesn't require more than one minor assumption to answer it") -> - There is little to no room for misinterpretation of the specific request - Prompt has a specific request that doesn't require more than one minor assumption to answer it | S3: =IFERROR(__xludf.DUMMYFUNCTION("""COMPUTED_VALUE"""),FALSE) -> FALSE
A4: ='2. Dimension Definition'!D8 -> 1 | B4: ='2. Dimension Definition'!A8 -> SFT | C4: ='2. Dimension Definition'!B8 -> Prompt | D4: ='2. Dimension Definition'!C8 -> Contrived / Unnatural Prompts | E4: =if(len('2. Dimension Definition'!E8)>0,'2. Dimension Definition'!E8,'2. Dimension Definition'!E8) -> This should check for artificial difficulty vs. natural complexity. Contrived examples include: demanding exact timestamps ("Find the email from January 15th at 3:47 PM"), requiring arbitrary format constraints ("Respond in exactly 3 sentences using passive voice"), or asking the agent to do something no real employee would do ("Intentionally send an incorrect email to test error handling"). Natural difficulty comes from entity confusion, scattered information, conflicting data across services, and hidden root causes. Prompts written as step-by-step command lists ("First search emails, then check CRM…") should also be considered contrived. | F4: =if(len('2. Dimension Definition'!G8)>0,'2. Dimension Definition'!G8,'2. Dimension Definition'!F8) -> [Fail - Contrived / Unnatural Prompt] - Prompt is contrived or otherwise unnatural note: prompts such as riddles that are intentionally constraints/details laden should not be considered contrived. | G4: =if(len('2. Dimension Definition'!I8)>0,'2. Dimension Definition'!I8,'2. Dimension Definition'!H8) -> [Non-Fail - Somewhat Contrived / Unnatural Prompt] - Prompt is somewhat contrived or is somewhat unnatural note: prompts such as riddles that are intentionally constraints/details laden should not be considered contrived. | H4: =if(len('2. Dimension Definition'!K8)>0,'2. Dimension Definition'!K8,'2. Dimension Definition'!J8) -> - The prompt is neither contrived or unnatural | I4: ='2. Dimension Definition'!L8 -> FALSE | K4: =IFERROR(__xludf.DUMMYFUNCTION("""COMPUTED_VALUE"""),1.0) -> 1 | L4: =IFERROR(__xludf.DUMMYFUNCTION("""COMPUTED_VALUE"""),"SFT") -> SFT | M4: =IFERROR(__xludf.DUMMYFUNCTION("""COMPUTED_VALUE"""),"Prompt") -> Prompt | N4: =IFERROR(__xludf.DUMMYFUNCTION("""COMPUTED_VALUE"""),"Contrived / Unnatural Prompts") -> Contrived / Unnatural Prompts | O4: =IFERROR(__xludf.DUMMYFUNCTION("""COMPUTED_VALUE"""),"This should check for artificial difficulty vs. natural complexity. Contrived examples include: demanding exact timestamps (""Find the email from January 15th at 3:47 PM""), requiring arbitrary format constraints (""Respond in exactly 3 sentences using pa"&"ssive voice""), or asking the agent to do something no real employee would do (""Intentionally send an incorrect email to test error handling""). Natural difficulty comes from entity confusion, scattered information, conflicting data across services, and "&"hidden root causes. Prompts written as step-by-step command lists (""First search emails, then check CRM…"") should also be considered contrived.") -> This should check for artificial difficulty vs. natural complexity. Contrived examples include: demanding exact timestamps ("Find the email from January 15th at 3:47 PM"), requiring arbitrary format constraints ("Respond in exactly 3 sentences using passive voice"), or asking the agent to do something no real employee would do ("Intentionally send an incorrect email to test error handling"). Natural difficulty comes from entity confusion, scattered information, conflicting data across services, and hidden root causes. Prompts written as step-by-step command lists ("First search emails, then check CRM…") should also be considered contrived. | P4: =IFERROR(__xludf.DUMMYFUNCTION("""COMPUTED_VALUE"""),"[Fail - Contrived / Unnatural Prompt] - Prompt is contrived or otherwise unnatural note: prompts such as riddles that are intentionally constraints/details laden should not be considered contrived. ") -> [Fail - Contrived / Unnatural Prompt] - Prompt is contrived or otherwise unnatural note: prompts such as riddles that are intentionally constraints/details laden should not be considered contrived. | Q4: =IFERROR(__xludf.DUMMYFUNCTION("""COMPUTED_VALUE"""),"[Non-Fail - Somewhat Contrived / Unnatural Prompt] - Prompt is somewhat contrived or is somewhat unnatural note: prompts such as riddles that are intentionally constraints/details laden should not be considered contrived. ") -> [Non-Fail - Somewhat Contrived / Unnatural Prompt] - Prompt is somewhat contrived or is somewhat unnatural note: prompts such as riddles that are intentionally constraints/details laden should not be considered contrived. | R4: =IFERROR(__xludf.DUMMYFUNCTION("""COMPUTED_VALUE"""),"- The prompt is neither contrived or unnatural") -> - The prompt is neither contrived or unnatural | S4: =IFERROR(__xludf.DUMMYFUNCTION("""COMPUTED_VALUE"""),FALSE) -> FALSE
A5: ='2. Dimension Definition'!D9 -> 1 | B5: ='2. Dimension Definition'!A9 -> SFT | C5: ='2. Dimension Definition'!B9 -> Prompt | D5: ='2. Dimension Definition'!C9 -> Truthfulness | E5: =if(len('2. Dimension Definition'!E9)>0,'2. Dimension Definition'!E9,'2. Dimension Definition'!E9) | F5: =if(len('2. Dimension Definition'!G9)>0,'2. Dimension Definition'!G9,'2. Dimension Definition'!F9) -> [Fail - Major Factual Errors] - The prompt contains 1 or more major factual errors [Fail - Minor Factual Errors] - The prompt contains 2 or more minor factual errors (e.g., statements irrelevant to the fulfillment of the prompt's request) | G5: =if(len('2. Dimension Definition'!I9)>0,'2. Dimension Definition'!I9,'2. Dimension Definition'!H9) -> [Non-Fail - Minor Factual Errors] - The prompt contains 1 minor factual errors. | H5: =if(len('2. Dimension Definition'!K9)>0,'2. Dimension Definition'!K9,'2. Dimension Definition'!J9) -> - The prompt has no factual errors - The prompt has no misleading statements | I5: ='2. Dimension Definition'!L9 -> FALSE | K5: =IFERROR(__xludf.DUMMYFUNCTION("""COMPUTED_VALUE"""),1.0) -> 1 | L5: =IFERROR(__xludf.DUMMYFUNCTION("""COMPUTED_VALUE"""),"SFT") -> SFT | M5: =IFERROR(__xludf.DUMMYFUNCTION("""COMPUTED_VALUE"""),"Prompt") -> Prompt | N5: =IFERROR(__xludf.DUMMYFUNCTION("""COMPUTED_VALUE"""),"Truthfulness") -> Truthfulness | P5: =IFERROR(__xludf.DUMMYFUNCTION("""COMPUTED_VALUE"""),"[Fail - Major Factual Errors] - The prompt contains 1 or more major factual errors [Fail - Minor Factual Errors] - The prompt contains 2 or more minor factual errors (e.g., statements irrelevant to the fulfillment of the prompt's request)") -> [Fail - Major Factual Errors] - The prompt contains 1 or more major factual errors [Fail - Minor Factual Errors] - The prompt contains 2 or more minor factual errors (e.g., statements irrelevant to the fulfillment of the prompt's request) | Q5: =IFERROR(__xludf.DUMMYFUNCTION("""COMPUTED_VALUE"""),"[Non-Fail - Minor Factual Errors] - The prompt contains 1 minor factual errors.") -> [Non-Fail - Minor Factual Errors] - The prompt contains 1 minor factual errors. | R5: =IFERROR(__xludf.DUMMYFUNCTION("""COMPUTED_VALUE"""),"- The prompt has no factual errors - The prompt has no misleading statements") -> - The prompt has no factual errors - The prompt has no misleading statements | S5: =IFERROR(__xludf.DUMMYFUNCTION("""COMPUTED_VALUE"""),FALSE) -> FALSE
A6: ='2. Dimension Definition'!D10 -> 1 | B6: ='2. Dimension Definition'!A10 | C6: ='2. Dimension Definition'!B10 | D6: ='2. Dimension Definition'!C10 | E6: =if(len('2. Dimension Definition'!E10)>0,'2. Dimension Definition'!E10,'2. Dimension Definition'!E10) | F6: =if(len('2. Dimension Definition'!G10)>0,'2. Dimension Definition'!G10,'2. Dimension Definition'!F10) | G6: =if(len('2. Dimension Definition'!I10)>0,'2. Dimension Definition'!I10,'2. Dimension Definition'!H10) | H6: =if(len('2. Dimension Definition'!K10)>0,'2. Dimension Definition'!K10,'2. Dimension Definition'!J10) | I6: ='2. Dimension Definition'!L10 | K6: =IFERROR(__xludf.DUMMYFUNCTION("""COMPUTED_VALUE"""),1.0) -> 1 | L6: =IFERROR(__xludf.DUMMYFUNCTION("""COMPUTED_VALUE"""),"RL") -> RL | M6: =IFERROR(__xludf.DUMMYFUNCTION("""COMPUTED_VALUE"""),"Prompt") -> Prompt | N6: =IFERROR(__xludf.DUMMYFUNCTION("""COMPUTED_VALUE"""),"Feasibility") -> Feasibility | P6: =IFERROR(__xludf.DUMMYFUNCTION("""COMPUTED_VALUE"""),"[Fail - Prompt Impractical Request] - Prompt contains an impractical request that can't be answered by an LLM in a single response [Fail - Prompt Impossible Request] - Prompt has at least one request that can't be fulfilled at all [Fail - Prompt Conflic"&"ting Instructions] - Prompt gives instructions that conflict/contradict with itself that can't be fulfilled simultaneously [Fail - Prompt Feasibility with Tools] - Prompt contains an impractical or impossible request that can't be answered by the tools a"&"vailable or enabled for the task") -> [Fail - Prompt Impractical Request] - Prompt contains an impractical request that can't be answered by an LLM in a single response [Fail - Prompt Impossible Request] - Prompt has at least one request that can't be fulfilled at all [Fail - Prompt Conflicting Instructions] - Prompt gives instructions that conflict/contradict with itself that can't be fulfilled simultaneously [Fail - Prompt Feasibility with Tools] - Prompt contains an impractical or impossible request that can't be answered by the tools available or enabled for the task | Q6: =IFERROR(__xludf.DUMMYFUNCTION("""COMPUTED_VALUE"""),"Non-Fail - Prompt Impractical Secondary Request] - There are multiple requests in the prompt and it's verging on being impractical for a model to answer it in a single response, but the core request of the prompt can be fulfilled with minor concessions on"&" the secondary requests") -> Non-Fail - Prompt Impractical Secondary Request] - There are multiple requests in the prompt and it's verging on being impractical for a model to answer it in a single response, but the core request of the prompt can be fulfilled with minor concessions on the secondary requests | R6: =IFERROR(__xludf.DUMMYFUNCTION("""COMPUTED_VALUE"""),"- The prompt is completely actionable by an LLM agent. - The prompt contains no conflicting instructions/statements") -> - The prompt is completely actionable by an LLM agent. - The prompt contains no conflicting instructions/statements | S6: =IFERROR(__xludf.DUMMYFUNCTION("""COMPUTED_VALUE"""),TRUE) -> TRUE
A7: ='2. Dimension Definition'!D11 -> 1 | B7: ='2. Dimension Definition'!A11 | C7: ='2. Dimension Definition'!B11 | D7: ='2. Dimension Definition'!C11 | E7: =if(len('2. Dimension Definition'!E11)>0,'2. Dimension Definition'!E11,'2. Dimension Definition'!E11) | F7: =if(len('2. Dimension Definition'!G11)>0,'2. Dimension Definition'!G11,'2. Dimension Definition'!F11) | G7: =if(len('2. Dimension Definition'!I11)>0,'2. Dimension Definition'!I11,'2. Dimension Definition'!H11) | H7: =if(len('2. Dimension Definition'!K11)>0,'2. Dimension Definition'!K11,'2. Dimension Definition'!J11) | I7: ='2. Dimension Definition'!L11 | K7: =IFERROR(__xludf.DUMMYFUNCTION("""COMPUTED_VALUE"""),2.0) -> 2 | L7: =IFERROR(__xludf.DUMMYFUNCTION("""COMPUTED_VALUE"""),"RL") -> RL | M7: =IFERROR(__xludf.DUMMYFUNCTION("""COMPUTED_VALUE"""),"Prompt") -> Prompt | N7: =IFERROR(__xludf.DUMMYFUNCTION("""COMPUTED_VALUE"""),"Tool use and Cross-service requirement") -> Tool use and Cross-service requirement | P7: =IFERROR(__xludf.DUMMYFUNCTION("""COMPUTED_VALUE"""),"[Fail - Tool Dependence] - The prompt can be answered without having to make any tool calls (either through basic reasoning or general knowledge) [Fail - Cross-service Requirement] - Prompt can be fully resolved within a single service (e.g., just email "&"or just CRM), or only trivially touches a second service.") -> [Fail - Tool Dependence] - The prompt can be answered without having to make any tool calls (either through basic reasoning or general knowledge) [Fail - Cross-service Requirement] - Prompt can be fully resolved within a single service (e.g., just email or just CRM), or only trivially touches a second service. | Q7: =IFERROR(__xludf.DUMMYFUNCTION("""COMPUTED_VALUE"""),"N/A") -> N/A | R7: =IFERROR(__xludf.DUMMYFUNCTION("""COMPUTED_VALUE"""),"- Prompt requires investigation across 2+ services to answer correctly (e.g., facts needed are scattered and must be reconciled).") -> - Prompt requires investigation across 2+ services to answer correctly (e.g., facts needed are scattered and must be reconciled). | S7: =IFERROR(__xludf.DUMMYFUNCTION("""COMPUTED_VALUE"""),TRUE) -> TRUE
A8: ='2. Dimension Definition'!D11 -> 1 | B8: ='2. Dimension Definition'!A12 | C8: ='2. Dimension Definition'!B12 | D8: ='2. Dimension Definition'!C12 | E8: =if(len('2. Dimension Definition'!E12)>0,'2. Dimension Definition'!E12,'2. Dimension Definition'!E12) | F8: =if(len('2. Dimension Definition'!G12)>0,'2. Dimension Definition'!G12,'2. Dimension Definition'!F12) | G8: =if(len('2. Dimension Definition'!I12)>0,'2. Dimension Definition'!I12,'2. Dimension Definition'!H12) | H8: =if(len('2. Dimension Definition'!K12)>0,'2. Dimension Definition'!K12,'2. Dimension Definition'!J12) | I8: ='2. Dimension Definition'!L12 | K8: =IFERROR(__xludf.DUMMYFUNCTION("""COMPUTED_VALUE"""),1.0) -> 1 | L8: =IFERROR(__xludf.DUMMYFUNCTION("""COMPUTED_VALUE"""),"RL") -> RL | M8: =IFERROR(__xludf.DUMMYFUNCTION("""COMPUTED_VALUE"""),"Prompt") -> Prompt | N8: =IFERROR(__xludf.DUMMYFUNCTION("""COMPUTED_VALUE"""),"Explicit Tool Mention") -> Explicit Tool Mention | P8: =IFERROR(__xludf.DUMMYFUNCTION("""COMPUTED_VALUE"""),"[Fail - Explicit Tool Mention] The prompt explicitly mentions a specific tool name The prompt unnaturally refers to an MCP server in an inorganic, technical manner “Use the Airbnb tool to…” (technical, unnatural) “I want to use Airbnb to find…” (general, "&"natural)") -> [Fail - Explicit Tool Mention] The prompt explicitly mentions a specific tool name The prompt unnaturally refers to an MCP server in an inorganic, technical manner “Use the Airbnb tool to…” (technical, unnatural) “I want to use Airbnb to find…” (general, natural) | Q8: =IFERROR(__xludf.DUMMYFUNCTION("""COMPUTED_VALUE"""),"N/A") -> N/A | R8: =IFERROR(__xludf.DUMMYFUNCTION("""COMPUTED_VALUE"""),"- The prompt does not explicitly state the use of tools ") -> - The prompt does not explicitly state the use of tools | S8: =IFERROR(__xludf.DUMMYFUNCTION("""COMPUTED_VALUE"""),TRUE) -> TRUE
A9: ='2. Dimension Definition'!D12 -> 2 | B9: ='2. Dimension Definition'!A13 | C9: ='2. Dimension Definition'!B13 | D9: ='2. Dimension Definition'!C13 | E9: =if(len('2. Dimension Definition'!E13)>0,'2. Dimension Definition'!E13,'2. Dimension Definition'!E13) | F9: =if(len('2. Dimension Definition'!G13)>0,'2. Dimension Definition'!G13,'2. Dimension Definition'!F13) | G9: =if(len('2. Dimension Definition'!I13)>0,'2. Dimension Definition'!I13,'2. Dimension Definition'!H13) | H9: =if(len('2. Dimension Definition'!K13)>0,'2. Dimension Definition'!K13,'2. Dimension Definition'!J13) | I9: ='2. Dimension Definition'!L13 | K9: =IFERROR(__xludf.DUMMYFUNCTION("""COMPUTED_VALUE"""),2.0) -> 2 | L9: =IFERROR(__xludf.DUMMYFUNCTION("""COMPUTED_VALUE"""),"RL") -> RL | M9: =IFERROR(__xludf.DUMMYFUNCTION("""COMPUTED_VALUE"""),"Prompt") -> Prompt | N9: =IFERROR(__xludf.DUMMYFUNCTION("""COMPUTED_VALUE"""),"Investigation + Action") -> Investigation + Action | P9: =IFERROR(__xludf.DUMMYFUNCTION("""COMPUTED_VALUE"""),"[Fail - Action Missing] - Prompt only asks for a summary/report/research with no required action. [Fail - Pre-solved] - Prompt tells agent the root cause and no investigation is needed.") -> [Fail - Action Missing] - Prompt only asks for a summary/report/research with no required action. [Fail - Pre-solved] - Prompt tells agent the root cause and no investigation is needed. | Q9: =IFERROR(__xludf.DUMMYFUNCTION("""COMPUTED_VALUE"""),"N/A") -> N/A | R9: =IFERROR(__xludf.DUMMYFUNCTION("""COMPUTED_VALUE"""),"Prompt clearly requires investigtion and at least one concrete action (email, ticket creation/update, booking, calendar scheduling, CRM update, etc.), and it logically follows from investigation.") -> Prompt clearly requires investigtion and at least one concrete action (email, ticket creation/update, booking, calendar scheduling, CRM update, etc.), and it logically follows from investigation. | S9: =IFERROR(__xludf.DUMMYFUNCTION("""COMPUTED_VALUE"""),TRUE) -> TRUE
A10: ='2. Dimension Definition'!D13 -> 2 | B10: ='2. Dimension Definition'!A14 | C10: ='2. Dimension Definition'!B14 | D10: ='2. Dimension Definition'!C14 | E10: =if(len('2. Dimension Definition'!E14)>0,'2. Dimension Definition'!E14,'2. Dimension Definition'!E14) | F10: =if(len('2. Dimension Definition'!G14)>0,'2. Dimension Definition'!G14,'2. Dimension Definition'!F14) | G10: =if(len('2. Dimension Definition'!I14)>0,'2. Dimension Definition'!I14,'2. Dimension Definition'!H14) | H10: =if(len('2. Dimension Definition'!K14)>0,'2. Dimension Definition'!K14,'2. Dimension Definition'!J14) | I10: ='2. Dimension Definition'!L14 | K10: =IFERROR(__xludf.DUMMYFUNCTION("""COMPUTED_VALUE"""),2.0) -> 2 | L10: =IFERROR(__xludf.DUMMYFUNCTION("""COMPUTED_VALUE"""),"RL") -> RL | M10: =IFERROR(__xludf.DUMMYFUNCTION("""COMPUTED_VALUE"""),"Prompt") -> Prompt | N10: =IFERROR(__xludf.DUMMYFUNCTION("""COMPUTED_VALUE"""),"Coherence") -> Coherence | O10: =IFERROR(__xludf.DUMMYFUNCTION("""COMPUTED_VALUE"""),"An example of failing bolt-on requests: ""Check weather in Miami, update my calendar for next week, email Marcus about Q3, and look up Seattle flights."" Why it fails: Four unrelated requests stapled together. Each sub-request should causally flow from "&"the same situation. How to tell if your prompt is ""bolted"": Remove any one sentence. If the rest still makes perfect sense without it, that sentence is a bolt-on") -> An example of failing bolt-on requests: "Check weather in Miami, update my calendar for next week, email Marcus about Q3, and look up Seattle flights." Why it fails: Four unrelated requests stapled together. Each sub-request should causally flow from the same situation. How to tell if your prompt is "bolted": Remove any one sentence. If the rest still makes perfect sense without it, that sentence is a bolt-on | P10: =IFERROR(__xludf.DUMMYFUNCTION("""COMPUTED_VALUE"""),"[Fail - Bolt-on requests] - Contains unrelated bolt-on requests; removing a sentence doesn’t change the rest.") -> [Fail - Bolt-on requests] - Contains unrelated bolt-on requests; removing a sentence doesn’t change the rest. | Q10: =IFERROR(__xludf.DUMMYFUNCTION("""COMPUTED_VALUE"""),"N/A") -> N/A | R10: =IFERROR(__xludf.DUMMYFUNCTION("""COMPUTED_VALUE"""),"One cohesive situation; stacked asks all tie back to the same purpose.") -> One cohesive situation; stacked asks all tie back to the same purpose. | S10: =IFERROR(__xludf.DUMMYFUNCTION("""COMPUTED_VALUE"""),TRUE) -> TRUE
A11: ='2. Dimension Definition'!D14 -> 2 | B11: ='2. Dimension Definition'!A15 | C11: ='2. Dimension Definition'!B15 | D11: ='2. Dimension Definition'!C15 | E11: =if(len('2. Dimension Definition'!E15)>0,'2. Dimension Definition'!E15,'2. Dimension Definition'!E15) | F11: =if(len('2. Dimension Definition'!G15)>0,'2. Dimension Definition'!G15,'2. Dimension Definition'!F15) | G11: =if(len('2. Dimension Definition'!I15)>0,'2. Dimension Definition'!I15,'2. Dimension Definition'!H15) | H11: =if(len('2. Dimension Definition'!K15)>0,'2. Dimension Definition'!K15,'2. Dimension Definition'!J15) | I11: ='2. Dimension Definition'!L15 | K11: =IFERROR(__xludf.DUMMYFUNCTION("""COMPUTED_VALUE"""),3.0) -> 3 | L11: =IFERROR(__xludf.DUMMYFUNCTION("""COMPUTED_VALUE"""),"RL") -> RL | M11: =IFERROR(__xludf.DUMMYFUNCTION("""COMPUTED_VALUE"""),"Universe") -> Universe | N11: =IFERROR(__xludf.DUMMYFUNCTION("""COMPUTED_VALUE"""),"Universe Feasibility (Data Exists)") -> Universe Feasibility (Data Exists) | O11: =IFERROR(__xludf.DUMMYFUNCTION("""COMPUTED_VALUE"""),"Auditors should check the Universe Explorer or Sandbox to verify that key data needed for the prompt exists. ") -> Auditors should check the Universe Explorer or Sandbox to verify that key data needed for the prompt exists. | P11: =IFERROR(__xludf.DUMMYFUNCTION("""COMPUTED_VALUE"""),"[Fail - Missing Universe Data] - Task depends on key facts/entities/events that do not exist in the universe (or cannot be retrieved with available tools), making the task unsolvable.") -> [Fail - Missing Universe Data] - Task depends on key facts/entities/events that do not exist in the universe (or cannot be retrieved with available tools), making the task unsolvable. | Q11: =IFERROR(__xludf.DUMMYFUNCTION("""COMPUTED_VALUE"""),"N/A") -> N/A | R11: =IFERROR(__xludf.DUMMYFUNCTION("""COMPUTED_VALUE"""),"All core facts required to solve the task exist in the universe and are retrievable via tools.") -> All core facts required to solve the task exist in the universe and are retrievable via tools. | S11: =IFERROR(__xludf.DUMMYFUNCTION("""COMPUTED_VALUE"""),TRUE) -> TRUE
A12: ='2. Dimension Definition'!D15 -> 3 | B12: ='2. Dimension Definition'!A16 | C12: ='2. Dimension Definition'!B16 | D12: ='2. Dimension Definition'!C16 | E12: =if(len('2. Dimension Definition'!E16)>0,'2. Dimension Definition'!E16,'2. Dimension Definition'!E16) | F12: =if(len('2. Dimension Definition'!G16)>0,'2. Dimension Definition'!G16,'2. Dimension Definition'!F16) | G12: =if(len('2. Dimension Definition'!I16)>0,'2. Dimension Definition'!I16,'2. Dimension Definition'!H16) | H12: =if(len('2. Dimension Definition'!K16)>0,'2. Dimension Definition'!K16,'2. Dimension Definition'!J16) | I12: ='2. Dimension Definition'!L16 | K12: =IFERROR(__xludf.DUMMYFUNCTION("""COMPUTED_VALUE"""),3.0) -> 3 | L12: =IFERROR(__xludf.DUMMYFUNCTION("""COMPUTED_VALUE"""),"RL") -> RL | M12: =IFERROR(__xludf.DUMMYFUNCTION("""COMPUTED_VALUE"""),"Universe") -> Universe | N12: =IFERROR(__xludf.DUMMYFUNCTION("""COMPUTED_VALUE"""),"Cross-service Coherence") -> Cross-service Coherence | O12: =IFERROR(__xludf.DUMMYFUNCTION("""COMPUTED_VALUE"""),"Auditors should refer to the changelog table in the sandbox to check changes that were made to the universe (if edits were made).") -> Auditors should refer to the changelog table in the sandbox to check changes that were made to the universe (if edits were made). | P12: =IFERROR(__xludf.DUMMYFUNCTION("""COMPUTED_VALUE"""),"[Fail - Incoherent Universe Changes] - Universe edits create contradictions that break solvability or realism (e.g., mismatched names across email vs CRM, impossible dates, entities referenced in one service but not elsewhere when required). Note: When e"&"valuating a contradiction, if there is sufficient supporting evidence to support one piece of information against a contradicting low-supported piece of information, do not count that as a contradiction.") -> [Fail - Incoherent Universe Changes] - Universe edits create contradictions that break solvability or realism (e.g., mismatched names across email vs CRM, impossible dates, entities referenced in one service but not elsewhere when required). Note: When evaluating a contradiction, if there is sufficient supporting evidence to support one piece of information against a contradicting low-supported piece of information, do not count that as a contradiction. | R12: =IFERROR(__xludf.DUMMYFUNCTION("""COMPUTED_VALUE"""),"Universe edits (if any) are internally consistent and coherent across services, including dates, names, and storyline continuity.") -> Universe edits (if any) are internally consistent and coherent across services, including dates, names, and storyline continuity. | S12: =IFERROR(__xludf.DUMMYFUNCTION("""COMPUTED_VALUE"""),TRUE) -> TRUE
A13: ='2. Dimension Definition'!D16 -> 3 | B13: ='2. Dimension Definition'!A17 | C13: ='2. Dimension Definition'!B17 | D13: ='2. Dimension Definition'!C17 | E13: =if(len('2. Dimension Definition'!E17)>0,'2. Dimension Definition'!E17,'2. Dimension Definition'!E17) | F13: =if(len('2. Dimension Definition'!G17)>0,'2. Dimension Definition'!G17,'2. Dimension Definition'!F17) | G13: =if(len('2. Dimension Definition'!I17)>0,'2. Dimension Definition'!I17,'2. Dimension Definition'!H17) | H13: =if(len('2. Dimension Definition'!K17)>0,'2. Dimension Definition'!K17,'2. Dimension Definition'!J17) | I13: ='2. Dimension Definition'!L17 | K13: =IFERROR(__xludf.DUMMYFUNCTION("""COMPUTED_VALUE"""),4.0) -> 4 | L13: =IFERROR(__xludf.DUMMYFUNCTION("""COMPUTED_VALUE"""),"RL") -> RL | M13: =IFERROR(__xludf.DUMMYFUNCTION("""COMPUTED_VALUE"""),"Oracle Events (OEs)") -> Oracle Events (OEs) | N13: =IFERROR(__xludf.DUMMYFUNCTION("""COMPUTED_VALUE"""),"OE Accuracy") -> OE Accuracy | O13: =IFERROR(__xludf.DUMMYFUNCTION("""COMPUTED_VALUE"""),"Auditors should verify OEs against the universe data using the Explorer or Sandbox. Each OE should reference the correct tool, correct service, correct parameters, and correct expected data. An OE that describes ""look up Fatimah's relocations in Linear"""&" when relocation records are actually in the CRM is inaccurate — the data exists but the OE points to the wrong place. OE Accuracy is distinct from OE Completeness: completeness checks whether steps are missing; accuracy checks whether the steps that exis"&"t are correct.") -> Auditors should verify OEs against the universe data using the Explorer or Sandbox. Each OE should reference the correct tool, correct service, correct parameters, and correct expected data. An OE that describes "look up Fatimah's relocations in Linear" when relocation records are actually in the CRM is inaccurate — the data exists but the OE points to the wrong place. OE Accuracy is distinct from OE Completeness: completeness checks whether steps are missing; accuracy checks whether the steps that exist are correct. | P13: =IFERROR(__xludf.DUMMYFUNCTION("""COMPUTED_VALUE"""),"N/A") -> N/A | Q13: =IFERROR(__xludf.DUMMYFUNCTION("""COMPUTED_VALUE"""),"[Non-Fail - Minor OE Inaccuracies] OEs are substantively correct but contain minor imprecisions (e.g., slightly wrong parameter name that doesn't change the outcome, approximate rather than exact expected values for freetext fields). [Non-Fail - Inaccura"&"te Oracle Events] One or more OEs reference the wrong tool, wrong service, wrong parameters, or wrong expected data. The described steps would not produce the correct results if followed literally (e.g., searching the wrong service for data that lives els"&"ewhere, expecting data that doesn't match the universe, specifying incorrect entity names or identifiers).") -> [Non-Fail - Minor OE Inaccuracies] OEs are substantively correct but contain minor imprecisions (e.g., slightly wrong parameter name that doesn't change the outcome, approximate rather than exact expected values for freetext fields). [Non-Fail - Inaccurate Oracle Events] One or more OEs reference the wrong tool, wrong service, wrong parameters, or wrong expected data. The described steps would not produce the correct results if followed literally (e.g., searching the wrong service for data that lives elsewhere, expecting data that doesn't match the universe, specifying incorrect entity names or identifiers). | R13: =IFERROR(__xludf.DUMMYFUNCTION("""COMPUTED_VALUE"""),"All OEs are factually accurate. Tools, services, parameters, and expected data match the universe. Following the OEs literally would produce a correct trajectory.") -> All OEs are factually accurate. Tools, services, parameters, and expected data match the universe. Following the OEs literally would produce a correct trajectory. | S13: =IFERROR(__xludf.DUMMYFUNCTION("""COMPUTED_VALUE"""),TRUE) -> TRUE
A14: ='2. Dimension Definition'!D17 -> 3 | B14: ='2. Dimension Definition'!A18 | C14: ='2. Dimension Definition'!B18 | D14: ='2. Dimension Definition'!C18 | E14: =if(len('2. Dimension Definition'!E18)>0,'2. Dimension Definition'!E18,'2. Dimension Definition'!E18) | F14: =if(len('2. Dimension Definition'!G18)>0,'2. Dimension Definition'!G18,'2. Dimension Definition'!F18) | G14: =if(len('2. Dimension Definition'!I18)>0,'2. Dimension Definition'!I18,'2. Dimension Definition'!H18) | H14: =if(len('2. Dimension Definition'!K18)>0,'2. Dimension Definition'!K18,'2. Dimension Definition'!J18) | I14: ='2. Dimension Definition'!L18 | K14: =IFERROR(__xludf.DUMMYFUNCTION("""COMPUTED_VALUE"""),4.0) -> 4 | L14: =IFERROR(__xludf.DUMMYFUNCTION("""COMPUTED_VALUE"""),"RL") -> RL | M14: =IFERROR(__xludf.DUMMYFUNCTION("""COMPUTED_VALUE"""),"Oracle Events (OEs)") -> Oracle Events (OEs) | N14: =IFERROR(__xludf.DUMMYFUNCTION("""COMPUTED_VALUE"""),"OE Completeness") -> OE Completeness | O14: =IFERROR(__xludf.DUMMYFUNCTION("""COMPUTED_VALUE"""),"Additional Notes: OEs are the key steps a correct agent would take. They serve two purposes: (1) prove solvability, and (2) generate TS and QC rubrics. Each OE should note: what action happens, what info is discovered, what tool is used, and what param"&"eters matter. OEs describe tool-use steps — not what the final response should say.") -> Additional Notes: OEs are the key steps a correct agent would take. They serve two purposes: (1) prove solvability, and (2) generate TS and QC rubrics. Each OE should note: what action happens, what info is discovered, what tool is used, and what parameters matter. OEs describe tool-use steps — not what the final response should say. | P14: =IFERROR(__xludf.DUMMYFUNCTION("""COMPUTED_VALUE"""),"N/A") -> N/A | Q14: =IFERROR(__xludf.DUMMYFUNCTION("""COMPUTED_VALUE"""),"[Non-Fail - Incomplete Oracle Events] - OEs are missing critical steps needed to solve the task (e.g., no step describing how key info is retrieved, or how required action is executed).") -> [Non-Fail - Incomplete Oracle Events] - OEs are missing critical steps needed to solve the task (e.g., no step describing how key info is retrieved, or how required action is executed). | R14: =IFERROR(__xludf.DUMMYFUNCTION("""COMPUTED_VALUE"""),"OEs describe the full critical path: key discovery steps + dependency chain(s) + required write action(s).") -> OEs describe the full critical path: key discovery steps + dependency chain(s) + required write action(s). | S14: =IFERROR(__xludf.DUMMYFUNCTION("""COMPUTED_VALUE"""),TRUE) -> TRUE
A15: ='2. Dimension Definition'!D18 | B15: ='2. Dimension Definition'!A19 | C15: ='2. Dimension Definition'!B19 | D15: ='2. Dimension Definition'!C19 | E15: =if(len('2. Dimension Definition'!E19)>0,'2. Dimension Definition'!E19,'2. Dimension Definition'!E19) | F15: =if(len('2. Dimension Definition'!G19)>0,'2. Dimension Definition'!G19,'2. Dimension Definition'!F19) | G15: =if(len('2. Dimension Definition'!I19)>0,'2. Dimension Definition'!I19,'2. Dimension Definition'!H19) | H15: =if(len('2. Dimension Definition'!K19)>0,'2. Dimension Definition'!K19,'2. Dimension Definition'!J19) | I15: ='2. Dimension Definition'!L19 | K15: =IFERROR(__xludf.DUMMYFUNCTION("""COMPUTED_VALUE"""),5.0) -> 5 | L15: =IFERROR(__xludf.DUMMYFUNCTION("""COMPUTED_VALUE"""),"RL") -> RL | M15: =IFERROR(__xludf.DUMMYFUNCTION("""COMPUTED_VALUE"""),"Rubrics") -> Rubrics | N15: =IFERROR(__xludf.DUMMYFUNCTION("""COMPUTED_VALUE"""),"Overall Rubric Quality") -> Overall Rubric Quality | P15: =IFERROR(__xludf.DUMMYFUNCTION("""COMPUTED_VALUE"""),"Use the number of criteria that the CB wrote as the denominator while calculating % values. See the additional notes section for the numerator. Do NOT double count criteria while tallying even if it has multiple issues. [Fail - 10%+ Major Rubric Errors] "&"More than 10% (>10%) of the criteria contain major issues [Fail - 15%+ Moderate Rubric Errors] More than 15% (>15%) of the criteria contain moderate or major issues [Fail - 20%+ Minor Rubric Errors] More than 20% (>20%) of the criteria contain minor or "&"moderate or major issues") -> Use the number of criteria that the CB wrote as the denominator while calculating % values. See the additional notes section for the numerator. Do NOT double count criteria while tallying even if it has multiple issues. [Fail - 10%+ Major Rubric Errors] More than 10% (>10%) of the criteria contain major issues [Fail - 15%+ Moderate Rubric Errors] More than 15% (>15%) of the criteria contain moderate or major issues [Fail - 20%+ Minor Rubric Errors] More than 20% (>20%) of the criteria contain minor or moderate or major issues | Q15: =IFERROR(__xludf.DUMMYFUNCTION("""COMPUTED_VALUE"""),"[Non-Fail - Up to 10% Major Errors] Up to 10% (<=10%) of the criteria contain major issues [Non-Fail - Up to 15% Moderate Errors] Up to 15% (<=15%) of criteria contain moderate or major issues (with major issues contributing lower than 5%) [Non-Fail - 5"&"-20% Minor Errors] Between 5 and 20% (>=5% and <=20%) of criteria contain minor or moderate or major issues (with major issues contributing lower than 5% and moderate issues contributing lower than 15%) ") -> [Non-Fail - Up to 10% Major Errors] Up to 10% (<=10%) of the criteria contain major issues [Non-Fail - Up to 15% Moderate Errors] Up to 15% (<=15%) of criteria contain moderate or major issues (with major issues contributing lower than 5%) [Non-Fail - 5-20% Minor Errors] Between 5 and 20% (>=5% and <=20%) of criteria contain minor or moderate or major issues (with major issues contributing lower than 5% and moderate issues contributing lower than 15%) | R15: =IFERROR(__xludf.DUMMYFUNCTION("""COMPUTED_VALUE"""),"- Less than 5% (<5%) of the rubrics have minor issues - No major or moderate issues ") -> - Less than 5% (<5%) of the rubrics have minor issues - No major or moderate issues | S15: =IFERROR(__xludf.DUMMYFUNCTION("""COMPUTED_VALUE"""),TRUE) -> TRUE
A16: ='2. Dimension Definition'!D19 | B16: ='2. Dimension Definition'!A20 | C16: ='2. Dimension Definition'!B20 | D16: ='2. Dimension Definition'!C20 | E16: =if(len('2. Dimension Definition'!E20)>0,'2. Dimension Definition'!E20,'2. Dimension Definition'!E20) | F16: =if(len('2. Dimension Definition'!G20)>0,'2. Dimension Definition'!G20,'2. Dimension Definition'!F20) | G16: =if(len('2. Dimension Definition'!I20)>0,'2. Dimension Definition'!I20,'2. Dimension Definition'!H20) | H16: =if(len('2. Dimension Definition'!K20)>0,'2. Dimension Definition'!K20,'2. Dimension Definition'!J20) | I16: ='2. Dimension Definition'!L20 | K16: =IFERROR(__xludf.DUMMYFUNCTION("""COMPUTED_VALUE"""),5.0) -> 5 | L16: =IFERROR(__xludf.DUMMYFUNCTION("""COMPUTED_VALUE"""),"RL") -> RL | M16: =IFERROR(__xludf.DUMMYFUNCTION("""COMPUTED_VALUE"""),"Rubrics") -> Rubrics | N16: =IFERROR(__xludf.DUMMYFUNCTION("""COMPUTED_VALUE"""),"Rubric Category Balance") -> Rubric Category Balance | O16: =IFERROR(__xludf.DUMMYFUNCTION("""COMPUTED_VALUE"""),"Outcome rubrics check final correctness (was the result right?). Process rubrics = Tool Selection + Query Construction (did the agent use the right tools with the right parameters?). Target ratio is approximately 80% Outcome, 20% Process. ") -> Outcome rubrics check final correctness (was the result right?). Process rubrics = Tool Selection + Query Construction (did the agent use the right tools with the right parameters?). Target ratio is approximately 80% Outcome, 20% Process. | P16: =IFERROR(__xludf.DUMMYFUNCTION("""COMPUTED_VALUE"""),"[Fail - No Outcome Rubrics] - The rubric set contains zero Outcome rubrics. [Fail - Process-Heavy] - More than 50% of rubrics are Process (Tool Selection + Query Construction), with Outcome rubrics underrepresented. [Fail - Missing Grounding Check] Inves"&"tigation-heavy task has no grounding-check rubric verifying the agent retrieved data before reporting it.") -> [Fail - No Outcome Rubrics] - The rubric set contains zero Outcome rubrics. [Fail - Process-Heavy] - More than 50% of rubrics are Process (Tool Selection + Query Construction), with Outcome rubrics underrepresented. [Fail - Missing Grounding Check] Investigation-heavy task has no grounding-check rubric verifying the agent retrieved data before reporting it. | R16: =IFERROR(__xludf.DUMMYFUNCTION("""COMPUTED_VALUE"""),"Approximately 80% or more of rubrics are Outcome. Process rubrics (TS + QC) are present but limited to critical oracle-event steps.") -> Approximately 80% or more of rubrics are Outcome. Process rubrics (TS + QC) are present but limited to critical oracle-event steps. | S16: =IFERROR(__xludf.DUMMYFUNCTION("""COMPUTED_VALUE"""),TRUE) -> TRUE
A17: ='2. Dimension Definition'!D20 | B17: ='2. Dimension Definition'!A21 | C17: ='2. Dimension Definition'!B21 | D17: ='2. Dimension Definition'!C21 | E17: =if(len('2. Dimension Definition'!E21)>0,'2. Dimension Definition'!E21,'2. Dimension Definition'!E21) | F17: =if(len('2. Dimension Definition'!G21)>0,'2. Dimension Definition'!G21,'2. Dimension Definition'!F21) | G17: =if(len('2. Dimension Definition'!I21)>0,'2. Dimension Definition'!I21,'2. Dimension Definition'!H21) | H17: =if(len('2. Dimension Definition'!K21)>0,'2. Dimension Definition'!K21,'2. Dimension Definition'!J21) | I17: ='2. Dimension Definition'!L21 | K17: =IFERROR(__xludf.DUMMYFUNCTION("""COMPUTED_VALUE"""),6.0) -> 6 | L17: =IFERROR(__xludf.DUMMYFUNCTION("""COMPUTED_VALUE"""),"RL") -> RL | M17: =IFERROR(__xludf.DUMMYFUNCTION("""COMPUTED_VALUE"""),"Trajectory") -> Trajectory | N17: =IFERROR(__xludf.DUMMYFUNCTION("""COMPUTED_VALUE"""),"Tool Call Count") -> Tool Call Count | O17: =IFERROR(__xludf.DUMMYFUNCTION("""COMPUTED_VALUE""")," Important note for auditors: During the QH audits, this criterion should not be evaluated.") -> Important note for auditors: During the QH audits, this criterion should not be evaluated. | P17: =IFERROR(__xludf.DUMMYFUNCTION("""COMPUTED_VALUE"""),"[Fail - Insufficient Tool Calls] - All trajectories contains fewer than 30 tool calls") -> [Fail - Insufficient Tool Calls] - All trajectories contains fewer than 30 tool calls | Q17: =IFERROR(__xludf.DUMMYFUNCTION("""COMPUTED_VALUE"""),"[Non-Fail - Below Target Tool Calls] - At least one trajectory contains 30–39 tool calls. The task elicits broad exploration but falls slightly short of the 40-call complexity target.") -> [Non-Fail - Below Target Tool Calls] - At least one trajectory contains 30–39 tool calls. The task elicits broad exploration but falls slightly short of the 40-call complexity target. | R17: =IFERROR(__xludf.DUMMYFUNCTION("""COMPUTED_VALUE"""),"At least one trajectory contains 40+ tool calls, reflecting genuine cross-service investigation and action complexity.") -> At least one trajectory contains 40+ tool calls, reflecting genuine cross-service investigation and action complexity. | S17: =IFERROR(__xludf.DUMMYFUNCTION("""COMPUTED_VALUE"""),TRUE) -> TRUE
A18: ='2. Dimension Definition'!D21 | B18: ='2. Dimension Definition'!A22 | C18: ='2. Dimension Definition'!B22 | D18: ='2. Dimension Definition'!C22 | E18: =if(len('2. Dimension Definition'!E22)>0,'2. Dimension Definition'!E22,'2. Dimension Definition'!E22) | F18: =if(len('2. Dimension Definition'!G22)>0,'2. Dimension Definition'!G22,'2. Dimension Definition'!F22) | G18: =if(len('2. Dimension Definition'!I22)>0,'2. Dimension Definition'!I22,'2. Dimension Definition'!H22) | H18: =if(len('2. Dimension Definition'!K22)>0,'2. Dimension Definition'!K22,'2. Dimension Definition'!J22) | I18: ='2. Dimension Definition'!L22 | K18: =IFERROR(__xludf.DUMMYFUNCTION("""COMPUTED_VALUE"""),6.0) -> 6 | L18: =IFERROR(__xludf.DUMMYFUNCTION("""COMPUTED_VALUE"""),"RL") -> RL | M18: =IFERROR(__xludf.DUMMYFUNCTION("""COMPUTED_VALUE"""),"Trajectory") -> Trajectory | N18: =IFERROR(__xludf.DUMMYFUNCTION("""COMPUTED_VALUE"""),"Agent Failure Rate") -> Agent Failure Rate | O18: =IFERROR(__xludf.DUMMYFUNCTION("""COMPUTED_VALUE"""),"At least 4 of the agent runs need to fail the prompt. A failure is defined as the model failing at least one valid outcome rubric. Process rubric failures are not model failures.") -> At least 4 of the agent runs need to fail the prompt. A failure is defined as the model failing at least one valid outcome rubric. Process rubric failures are not model failures. | P18: =IFERROR(__xludf.DUMMYFUNCTION("""COMPUTED_VALUE"""),"[Fail - Too Easy] - More than 2 of 6 runs pass all valid outcome rubrics (i.e., pass@1 > 40%) ") -> [Fail - Too Easy] - More than 2 of 6 runs pass all valid outcome rubrics (i.e., pass@1 > 40%) | R18: =IFERROR(__xludf.DUMMYFUNCTION("""COMPUTED_VALUE"""),"0–2 of 6 runs pass all outcome rubrics (pass@1 ≤ 40%), proving the task is sufficiently difficult") -> 0–2 of 6 runs pass all outcome rubrics (pass@1 ≤ 40%), proving the task is sufficiently difficult | S18: =IFERROR(__xludf.DUMMYFUNCTION("""COMPUTED_VALUE"""),TRUE) -> TRUE
A19: ='2. Dimension Definition'!D22 | B19: ='2. Dimension Definition'!A23 | C19: ='2. Dimension Definition'!B23 | D19: ='2. Dimension Definition'!C23 | E19: =if(len('2. Dimension Definition'!E23)>0,'2. Dimension Definition'!E23,'2. Dimension Definition'!E23) | F19: =if(len('2. Dimension Definition'!G23)>0,'2. Dimension Definition'!G23,'2. Dimension Definition'!F23) | G19: =if(len('2. Dimension Definition'!I23)>0,'2. Dimension Definition'!I23,'2. Dimension Definition'!H23) | H19: =if(len('2. Dimension Definition'!K23)>0,'2. Dimension Definition'!K23,'2. Dimension Definition'!J23) | I19: ='2. Dimension Definition'!L23 | K19: =IFERROR(__xludf.DUMMYFUNCTION("""COMPUTED_VALUE"""),2.0) -> 2 | L19: =IFERROR(__xludf.DUMMYFUNCTION("""COMPUTED_VALUE"""),"RL") -> RL | M19: =IFERROR(__xludf.DUMMYFUNCTION("""COMPUTED_VALUE"""),"Prompt") -> Prompt | N19: =IFERROR(__xludf.DUMMYFUNCTION("""COMPUTED_VALUE"""),"Persona") -> Persona | O19: =IFERROR(__xludf.DUMMYFUNCTION("""COMPUTED_VALUE"""),"See the list of personas in the instructions doc or in the summary doc") -> See the list of personas in the instructions doc or in the summary doc | P19: =IFERROR(__xludf.DUMMYFUNCTION("""COMPUTED_VALUE"""),"[Fail - Persona Mismatch] The prompt written by the CB does not read like it could have been written by the persona selected. Note: Do not flag if you think the prompt suits a different persona, but rather only fail the task if the prompt cannot plausibly"&" be written by the persona selected.") -> [Fail - Persona Mismatch] The prompt written by the CB does not read like it could have been written by the persona selected. Note: Do not flag if you think the prompt suits a different persona, but rather only fail the task if the prompt cannot plausibly be written by the persona selected. | Q19: =IFERROR(__xludf.DUMMYFUNCTION("""COMPUTED_VALUE"""),"[Non-Fail - Persona Mismatch] The prompt written by the CB is plausible for the persona selected, but fits a different persona better") -> [Non-Fail - Persona Mismatch] The prompt written by the CB is plausible for the persona selected, but fits a different persona better | R19: =IFERROR(__xludf.DUMMYFUNCTION("""COMPUTED_VALUE"""),"The prompt written by the CB aligns with the persona selected") -> The prompt written by the CB aligns with the persona selected | S19: =IFERROR(__xludf.DUMMYFUNCTION("""COMPUTED_VALUE"""),TRUE) -> TRUE
A20: ='2. Dimension Definition'!D23 | B20: ='2. Dimension Definition'!A24 | C20: ='2. Dimension Definition'!B24 | D20: ='2. Dimension Definition'!C24 | E20: =if(len('2. Dimension Definition'!E24)>0,'2. Dimension Definition'!E24,'2. Dimension Definition'!E24) | F20: =if(len('2. Dimension Definition'!G24)>0,'2. Dimension Definition'!G24,'2. Dimension Definition'!F24) | G20: =if(len('2. Dimension Definition'!I24)>0,'2. Dimension Definition'!I24,'2. Dimension Definition'!H24) | H20: =if(len('2. Dimension Definition'!K24)>0,'2. Dimension Definition'!K24,'2. Dimension Definition'!J24) | I20: ='2. Dimension Definition'!L24
A21: ='2. Dimension Definition'!D24 | B21: ='2. Dimension Definition'!A25 | C21: ='2. Dimension Definition'!B25 | D21: ='2. Dimension Definition'!C25 | E21: =if(len('2. Dimension Definition'!E25)>0,'2. Dimension Definition'!E25,'2. Dimension Definition'!E25) | F21: =if(len('2. Dimension Definition'!G25)>0,'2. Dimension Definition'!G25,'2. Dimension Definition'!F25) | G21: =if(len('2. Dimension Definition'!I25)>0,'2. Dimension Definition'!I25,'2. Dimension Definition'!H25) | H21: =if(len('2. Dimension Definition'!K25)>0,'2. Dimension Definition'!K25,'2. Dimension Definition'!J25) | I21: ='2. Dimension Definition'!L25
A22: ='2. Dimension Definition'!D25 | B22: ='2. Dimension Definition'!A26 | C22: ='2. Dimension Definition'!B26 | D22: ='2. Dimension Definition'!C26 | E22: =if(len('2. Dimension Definition'!E26)>0,'2. Dimension Definition'!E26,'2. Dimension Definition'!E26) | F22: =if(len('2. Dimension Definition'!G26)>0,'2. Dimension Definition'!G26,'2. Dimension Definition'!F26) | G22: =if(len('2. Dimension Definition'!I26)>0,'2. Dimension Definition'!I26,'2. Dimension Definition'!H26) | H22: =if(len('2. Dimension Definition'!K26)>0,'2. Dimension Definition'!K26,'2. Dimension Definition'!J26) | I22: ='2. Dimension Definition'!L26
A23: ='2. Dimension Definition'!D26 | B23: ='2. Dimension Definition'!A27 | C23: ='2. Dimension Definition'!B27 | D23: ='2. Dimension Definition'!C27 | E23: =if(len('2. Dimension Definition'!E27)>0,'2. Dimension Definition'!E27,'2. Dimension Definition'!E27) | F23: =if(len('2. Dimension Definition'!G27)>0,'2. Dimension Definition'!G27,'2. Dimension Definition'!F27) | G23: =if(len('2. Dimension Definition'!I27)>0,'2. Dimension Definition'!I27,'2. Dimension Definition'!H27) | H23: =if(len('2. Dimension Definition'!K27)>0,'2. Dimension Definition'!K27,'2. Dimension Definition'!J27) | I23: ='2. Dimension Definition'!L27
A24: ='2. Dimension Definition'!D27 | B24: ='2. Dimension Definition'!A28 | C24: ='2. Dimension Definition'!B28 | D24: ='2. Dimension Definition'!C28 | E24: =if(len('2. Dimension Definition'!E28)>0,'2. Dimension Definition'!E28,'2. Dimension Definition'!E28) | F24: =if(len('2. Dimension Definition'!G28)>0,'2. Dimension Definition'!G28,'2. Dimension Definition'!F28) | G24: =if(len('2. Dimension Definition'!I28)>0,'2. Dimension Definition'!I28,'2. Dimension Definition'!H28) | H24: =if(len('2. Dimension Definition'!K28)>0,'2. Dimension Definition'!K28,'2. Dimension Definition'!J28) | I24: ='2. Dimension Definition'!L28
A25: ='2. Dimension Definition'!D28 | B25: ='2. Dimension Definition'!A29 | C25: ='2. Dimension Definition'!B29 | D25: ='2. Dimension Definition'!C29 | E25: =if(len('2. Dimension Definition'!E29)>0,'2. Dimension Definition'!E29,'2. Dimension Definition'!E29) | F25: =if(len('2. Dimension Definition'!G29)>0,'2. Dimension Definition'!G29,'2. Dimension Definition'!F29) | G25: =if(len('2. Dimension Definition'!I29)>0,'2. Dimension Definition'!I29,'2. Dimension Definition'!H29) | H25: =if(len('2. Dimension Definition'!K29)>0,'2. Dimension Definition'!K29,'2. Dimension Definition'!J29) | I25: ='2. Dimension Definition'!L29
A26: ='2. Dimension Definition'!D29 | B26: ='2. Dimension Definition'!A30 | C26: ='2. Dimension Definition'!B30 | D26: ='2. Dimension Definition'!C30 | E26: =if(len('2. Dimension Definition'!E30)>0,'2. Dimension Definition'!E30,'2. Dimension Definition'!E30) | F26: =if(len('2. Dimension Definition'!G30)>0,'2. Dimension Definition'!G30,'2. Dimension Definition'!F30) | G26: =if(len('2. Dimension Definition'!I30)>0,'2. Dimension Definition'!I30,'2. Dimension Definition'!H30) | H26: =if(len('2. Dimension Definition'!K30)>0,'2. Dimension Definition'!K30,'2. Dimension Definition'!J30) | I26: ='2. Dimension Definition'!L30
A27: ='2. Dimension Definition'!D30 | B27: ='2. Dimension Definition'!A31 | C27: ='2. Dimension Definition'!B31 | D27: ='2. Dimension Definition'!C31 | E27: =if(len('2. Dimension Definition'!E31)>0,'2. Dimension Definition'!E31,'2. Dimension Definition'!E31) | F27: =if(len('2. Dimension Definition'!G31)>0,'2. Dimension Definition'!G31,'2. Dimension Definition'!F31) | G27: =if(len('2. Dimension Definition'!I31)>0,'2. Dimension Definition'!I31,'2. Dimension Definition'!H31) | H27: =if(len('2. Dimension Definition'!K31)>0,'2. Dimension Definition'!K31,'2. Dimension Definition'!J31) | I27: ='2. Dimension Definition'!L31
A28: ='2. Dimension Definition'!D31 | B28: ='2. Dimension Definition'!A32 | C28: ='2. Dimension Definition'!B32 | D28: ='2. Dimension Definition'!C32 | E28: =if(len('2. Dimension Definition'!E32)>0,'2. Dimension Definition'!E32,'2. Dimension Definition'!E32) | F28: =if(len('2. Dimension Definition'!G32)>0,'2. Dimension Definition'!G32,'2. Dimension Definition'!F32) | G28: =if(len('2. Dimension Definition'!I32)>0,'2. Dimension Definition'!I32,'2. Dimension Definition'!H32) | H28: =if(len('2. Dimension Definition'!K32)>0,'2. Dimension Definition'!K32,'2. Dimension Definition'!J32) | I28: ='2. Dimension Definition'!L32
A29: ='2. Dimension Definition'!D32 | B29: ='2. Dimension Definition'!A33 | C29: ='2. Dimension Definition'!B33 | D29: ='2. Dimension Definition'!C33 | E29: =if(len('2. Dimension Definition'!E33)>0,'2. Dimension Definition'!E33,'2. Dimension Definition'!E33) | F29: =if(len('2. Dimension Definition'!G33)>0,'2. Dimension Definition'!G33,'2. Dimension Definition'!F33) | G29: =if(len('2. Dimension Definition'!I33)>0,'2. Dimension Definition'!I33,'2. Dimension Definition'!H33) | H29: =if(len('2. Dimension Definition'!K33)>0,'2. Dimension Definition'!K33,'2. Dimension Definition'!J33) | I29: ='2. Dimension Definition'!L33
A30: ='2. Dimension Definition'!D33 | B30: ='2. Dimension Definition'!A34 | C30: ='2. Dimension Definition'!B34 | D30: ='2. Dimension Definition'!C34 | E30: =if(len('2. Dimension Definition'!E34)>0,'2. Dimension Definition'!E34,'2. Dimension Definition'!E34) | F30: =if(len('2. Dimension Definition'!G34)>0,'2. Dimension Definition'!G34,'2. Dimension Definition'!F34) | G30: =if(len('2. Dimension Definition'!I34)>0,'2. Dimension Definition'!I34,'2. Dimension Definition'!H34) | H30: =if(len('2. Dimension Definition'!K34)>0,'2. Dimension Definition'!K34,'2. Dimension Definition'!J34) | I30: ='2. Dimension Definition'!L34
A31: ='2. Dimension Definition'!D34 | B31: ='2. Dimension Definition'!A35 | C31: ='2. Dimension Definition'!B35 | D31: ='2. Dimension Definition'!C35 | E31: =if(len('2. Dimension Definition'!E35)>0,'2. Dimension Definition'!E35,'2. Dimension Definition'!E35) | F31: =if(len('2. Dimension Definition'!G35)>0,'2. Dimension Definition'!G35,'2. Dimension Definition'!F35) | G31: =if(len('2. Dimension Definition'!I35)>0,'2. Dimension Definition'!I35,'2. Dimension Definition'!H35) | H31: =if(len('2. Dimension Definition'!K35)>0,'2. Dimension Definition'!K35,'2. Dimension Definition'!J35) | I31: ='2. Dimension Definition'!L35
... A35: ='2. Dimension Definition'!D38 | B35: ='2. Dimension Definition'!A39 | C35: ='2. Dimension Definition'!B39 | D35: ='2. Dimension Definition'!C39 | E35: =if(len('2. Dimension Definition'!E39)>0,'2. Dimension Definition'!E39,'2. Dimension Definition'!E39) | F35: =if(len('2. Dimension Definition'!G39)>0,'2. Dimension Definition'!G39,'2. Dimension Definition'!F39) | G35: =if(len('2. Dimension Definition'!I39)>0,'2. Dimension Definition'!I39,'2. Dimension Definition'!H39) | H35: =if(len('2. Dimension Definition'!K39)>0,'2. Dimension Definition'!K39,'2. Dimension Definition'!J39) | I35: ='2. Dimension Definition'!L39
A36: ='2. Dimension Definition'!D39 | B36: ='2. Dimension Definition'!A39 | C36: ='2. Dimension Definition'!B39 | D36: ='2. Dimension Definition'!C39 | F36: =if(len('2. Dimension Definition'!G39)>0,'2. Dimension Definition'!G39,'2. Dimension Definition'!F39) | G36: =if(len('2. Dimension Definition'!I39)>0,'2. Dimension Definition'!I39,'2. Dimension Definition'!H39) | H36: =if(len('2. Dimension Definition'!K39)>0,'2. Dimension Definition'!K39,'2. Dimension Definition'!J39) | I36: ='2. Dimension Definition'!L39
A37: ='2. Dimension Definition'!D40 | B37: ='2. Dimension Definition'!A40 | C37: ='2. Dimension Definition'!B40 | D37: ='2. Dimension Definition'!C40 | F37: =if(len('2. Dimension Definition'!G40)>0,'2. Dimension Definition'!G40,'2. Dimension Definition'!F40) | G37: =if(len('2. Dimension Definition'!I40)>0,'2. Dimension Definition'!I40,'2. Dimension Definition'!H40) | H37: =if(len('2. Dimension Definition'!K40)>0,'2. Dimension Definition'!K40,'2. Dimension Definition'!J40) | I37: ='2. Dimension Definition'!L40
A38: ='2. Dimension Definition'!D41 | B38: ='2. Dimension Definition'!A41 | C38: ='2. Dimension Definition'!B41 | D38: ='2. Dimension Definition'!C41 | F38: =if(len('2. Dimension Definition'!G41)>0,'2. Dimension Definition'!G41,'2. Dimension Definition'!F41) | G38: =if(len('2. Dimension Definition'!I41)>0,'2. Dimension Definition'!I41,'2. Dimension Definition'!H41) | H38: =if(len('2. Dimension Definition'!K41)>0,'2. Dimension Definition'!K41,'2. Dimension Definition'!J41) | I38: ='2. Dimension Definition'!L41
A39: ='2. Dimension Definition'!D42 | B39: ='2. Dimension Definition'!A42 | C39: ='2. Dimension Definition'!B42 | D39: ='2. Dimension Definition'!C42 | F39: =if(len('2. Dimension Definition'!G42)>0,'2. Dimension Definition'!G42,'2. Dimension Definition'!F42) | G39: =if(len('2. Dimension Definition'!I42)>0,'2. Dimension Definition'!I42,'2. Dimension Definition'!H42) | H39: =if(len('2. Dimension Definition'!K42)>0,'2. Dimension Definition'!K42,'2. Dimension Definition'!J42) | I39: ='2. Dimension Definition'!L42
A40: ='2. Dimension Definition'!D43 | B40: ='2. Dimension Definition'!A43 | C40: ='2. Dimension Definition'!B43 | D40: ='2. Dimension Definition'!C43 | F40: =if(len('2. Dimension Definition'!G43)>0,'2. Dimension Definition'!G43,'2. Dimension Definition'!F43) | G40: =if(len('2. Dimension Definition'!I43)>0,'2. Dimension Definition'!I43,'2. Dimension Definition'!H43) | H40: =if(len('2. Dimension Definition'!K43)>0,'2. Dimension Definition'!K43,'2. Dimension Definition'!J43) | I40: ='2. Dimension Definition'!L43
A41: ='2. Dimension Definition'!D44 | B41: ='2. Dimension Definition'!A44 | C41: ='2. Dimension Definition'!B44 | D41: ='2. Dimension Definition'!C44 | F41: =if(len('2. Dimension Definition'!G44)>0,'2. Dimension Definition'!G44,'2. Dimension Definition'!F44) | G41: =if(len('2. Dimension Definition'!I44)>0,'2. Dimension Definition'!I44,'2. Dimension Definition'!H44) | H41: =if(len('2. Dimension Definition'!K44)>0,'2. Dimension Definition'!K44,'2. Dimension Definition'!J44) | I41: ='2. Dimension Definition'!L44
A42: ='2. Dimension Definition'!D45 | B42: ='2. Dimension Definition'!A45 | C42: ='2. Dimension Definition'!B45 | D42: ='2. Dimension Definition'!C45 | F42: =if(len('2. Dimension Definition'!G45)>0,'2. Dimension Definition'!G45,'2. Dimension Definition'!F45) | G42: =if(len('2. Dimension Definition'!I45)>0,'2. Dimension Definition'!I45,'2. Dimension Definition'!H45) | H42: =if(len('2. Dimension Definition'!K45)>0,'2. Dimension Definition'!K45,'2. Dimension Definition'!J45) | I42: ='2. Dimension Definition'!L45
A43: ='2. Dimension Definition'!D46 | B43: ='2. Dimension Definition'!A46 | C43: ='2. Dimension Definition'!B46 | D43: ='2. Dimension Definition'!C46 | F43: =if(len('2. Dimension Definition'!G46)>0,'2. Dimension Definition'!G46,'2. Dimension Definition'!F46) | G43: =if(len('2. Dimension Definition'!I46)>0,'2. Dimension Definition'!I46,'2. Dimension Definition'!H46) | H43: =if(len('2. Dimension Definition'!K46)>0,'2. Dimension Definition'!K46,'2. Dimension Definition'!J46) | I43: ='2. Dimension Definition'!L46
A44: ='2. Dimension Definition'!D47 | B44: ='2. Dimension Definition'!A47 | C44: ='2. Dimension Definition'!B47 | D44: ='2. Dimension Definition'!C47 | F44: =if(len('2. Dimension Definition'!G47)>0,'2. Dimension Definition'!G47,'2. Dimension Definition'!F47) | G44: =if(len('2. Dimension Definition'!I47)>0,'2. Dimension Definition'!I47,'2. Dimension Definition'!H47) | H44: =if(len('2. Dimension Definition'!K47)>0,'2. Dimension Definition'!K47,'2. Dimension Definition'!J47) | I44: ='2. Dimension Definition'!L47
A45: ='2. Dimension Definition'!D48 | B45: ='2. Dimension Definition'!A48 | C45: ='2. Dimension Definition'!B48 | D45: ='2. Dimension Definition'!C48 | F45: =if(len('2. Dimension Definition'!G48)>0,'2. Dimension Definition'!G48,'2. Dimension Definition'!F48) | G45: =if(len('2. Dimension Definition'!I48)>0,'2. Dimension Definition'!I48,'2. Dimension Definition'!H48) | H45: =if(len('2. Dimension Definition'!K48)>0,'2. Dimension Definition'!K48,'2. Dimension Definition'!J48) | I45: ='2. Dimension Definition'!L48
A46: ='2. Dimension Definition'!D49 | B46: ='2. Dimension Definition'!A49 | C46: ='2. Dimension Definition'!B49 | D46: ='2. Dimension Definition'!C49 | F46: =if(len('2. Dimension Definition'!G49)>0,'2. Dimension Definition'!G49,'2. Dimension Definition'!F49) | G46: =if(len('2. Dimension Definition'!I49)>0,'2. Dimension Definition'!I49,'2. Dimension Definition'!H49) | H46: =if(len('2. Dimension Definition'!K49)>0,'2. Dimension Definition'!K49,'2. Dimension Definition'!J49) | I46: ='2. Dimension Definition'!L52 -> Complete
A47: ='2. Dimension Definition'!D53 -> 1 | B47: ='2. Dimension Definition'!A53 -> RL | C47: ='2. Dimension Definition'!B53 -> Prompt | D47: ='2. Dimension Definition'!C53 -> Feasibility | E47: =if(len('2. Dimension Definition'!E53)>0,'2. Dimension Definition'!E53,'2. Dimension Definition'!E25) | F47: ='2. Dimension Definition'!F53 -> [Fail - Prompt Impractical Request] - Prompt contains an impractical request that can't be answered by an LLM in a single response [Fail - Prompt Impossible Request] - Prompt has at least one request that can't be fulfilled at all [Fail - Prompt Conflicting Instructions] - Prompt gives instructions that conflict/contradict with itself that can't be fulfilled simultaneously [Fail - Prompt Feasibility with Tools] - Prompt contains an impractical or impossible request that can't be answered by the tools available or enabled for the task | G47: ='2. Dimension Definition'!H53 -> Non-Fail - Prompt Impractical Secondary Request] - There are multiple requests in the prompt and it's verging on being impractical for a model to answer it in a single response, but the core request of the prompt can be fulfilled with minor concessions on the secondary requests | H47: ='2. Dimension Definition'!J53 -> - The prompt is completely actionable by an LLM agent. - The prompt contains no conflicting instructions/statements | I47: ='2. Dimension Definition'!L53 -> TRUE
A48: ='2. Dimension Definition'!D54 -> 2 | B48: ='2. Dimension Definition'!A54 -> RL | C48: ='2. Dimension Definition'!B54 -> Prompt | D48: ='2. Dimension Definition'!C54 -> Tool use and Cross-service requirement | E48: =if(len('2. Dimension Definition'!E54)>0,'2. Dimension Definition'!E54,'2. Dimension Definition'!E26) | F48: ='2. Dimension Definition'!F54 -> [Fail - Tool Dependence] - The prompt can be answered without having to make any tool calls (either through basic reasoning or general knowledge) [Fail - Cross-service Requirement] - Prompt can be fully resolved within a single service (e.g., just email or just CRM), or only trivially touches a second service. | G48: ='2. Dimension Definition'!H54 -> N/A | H48: ='2. Dimension Definition'!J54 -> - Prompt requires investigation across 2+ services to answer correctly (e.g., facts needed are scattered and must be reconciled). | I48: ='2. Dimension Definition'!L54 -> TRUE
A49: ='2. Dimension Definition'!D55 -> 1 | B49: ='2. Dimension Definition'!A55 -> RL | C49: ='2. Dimension Definition'!B55 -> Prompt | D49: ='2. Dimension Definition'!C55 -> Explicit Tool Mention | E49: =if(len('2. Dimension Definition'!E55)>0,'2. Dimension Definition'!E55,'2. Dimension Definition'!E27) | F49: ='2. Dimension Definition'!F55 -> [Fail - Explicit Tool Mention] The prompt explicitly mentions a specific tool name The prompt unnaturally refers to an MCP server in an inorganic, technical manner “Use the Airbnb tool to…” (technical, unnatural) “I want to use Airbnb to find…” (general, natural) | G49: ='2. Dimension Definition'!H55 -> N/A | H49: ='2. Dimension Definition'!J55 -> - The prompt does not explicitly state the use of tools | I49: ='2. Dimension Definition'!L55 -> TRUE
A50: ='2. Dimension Definition'!D56 -> 2 | B50: ='2. Dimension Definition'!A56 -> RL | C50: ='2. Dimension Definition'!B56 -> Prompt | D50: ='2. Dimension Definition'!C56 -> Investigation + Action | E50: =if(len('2. Dimension Definition'!E56)>0,'2. Dimension Definition'!E56,'2. Dimension Definition'!E28) | F50: ='2. Dimension Definition'!F56 -> [Fail - Action Missing] - Prompt only asks for a summary/report/research with no required action. [Fail - Pre-solved] - Prompt tells agent the root cause and no investigation is needed. | G50: ='2. Dimension Definition'!H56 -> N/A | H50: ='2. Dimension Definition'!J56 -> Prompt clearly requires investigtion and at least one concrete action (email, ticket creation/update, booking, calendar scheduling, CRM update, etc.), and it logically follows from investigation. | I50: ='2. Dimension Definition'!L56 -> TRUE
A51: ='2. Dimension Definition'!D56 -> 2 | B51: ='2. Dimension Definition'!A56 -> RL | C51: ='2. Dimension Definition'!B56 -> Prompt | D51: ='2. Dimension Definition'!C56 -> Investigation + Action | E51: =if(len('2. Dimension Definition'!E56)>0,'2. Dimension Definition'!E56,'2. Dimension Definition'!E29) | F51: ='2. Dimension Definition'!F56 -> [Fail - Action Missing] - Prompt only asks for a summary/report/research with no required action. [Fail - Pre-solved] - Prompt tells agent the root cause and no investigation is needed. | G51: ='2. Dimension Definition'!H56 -> N/A | H51: ='2. Dimension Definition'!J56 -> Prompt clearly requires investigtion and at least one concrete action (email, ticket creation/update, booking, calendar scheduling, CRM update, etc.), and it logically follows from investigation. | I51: ='2. Dimension Definition'!L56 -> TRUE
A52: ='2. Dimension Definition'!D57 -> 2 | B52: ='2. Dimension Definition'!A57 -> RL | C52: ='2. Dimension Definition'!B57 -> Prompt | D52: ='2. Dimension Definition'!C57 -> Coherence | E52: =if(len('2. Dimension Definition'!E57)>0,'2. Dimension Definition'!E57,'2. Dimension Definition'!E30) -> An example of failing bolt-on requests: "Check weather in Miami, update my calendar for next week, email Marcus about Q3, and look up Seattle flights." Why it fails: Four unrelated requests stapled together. Each sub-request should causally flow from the same situation. How to tell if your prompt is "bolted": Remove any one sentence. If the rest still makes perfect sense without it, that sentence is a bolt-on | F52: ='2. Dimension Definition'!F57 -> [Fail - Bolt-on requests] - Contains unrelated bolt-on requests; removing a sentence doesn’t change the rest. | G52: ='2. Dimension Definition'!H57 -> N/A | H52: ='2. Dimension Definition'!J57 -> One cohesive situation; stacked asks all tie back to the same purpose. | I52: ='2. Dimension Definition'!L57 -> TRUE
A53: ='2. Dimension Definition'!D58 -> 3 | B53: ='2. Dimension Definition'!A58 -> RL | C53: ='2. Dimension Definition'!B58 -> Universe | D53: ='2. Dimension Definition'!C58 -> Universe Feasibility (Data Exists) | E53: =if(len('2. Dimension Definition'!E58)>0,'2. Dimension Definition'!E58,'2. Dimension Definition'!E31) -> Auditors should check the Universe Explorer or Sandbox to verify that key data needed for the prompt exists. | F53: ='2. Dimension Definition'!F58 -> [Fail - Missing Universe Data] - Task depends on key facts/entities/events that do not exist in the universe (or cannot be retrieved with available tools), making the task unsolvable. | G53: ='2. Dimension Definition'!H58 -> N/A | H53: ='2. Dimension Definition'!J58 -> All core facts required to solve the task exist in the universe and are retrievable via tools. | I53: ='2. Dimension Definition'!L58 -> TRUE
A54: ='2. Dimension Definition'!D59 -> 3 | B54: ='2. Dimension Definition'!A59 -> RL | C54: ='2. Dimension Definition'!B59 -> Universe | D54: ='2. Dimension Definition'!C59 -> Cross-service Coherence | E54: =if(len('2. Dimension Definition'!E59)>0,'2. Dimension Definition'!E59,'2. Dimension Definition'!E32) -> Auditors should refer to the changelog table in the sandbox to check changes that were made to the universe (if edits were made). | F54: ='2. Dimension Definition'!F59 -> [Fail - Incoherent Universe Changes] - Universe edits create contradictions that break solvability or realism (e.g., mismatched names across email vs CRM, impossible dates, entities referenced in one service but not elsewhere when required). Note: When evaluating a contradiction, if there is sufficient supporting evidence to support one piece of information against a contradicting low-supported piece of information, do not count that as a contradiction. | G54: ='2. Dimension Definition'!H59 | H54: ='2. Dimension Definition'!J59 -> Universe edits (if any) are internally consistent and coherent across services, including dates, names, and storyline continuity. | I54: ='2. Dimension Definition'!L59 -> TRUE
A55: ='2. Dimension Definition'!D60 -> 4 | B55: ='2. Dimension Definition'!A60 -> RL | C55: ='2. Dimension Definition'!B60 -> Oracle Events (OEs) | D55: ='2. Dimension Definition'!C60 -> OE Accuracy | E55: =if(len('2. Dimension Definition'!E60)>0,'2. Dimension Definition'!E60,'2. Dimension Definition'!E33) -> Auditors should verify OEs against the universe data using the Explorer or Sandbox. Each OE should reference the correct tool, correct service, correct parameters, and correct expected data. An OE that describes "look up Fatimah's relocations in Linear" when relocation records are actually in the CRM is inaccurate — the data exists but the OE points to the wrong place. OE Accuracy is distinct from OE Completeness: completeness checks whether steps are missing; accuracy checks whether the steps that exist are correct. | F55: ='2. Dimension Definition'!F60 -> N/A | G55: ='2. Dimension Definition'!H60 -> [Non-Fail - Minor OE Inaccuracies] OEs are substantively correct but contain minor imprecisions (e.g., slightly wrong parameter name that doesn't change the outcome, approximate rather than exact expected values for freetext fields). [Non-Fail - Inaccurate Oracle Events] One or more OEs reference the wrong tool, wrong service, wrong parameters, or wrong expected data. The described steps would not produce the correct results if followed literally (e.g., searching the wrong service for data that lives elsewhere, expecting data that doesn't match the universe, specifying incorrect entity names or identifiers). | H55: ='2. Dimension Definition'!J60 -> All OEs are factually accurate. Tools, services, parameters, and expected data match the universe. Following the OEs literally would produce a correct trajectory. | I55: ='2. Dimension Definition'!L60 -> TRUE
A56: ='2. Dimension Definition'!D61 -> 4 | B56: ='2. Dimension Definition'!A61 -> RL | C56: ='2. Dimension Definition'!B61 -> Oracle Events (OEs) | D56: ='2. Dimension Definition'!C61 -> OE Completeness | E56: =if(len('2. Dimension Definition'!E61)>0,'2. Dimension Definition'!E61,'2. Dimension Definition'!E33) -> Additional Notes: OEs are the key steps a correct agent would take. They serve two purposes: (1) prove solvability, and (2) generate TS and QC rubrics. Each OE should note: what action happens, what info is discovered, what tool is used, and what parameters matter. OEs describe tool-use steps — not what the final response should say. | F56: ='2. Dimension Definition'!F61 -> N/A | G56: ='2. Dimension Definition'!H61 -> [Non-Fail - Incomplete Oracle Events] - OEs are missing critical steps needed to solve the task (e.g., no step describing how key info is retrieved, or how required action is executed). | H56: ='2. Dimension Definition'!J61 -> OEs describe the full critical path: key discovery steps + dependency chain(s) + required write action(s). | I56: ='2. Dimension Definition'!L61 -> TRUE
A57: ='2. Dimension Definition'!D62 -> 5 | B57: ='2. Dimension Definition'!A62 -> RL | C57: ='2. Dimension Definition'!B62 -> Rubrics | D57: ='2. Dimension Definition'!C62 -> Overall Rubric Quality | E57: =if(len('2. Dimension Definition'!E62)>0,'2. Dimension Definition'!E62,'2. Dimension Definition'!E34) | F57: ='2. Dimension Definition'!F62 -> Use the number of criteria that the CB wrote as the denominator while calculating % values. See the additional notes section for the numerator. Do NOT double count criteria while tallying even if it has multiple issues. [Fail - 10%+ Major Rubric Errors] More than 10% (>10%) of the criteria contain major issues [Fail - 15%+ Moderate Rubric Errors] More than 15% (>15%) of the criteria contain moderate or major issues [Fail - 20%+ Minor Rubric Errors] More than 20% (>20%) of the criteria contain minor or moderate or major issues | G57: ='2. Dimension Definition'!H62 -> [Non-Fail - Up to 10% Major Errors] Up to 10% (<=10%) of the criteria contain major issues [Non-Fail - Up to 15% Moderate Errors] Up to 15% (<=15%) of criteria contain moderate or major issues (with major issues contributing lower than 5%) [Non-Fail - 5-20% Minor Errors] Between 5 and 20% (>=5% and <=20%) of criteria contain minor or moderate or major issues (with major issues contributing lower than 5% and moderate issues contributing lower than 15%) | H57: ='2. Dimension Definition'!J62 -> - Less than 5% (<5%) of the rubrics have minor issues - No major or moderate issues | I57: ='2. Dimension Definition'!L62 -> TRUE
A58: ='2. Dimension Definition'!D63 -> 5 | B58: ='2. Dimension Definition'!A63 -> RL | C58: ='2. Dimension Definition'!B63 -> Rubrics | D58: ='2. Dimension Definition'!C63 -> Rubric Category Balance | E58: =if(len('2. Dimension Definition'!E63)>0,'2. Dimension Definition'!E63,'2. Dimension Definition'!E35) -> Outcome rubrics check final correctness (was the result right?). Process rubrics = Tool Selection + Query Construction (did the agent use the right tools with the right parameters?). Target ratio is approximately 80% Outcome, 20% Process. | F58: ='2. Dimension Definition'!F63 -> [Fail - No Outcome Rubrics] - The rubric set contains zero Outcome rubrics. [Fail - Process-Heavy] - More than 50% of rubrics are Process (Tool Selection + Query Construction), with Outcome rubrics underrepresented. [Fail - Missing Grounding Check] Investigation-heavy task has no grounding-check rubric verifying the agent retrieved data before reporting it. | G58: ='2. Dimension Definition'!H63 | H58: ='2. Dimension Definition'!J63 -> Approximately 80% or more of rubrics are Outcome. Process rubrics (TS + QC) are present but limited to critical oracle-event steps. | I58: ='2. Dimension Definition'!L63 -> TRUE
A59: ='2. Dimension Definition'!D64 -> 6 | B59: ='2. Dimension Definition'!A64 -> RL | C59: ='2. Dimension Definition'!B64 -> Trajectory | D59: ='2. Dimension Definition'!C64 -> Tool Call Count | E59: =if(len('2. Dimension Definition'!E64)>0,'2. Dimension Definition'!E64,'2. Dimension Definition'!E35) -> Important note for auditors: During the QH audits, this criterion should not be evaluated. | F59: ='2. Dimension Definition'!F64 -> [Fail - Insufficient Tool Calls] - All trajectories contains fewer than 30 tool calls | G59: ='2. Dimension Definition'!H64 -> [Non-Fail - Below Target Tool Calls] - At least one trajectory contains 30–39 tool calls. The task elicits broad exploration but falls slightly short of the 40-call complexity target. | H59: ='2. Dimension Definition'!J64 -> At least one trajectory contains 40+ tool calls, reflecting genuine cross-service investigation and action complexity. | I59: ='2. Dimension Definition'!L64 -> TRUE
A60: ='2. Dimension Definition'!D65 -> 6 | B60: ='2. Dimension Definition'!A65 -> RL | C60: ='2. Dimension Definition'!B65 -> Trajectory | D60: ='2. Dimension Definition'!C65 -> Agent Failure Rate | E60: =if(len('2. Dimension Definition'!E65)>0,'2. Dimension Definition'!E65,'2. Dimension Definition'!E36) -> At least 4 of the agent runs need to fail the prompt. A failure is defined as the model failing at least one valid outcome rubric. Process rubric failures are not model failures. | F60: ='2. Dimension Definition'!F65 -> [Fail - Too Easy] - More than 2 of 6 runs pass all valid outcome rubrics (i.e., pass@1 > 40%) | G60: ='2. Dimension Definition'!H65 | H60: ='2. Dimension Definition'!J65 -> 0–2 of 6 runs pass all outcome rubrics (pass@1 ≤ 40%), proving the task is sufficiently difficult | I60: ='2. Dimension Definition'!L65 -> TRUE
A61: ='2. Dimension Definition'!D66 -> 2 | B61: ='2. Dimension Definition'!A66 -> RL | C61: ='2. Dimension Definition'!B66 -> Prompt | D61: ='2. Dimension Definition'!C66 -> Persona | E61: =if(len('2. Dimension Definition'!E66)>0,'2. Dimension Definition'!E66,'2. Dimension Definition'!E37) -> See the list of personas in the instructions doc or in the summary doc | F61: ='2. Dimension Definition'!F66 -> [Fail - Persona Mismatch] The prompt written by the CB does not read like it could have been written by the persona selected. Note: Do not flag if you think the prompt suits a different persona, but rather only fail the task if the prompt cannot plausibly be written by the persona selected. | G61: ='2. Dimension Definition'!H66 -> [Non-Fail - Persona Mismatch] The prompt written by the CB is plausible for the persona selected, but fits a different persona better | H61: ='2. Dimension Definition'!J66 -> The prompt written by the CB aligns with the persona selected | I61: ='2. Dimension Definition'!L66 -> TRUE
A62: ='2. Dimension Definition'!D67 | B62: ='2. Dimension Definition'!A67 | C62: ='2. Dimension Definition'!B67 | D62: ='2. Dimension Definition'!C67 | E62: =if(len('2. Dimension Definition'!E67)>0,'2. Dimension Definition'!E67,'2. Dimension Definition'!E38) | F62: ='2. Dimension Definition'!F67 | G62: ='2. Dimension Definition'!H67 | H62: ='2. Dimension Definition'!J67 | I62: ='2. Dimension Definition'!L67
A63: ='2. Dimension Definition'!D68 | B63: ='2. Dimension Definition'!A68 | C63: ='2. Dimension Definition'!B68 | D63: ='2. Dimension Definition'!C68 | E63: =if(len('2. Dimension Definition'!E68)>0,'2. Dimension Definition'!E68,'2. Dimension Definition'!E39) | F63: ='2. Dimension Definition'!F68 | G63: ='2. Dimension Definition'!H68 | H63: ='2. Dimension Definition'!J68 | I63: ='2. Dimension Definition'!L68
A64: ='2. Dimension Definition'!D69 | B64: ='2. Dimension Definition'!A69 | C64: ='2. Dimension Definition'!B69 | D64: ='2. Dimension Definition'!C69 | E64: =if(len('2. Dimension Definition'!E69)>0,'2. Dimension Definition'!E69,'2. Dimension Definition'!E40) | F64: ='2. Dimension Definition'!F69 | G64: ='2. Dimension Definition'!H69 | H64: ='2. Dimension Definition'!J69 | I64: ='2. Dimension Definition'!L69
A65: ='2. Dimension Definition'!D70 | B65: ='2. Dimension Definition'!A70 | C65: ='2. Dimension Definition'!B70 | D65: ='2. Dimension Definition'!C70 | E65: =if(len('2. Dimension Definition'!E70)>0,'2. Dimension Definition'!E70,'2. Dimension Definition'!E41) | F65: ='2. Dimension Definition'!F70 | G65: ='2. Dimension Definition'!H70 | H65: ='2. Dimension Definition'!J70 | I65: ='2. Dimension Definition'!L70
A66: ='2. Dimension Definition'!D71 | B66: ='2. Dimension Definition'!A71 | C66: ='2. Dimension Definition'!B71 | D66: ='2. Dimension Definition'!C71 | E66: =if(len('2. Dimension Definition'!E71)>0,'2. Dimension Definition'!E71,'2. Dimension Definition'!E42) | F66: ='2. Dimension Definition'!F71 | G66: ='2. Dimension Definition'!H71 | H66: ='2. Dimension Definition'!J71 | I66: ='2. Dimension Definition'!L71
A67: ='2. Dimension Definition'!D72 | B67: ='2. Dimension Definition'!A72 | C67: ='2. Dimension Definition'!B72 | D67: ='2. Dimension Definition'!C72 | E67: =if(len('2. Dimension Definition'!E72)>0,'2. Dimension Definition'!E72,'2. Dimension Definition'!E43) | F67: ='2. Dimension Definition'!F72 | G67: ='2. Dimension Definition'!H72 | H67: ='2. Dimension Definition'!J72 | I67: ='2. Dimension Definition'!L72
A68: ='2. Dimension Definition'!D73 | B68: ='2. Dimension Definition'!A73 | C68: ='2. Dimension Definition'!B73 | D68: ='2. Dimension Definition'!C73 | E68: =if(len('2. Dimension Definition'!E73)>0,'2. Dimension Definition'!E73,'2. Dimension Definition'!E44) | F68: ='2. Dimension Definition'!F73 | G68: ='2. Dimension Definition'!H73 | H68: ='2. Dimension Definition'!J73 | I68: ='2. Dimension Definition'!L73
A69: ='2. Dimension Definition'!D74 | B69: ='2. Dimension Definition'!A74 | C69: ='2. Dimension Definition'!B74 | D69: ='2. Dimension Definition'!C74 | E69: =if(len('2. Dimension Definition'!E74)>0,'2. Dimension Definition'!E74,'2. Dimension Definition'!E45) | F69: ='2. Dimension Definition'!F74 | G69: ='2. Dimension Definition'!H74 | H69: ='2. Dimension Definition'!J74 | I69: ='2. Dimension Definition'!L74
A70: ='2. Dimension Definition'!D75 | B70: ='2. Dimension Definition'!A75 | C70: ='2. Dimension Definition'!B75 | D70: ='2. Dimension Definition'!C75 | E70: =if(len('2. Dimension Definition'!E75)>0,'2. Dimension Definition'!E75,'2. Dimension Definition'!E46) | F70: ='2. Dimension Definition'!F75 | G70: ='2. Dimension Definition'!H75 | H70: ='2. Dimension Definition'!J75 | I70: ='2. Dimension Definition'!L75
... A79: ='2. Dimension Definition'!D84 | B79: ='2. Dimension Definition'!A84 | C79: ='2. Dimension Definition'!B84 | D79: ='2. Dimension Definition'!C84 | E79: =if(len('2. Dimension Definition'!E84)>0,'2. Dimension Definition'!E84,'2. Dimension Definition'!E55) | F79: ='2. Dimension Definition'!F84 | G79: ='2. Dimension Definition'!H84 | H79: ='2. Dimension Definition'!J84 | I79: ='2. Dimension Definition'!L84
A80: ='2. Dimension Definition'!D85 | B80: ='2. Dimension Definition'!A85 | C80: ='2. Dimension Definition'!B85 | D80: ='2. Dimension Definition'!C85 | E80: =if(len('2. Dimension Definition'!E85)>0,'2. Dimension Definition'!E85,#REF!) -> #REF! | F80: ='2. Dimension Definition'!F85 | G80: ='2. Dimension Definition'!H85 | H80: ='2. Dimension Definition'!J85 | I80: ='2. Dimension Definition'!L85
A81: ='2. Dimension Definition'!D86 | B81: ='2. Dimension Definition'!A86 | C81: ='2. Dimension Definition'!B86 | D81: ='2. Dimension Definition'!C86 | E81: =if(len('2. Dimension Definition'!E86)>0,'2. Dimension Definition'!E86,'2. Dimension Definition'!E56) | F81: ='2. Dimension Definition'!F86 | G81: ='2. Dimension Definition'!H86 | H81: ='2. Dimension Definition'!J86 | I81: ='2. Dimension Definition'!L86
A82: ='2. Dimension Definition'!D87 | B82: ='2. Dimension Definition'!A87 | C82: ='2. Dimension Definition'!B87 | D82: ='2. Dimension Definition'!C87 | E82: =if(len('2. Dimension Definition'!E87)>0,'2. Dimension Definition'!E87,'2. Dimension Definition'!E57) -> An example of failing bolt-on requests: "Check weather in Miami, update my calendar for next week, email Marcus about Q3, and look up Seattle flights." Why it fails: Four unrelated requests stapled together. Each sub-request should causally flow from the same situation. How to tell if your prompt is "bolted": Remove any one sentence. If the rest still makes perfect sense without it, that sentence is a bolt-on | F82: ='2. Dimension Definition'!F87 | G82: ='2. Dimension Definition'!H87 | H82: ='2. Dimension Definition'!J87 | I82: ='2. Dimension Definition'!L87
A83: ='2. Dimension Definition'!D88 | B83: ='2. Dimension Definition'!A88 | C83: ='2. Dimension Definition'!B88 | D83: ='2. Dimension Definition'!C88 | E83: =if(len('2. Dimension Definition'!E88)>0,'2. Dimension Definition'!E88,'2. Dimension Definition'!E58) -> Auditors should check the Universe Explorer or Sandbox to verify that key data needed for the prompt exists. | F83: ='2. Dimension Definition'!F88 | G83: ='2. Dimension Definition'!H88 | H83: ='2. Dimension Definition'!J88 | I83: ='2. Dimension Definition'!L88
A84: ='2. Dimension Definition'!D89 | B84: ='2. Dimension Definition'!A89 | C84: ='2. Dimension Definition'!B89 | D84: ='2. Dimension Definition'!C89 | E84: =if(len('2. Dimension Definition'!E89)>0,'2. Dimension Definition'!E89,'2. Dimension Definition'!E59) -> Auditors should refer to the changelog table in the sandbox to check changes that were made to the universe (if edits were made). | F84: ='2. Dimension Definition'!F89 | G84: ='2. Dimension Definition'!H89 | H84: ='2. Dimension Definition'!J89 | I84: ='2. Dimension Definition'!L89
A85: ='2. Dimension Definition'!D90 | B85: ='2. Dimension Definition'!A90 | C85: ='2. Dimension Definition'!B90 | D85: ='2. Dimension Definition'!C90 | E85: =if(len('2. Dimension Definition'!E90)>0,'2. Dimension Definition'!E90,'2. Dimension Definition'!E61) -> Additional Notes: OEs are the key steps a correct agent would take. They serve two purposes: (1) prove solvability, and (2) generate TS and QC rubrics. Each OE should note: what action happens, what info is discovered, what tool is used, and what parameters matter. OEs describe tool-use steps — not what the final response should say. | F85: ='2. Dimension Definition'!F90 | G85: ='2. Dimension Definition'!H90 | H85: ='2. Dimension Definition'!J90 | I85: ='2. Dimension Definition'!L90
A86: ='2. Dimension Definition'!D91 | B86: ='2. Dimension Definition'!A91 | C86: ='2. Dimension Definition'!B91 | D86: ='2. Dimension Definition'!C91 | E86: =if(len('2. Dimension Definition'!E91)>0,'2. Dimension Definition'!E91,'2. Dimension Definition'!E62) | F86: ='2. Dimension Definition'!F91 | G86: ='2. Dimension Definition'!H91 | H86: ='2. Dimension Definition'!J91 | I86: ='2. Dimension Definition'!L91
B87: ='2. Dimension Definition'!A92 | C87: ='2. Dimension Definition'!B92 | D87: ='2. Dimension Definition'!C92 | F87: ='2. Dimension Definition'!F92 | G87: ='2. Dimension Definition'!H92 | H87: ='2. Dimension Definition'!J92 | I87: ='2. Dimension Definition'!L89
B88: ='2. Dimension Definition'!A93 | C88: ='2. Dimension Definition'!B93 | D88: ='2. Dimension Definition'!C93 | F88: ='2. Dimension Definition'!F93 | G88: ='2. Dimension Definition'!H93 | H88: ='2. Dimension Definition'!J93 | I88: ='2. Dimension Definition'!L90
